Workbook

Sheet Forecasted January 2021
E4: Diverse Costs | F4: Difference | G4: Forecasted Full 2020/2021 | H4: 2020/2021 (Incomplete) | I4: 2019/2020 | J4: 2018/2019
E5: Bank costs | F5: =G5-H5 -> 750.798 | G5: =H5*1.3 -> 3253.458 | H5: 2502.66 | I5: 1266.21 | J5: 5090.79
E6: Bemarkingskostes | F6: =G6-H6 -> -12656.62 | H6: 12656.62 | I6: 10357.33 | J6: 26518.21
E7: Bemesting and Gifstowwe | F7: =G7-H7 -> 355727.28 | G7: =H7*2 -> 711454.56 | H7: 355727.28 | I7: 415528.13 | J7: 674535.45
E8: Protective Clothing | F8: =G8-H8 -> 6480 | G8: =H8*5 -> 8100 | H8: 1620 | I8: 1595.02 | J8: 1563.9
E9: Diesel | F9: =G9-H9 -> 266965.1 | G9: =H9*2 -> 533930.2 | H9: 266965.1 | I9: 524450.34 | J9: 567176.87
E10: Skryfbehoeftes | F10: =G10-H10 -> 613.321 | G10: =H10*1.1 -> 6746.531 | H10: 6133.21 | I10: 6606.09 | J10: 8026.86
C11: =G11 -> 47107.52 | D11: 1 | E11: Electricity | F11: =G11-H11 -> 1193.18 | G11: =I11 -> 47107.52 | H11: 45914.34 | I11: 47107.52 | J11: 41678.31
E12: Erfelasting | F12: =G12-H12 -> 6782.38 | G12: =J12 -> 6782.38 | I12: 3615.84 | J12: 6782.38
E13: Finansieringskostes | F13: =G13-H13 -> -1015.12 | G13: =J13 -> 1228.67 | H13: 2243.79 | I13: 1624.65 | J13: 1228.67
E14: Huurbetaal | F14: =G14-H14 -> #REF! | G14: =I14 -> 178428.08 | H14: =Sheet1!B215 -> #REF! | I14: 178428.08 | J14: 174034.59
E15: Instandhouding - Besproeing | F15: =G15-H15 -> #REF! | G15: 10000 | H15: =Sheet1!B220 -> #REF! | I15: -26646.98 | J15: 66888
C16: =G16 -> 1016373.6 | D16: 1 | E16: Instandhouding - Implemente en Toerusting | F16: =G16-H16 -> 0 | G16: =H16 -> 1016373.6 | H16: 1016373.6 | I16: 1076544.6 | J16: 997009.07
C17: =G17 -> 24000 | D17: 1 | E17: Kommunikasiekostes - Selluler | F17: =G17-H17 -> 13816 | G17: 24000 | H17: 10184 | I17: 13930.17
E18: Kommunikasiekostes - Posgeld | F18: =G18-H18 -> 0 | I18: 26552.18 | J18: 430.43
C19: =G19 -> 13043.48 | D19: 1 | E19: Kommunikasiekostes - Internet | F19: =G19-H19 -> 0 | G19: =H19 -> 13043.48 | H19: 13043.48 | J19: 368.42
C20: =G20 -> 13043.48 | D20: 1 | E20: Kommunikasiekostes - Telefoon | F20: =G20-H20 -> 0 | G20: =H20 -> 13043.48 | H20: 13043.48 | I20: 32340.95 | J20: 7041.85
C21: =G21 -> 15354.72 | D21: 1 | E21: Ledegelde | F21: =G21-H21 -> 0 | G21: =H21 -> 15354.72 | H21: 15354.72 | I21: 7945.75 | J21: 7524.03
C22: =G22 -> #REF! | D22: 1 | E22: Lisensies | F22: =G22-H22 -> #REF! | G22: =H22 -> #REF! | H22: =Sheet1!B346 -> #REF! | I22: 19248 | J22: 16597.97
E23: Oesdeel | F23: =G23-H23 -> 300000 | G23: 300000 | I23: 778171.02 | J23: 1105670.2
C24: =G24 -> 110000 | D24: 1 | E24: Oeskoste van Druiwe | F24: =G24-H24 -> 110000 | G24: 110000 | I24: 39000 | J24: 112294.5
E25: Regskostes- Skuldinvordering | F25: =G25-H25 -> #REF! | G25: =H25 -> #REF! | H25: =Sheet1!B354 -> #REF! | I25: 743.48
E26: Regskostes- Kapitale uitgawes | F26: =G26-H26 -> 0 | G26: =H26 | J26: 297.39
E27: Reis en Verblyf: Plaaslik | F27: =G27-H27 -> 0 | G27: =H27 | I27: 9000 | J27: 12000
E28: Reis en Verblyf: Buiteland | F28: =G28-H28 -> 0 | G28: =H28 | J28: 4538.63
E29: Rekenmeestergelde | F29: =G29-H29 -> 15178.03 | G29: =I29 -> 39008.03 | H29: 23830 | I29: 39008.03 | J29: 41340.7 | M29: Forecasted
E30: Saad & Plantmateriaal | F30: =G30-H30 -> #REF! | G30: =H30 -> #REF! | H30: =Sheet1!B376 -> #REF! | I30: 10200 | K30: =SUM(H31:H37) -> #REF! | L30: S&L 2020 | M30: =K30*1.5 -> #REF! | N30: S&L Full 2020
C31: =G31 -> 100000 | D31: 1 | E31: S & L - Salarisse | F31: =G31-H31 -> 19793 | G31: 100000 | H31: 80207 | I31: 147324.36 | J31: 49944.56 | K31: =SUM(I31:I37) -> 2820749 | L31: S&L 2019
C32: =G32 -> 700000 | D32: 1 | E32: S & L - Lone | F32: =G32-H32 -> 150666.04 | G32: 700000 | H32: 549333.96 | I32: 1874669.3 | J32: 1251680.1 | K32: =SUM(J31:J37) -> 1721624.6 | L32: S&L 2018 | M32: =1313687.94/200000 -> 6.5684397
C33: =G33 -> #REF! | D33: 1 | E33: S & L - Werkloosheidsversekering | F33: =G33-H33 -> #REF! | G33: =0.015*M30 -> #REF! | H33: =Sheet1!B505 -> #REF! | I33: 14582 | J33: 28119.56
C34: =G34 -> 450000 | D34: 1 | E34: S & L - Rantsoene | F34: =G34-H34 -> 53345.77 | G34: 450000 | H34: 396654.23 | I34: 718768.19 | J34: 362884.46 | K34: =K32*0.015 -> 25824.37
C35: =G35 -> 20000 | D35: 1 | E35: S & L - Personeelvoordele | F35: =G35-H35 -> 4066.77 | G35: 20000 | H35: 15933.23 | I35: 47459.5 | J35: 23395.94
C36: =G36 -> 102691.92 | D36: 1 | E36: S & L - Teesaad | F36: =G36-H36 -> 10000 | G36: =H36+10000 -> 102691.92 | H36: 92691.92 | I36: 17945.61 | J36: 5600 | K36: =SUM(G31:G37) -> #REF!
C37: =G37 | D37: 1 | E37: S & L - Ongevalleversekering | F37: =G37-H37 -> #REF! | H37: =Sheet1!B566 -> #REF!
E38: Sekuriteit | F38: =G38-H38 -> #REF! | G38: 4000 | H38: =Sheet1!B585 -> #REF! | I38: 2466.44 | J38: 31195.13 | K38: =K36-K30 -> #REF!
C39: =G39 -> 16000 | D39: 1 | E39: Veemedisyne en -doserings | F39: =G39-H39 -> -3023.99 | G39: 16000 | H39: 19023.99 | I39: 20059.27 | J39: 4006.57
E40: Veevoer | F40: =G40-H40 -> 4000 | G40: =H40+4000 -> 165397.1 | H40: 161397.1 | I40: 79496.69 | J40: 28508.16
E41: Verbeteringe - Aanplantings en opleiding | F41: =G41-H41 -> 0 | G41: =H41 | I41: 463250.86 | J41: -126537.2
E42: Verbeteringe - Geboue | F42: =G42-H42 -> 10000 | G42: 10000 | I42: 504906.93
E43: Verpakkingsmateriaal | F43: =G43-H43 -> 10000 | G43: 10000 | I43: 9385.6 | J43: 8888.35
C44: =G44 -> 184403.61 | D44: 1 | E44: Versekering | F44: =G44-H44 -> 33878.08 | G44: =I44 -> 184403.61 | H44: 150525.53 | I44: 184403.61 | J44: 160923.73
E45: Vervoerkostes | F45: =G45-H45 -> #REF! | G45: =H45+20000 -> #REF! | H45: =Sheet1!B646 -> #REF! | I45: 35990.21 | J45: 263625.93
E46: Waterbelasting | F46: =G46-H46 -> #REF! | G46: =H46+50000 -> #REF! | H46: =Sheet1!B651 -> #REF! | I46: 2220.96 | J46: 221688.05
C47: =SUM(C5:C46) -> #REF! | E47: Total | F47: =SUM(F5:F46) -> #REF! | G47: =SUM(G5:G46) -> #REF! | H47: =SUM(H5:H46) -> #REF! | I47: =SUM(I5:I46) -> 7339546 | J47: =SUM(J5:J46) -> 6192560.6
E49: Income
E50: Sales: Tea | F50: =G50-H50 -> -2580000 | G50: =H50-80000-2500000 -> 5782455.9 | H50: 8362455.9 | I50: -12969518 | J50: -18526229
E51: Sales: Wol | F51: =G51-H51 -> 0 | G51: =H51 -> 314869.76 | H51: 314869.76 | I51: -130909.65 | J51: -210879.25
E52: Sales: Wyn | G52: =H52 -> 869417.2 | H52: =869417.2 -> 869417.2 | I52: -753387 | J52: -800800
E53: Sales: Livestock | F53: =G53-H53 -> 0 | G53: =H53 | I53: -92102.2 | J53: 5497615.3
E54: Interest Received | F54: =G54-H54 -> -10000 | G54: =-10000 -> -10000 | I54: -38631.25
E55: Dividend Received | F55: =G55-H55 -> 0 | J55: -4299.23
E56: Verkoop van nie-bedryfsbate | F56: =G56-H56 -> 0 | J56: -205000
E57: Diverse Income | G57: =H57 -> #REF! | H57: =Sheet1!B75 -> #REF! | I57: 0 | J57: -5956.52
E58: Total | F58: =SUM(F50:F57) -> -2590000 | G58: =SUM(G50:G57) -> #REF! | H58: =SUM(H50:H57) -> #REF! | I58: =SUM(I50:I57) -> -13984548 | J58: =SUM(J50:J57) -> -14255549
F60: =F58/F47 -> #REF! | G60: =G58/G47 -> #REF! | H60: =H58/H47 -> #REF! | I60: =I58/I47 -> -1.9053696 | J60: =J58/J47 -> -2.3020443
G65: =200000*15 -> 3000000
H67: =-200000*9 -> -1800000
H68: =SUM(H51:H57) -> #REF!
H69: =H68+H67 -> #REF!

Sheet Farms
A1: ID | B1: Farm Name | C1: Status | D1: Relationship | E1: Province/District | F1: Title Deed / Notes | G1: Nearest Town | H1: Distance from Cloudskraal (km) | I1: Size (ha) | J1: Primary Enterprise | K1: Annual Production Capacity | L1: Water Source | M1: Power | N1: Key Infrastructure | O1: Soil/Topo Notes | P1: GPS (lat,lon) | Q1: Ownership/Counterparty | R1: Contact | S1: Deal Terms | T1: Capex Needed (R) | U1: Opex/Yr (R) | V1: Target ROI/IRR (%) | W1: Strategic Fit | X1: Risk Level | Y1: Priority | Z1: Next Action | AA1: Owner | AB1: Target Date (yyyy-mm-dd) | AC1: Notes | AD1: Readiness Score (0–100)
A2: CLO001 | B2: Cloudskraal | C2: Operating | D2: Own | E2: Northern Cape | G2: Nieuwoudtville | H2: 0 | I2: 757.61 | J2: Rooibos | K2: 500 cattle | L2: River | M2: Solar | N2: Homestead, Tea Courts, Sheds | O2: Clay | P2: -33.00, 19.50 | Q2: Self | R2: Jane Smith | S2: N/A | T2: 0 | U2: 0 | V2: 20 | W2: Core | X2: Low | Y2: P1 | Z2: N/A | AA2: Bob | AB2: 46203 | AC2: Key operational farm. | AD2: 100
A3: GAR002 | B3: Garsland | C3: Operating | D3: Own | E3: Northern Cape | G3: Nieuwoudtville | H3: 1.4 | I3: 73.66 | J3: Rooibos | K3: 20 tons | L3: Borehole | M3: Solar | N3: Homestead, Sheds, Dams | O3: Sandy Loam | P3: -33.34, 19.33 | Q3: AgriCo | R3: John Doe | S3: Term Sheet | T3: 500000 | U3: 100000 | V3: 15 | W3: Core | X3: Med | Y3: P1 | Z3: Due Diligence | AA3: Alice | AB3: 46022 | AC3: Initial assessment looks good. | AD3: 80
A4: GLE003 | B4: Glenridge Leeus | C4: Operating | D4: Own | E4: Northern Cape | G4: Nieuwoudtville | H4: 3.4 | I4: 390.82 | J4: Rooibos | K4: 300 tons | L4: Borehole | M4: Solar | N4: Cellar | O4: Granite | P4: -33.45, 18.67 | Q4: Self | R4: Eva Brown | S4: N/A | T4: 0 | U4: 0 | V4: 22 | W4: Core | X4: Low | Y4: P1 | Z4: Harvest Prep | AA4: Alice | AB4: 45962 | AC4: Stable production. | AD4: 100
A5: GLE004 | B5: Glenridge Kerk | C5: Operating | D5: Own | E5: Northern Cape | G5: Nieuwoudtville | H5: 5.1 | I5: 292.81 | J5: Livestock | M5: Solar
A6: BIE005 | B6: Biekoes - Vaal | C6: Operating | D6: Own | E6: Northern Cape | G6: Nieuwoudtville | H6: 0.3 | I6: 622.7 | J6: Rooibos | K6: 1000 tons | L6: Dam | M6: Solar | N6: Silo | O6: Loam | P6: -32.30, 20.00 | Q6: Farmer X | R6: Chris Green | S6: LOI | T6: 1000000 | U6: 200000 | V6: 18 | W6: Adjacent | X6: Med | Y6: P2 | Z6: Finalize Agreement | AA6: David | AB6: 46096 | AC6: Good potential for expansion. | AD6: 60
A7: BIE006 | B7: Biekoes - Straatklip | C7: Operating | D7: Own | E7: Northern Cape | F7: 5/645 | G7: Nieuwoudtville | H7: 1.8 | I7: 169.42 | J7: Rooibos | M7: Solar
A8: KAR007 | B8: Karoo - Winterplaas CL | C8: Operating | D8: Own | E8: Western Cape | F8: RE/224 | G8: Nieuwoudtville | H8: 4.3 | I8: 2872.19 | J8: Livestock | K8: 400 Sheep | L8: Borehole | M8: None | N8: Kraal | O8: Rocky | P8: -33.90, 21.00 | Q8: Farmer Y | R8: Frank White | S8: MOU | T8: 750000 | U8: 150000 | V8: 17 | W8: Adjacent | X8: Med | Y8: P2 | Z8: Valuation | AA8: Bob | AB8: 46053 | AC8: Requires infrastructure upgrade. | AD8: 50
A9: KAR008 | B9: Karoo CL Kromvlei | C9: Operating | D9: Own | E9: Western Cape | F9: 1/224 | G9: Nieuwoudtville | H9: 3.8 | I9: 1173.2 | J9: Livestock | K9: 200 Sheep | M9: None
A10: CLA009 | B10: Claudskraal 645 (6/7/8/9) | C10: Prospective | D10: Occupation | E10: Northern Cape | G10: Nieuwoudtville | H10: 0.1 | I10: 295.5 | J10: Rooibos | M10: Eskom
A11: KLI010 | B11: Klippe Rivier 645/(19/18/6) | C11: Prospective | D11: Occupation | E11: Northern Cape | G11: Nieuwoudtville | H11: 3 | I11: 267.51 | J11: Livestock | M11: Eskom
A12: KRO011 | B12: Kromvlei | C12: Prospective | D12: Negotiating | E12: Northern Cape | F12: RE/644 | G12: Nieuwoudtville | H12: 2.8 | I12: 391.02 | J12: Rooibos | M12: Eskom
A13: KRO012 | B13: Kromvlei Driehoek | C13: Prospective | D13: Negotiating | E13: Northern Cape | F13: RE/637 | G13: Nieuwoudtville | H13: 4.3 | I13: 199.16 | J13: Rooibos | M13: Eskom
A14: TAB013 | B14: Tabaktuin | C14: Prospective | D14: No Offer | E14: Northern Cape | G14: Nieuwoudtville | H14: 4.7 | J14: Rooibos | M14: Eskom

Sheet Fields
A1: Field Name / Identifier | B1: Farm Name (Linked) | C1: Field ID | D1: Title Deed / Notes | E1: Size (ha) | F1: Perimeter (m) | G1: Crop / Enterprise | H1: Current Status | I1: Planting Date (yyyy-mm-dd) | J1: Harvest Date (yyyy-mm-dd) | K1: Yield Target (kg or t/ha) | L1: Soil Type | M1: Irrigation Type | N1: Water Source | O1: Fertility / Input Notes | P1: Weed / Pest Pressure | Q1: Risk Level | R1: Last Activity | S1: Next Action | T1: Responsible Person | U1: GPS / Shape ID | V1: Notes | W1: % of Farm Area
A2: Rooibos-1 | B2: Garsland | C2: F001 | D2: Block R1 | E2: 25 | F2: 2000 | G2: Rooibos | H2: Planted | I2: 45726 | J2: 46068 | K2: 800 kg/ha | L2: Sand | M2: Drip | N2: Borehole | O2: Fertiliser Mix A | P2: Low | Q2: Low | R2: Sprayed 2025-09-20 | S2: Apply Herbicide | T2: Alice | U2: [URL] | V2: Good growth. | W2: 34
A3: Block A | B3: Cloudskraal | C3: F002 | D3: Camp 1 | E3: 150 | F3: 5500 | G3: Grazing | H3: Pasture | I3: N/A | J3: N/A | K3: 100 cattle | L3: Clay | M3: None | N3: River | O3: Pasture rotation plan | P3: Low | Q3: Low | R3: Checked 2025-09-28 | S3: Move livestock | T3: Bob | U3: [URL] | V3: Needs reseeding. | W3: 19.8
A4: Vineyard-West | B4: Glenridge | C4: F003 | D4: Vineyard Block 3 | E4: 15 | F4: 1200 | G4: Vines | H4: Planted | I4: 45139 | J4: 46082 | K4: 10 t/ha | L4: Loam | M4: Drip | N4: Eskom | O4: Organic compost | P4: Medium | Q4: Medium | R4: Pruned 2025-09-15 | S4: Apply Fungicide | T4: Eva | U4: [URL] | V4: Healthy vines. | W4: 3.8
A5: Block B | B5: Biekoes | C5: F004 | D5: Field B | E5: 100 | F5: 4000 | G5: Wheat | H5: Planted | I5: 45778 | J5: 45981 | K5: 5 t/ha | L5: Loam | M5: Pivot | N5: Dam | O5: Standard fertilising | P5: Medium | Q5: Medium | R5: Sprayed 2025-09-25 | S5: Harvest | T5: David | U5: [URL] | V5: Anticipating good yield. | W5: 16
A6: Old Lands | B6: Kromvlei 244 | C6: F005 | D6: Historical Area | E6: 50 | F6: 3000 | G6: Fallow | H6: Fallow | I6: N/A | J6: N/A | K6: N/A | L6: Sandy | M6: None | N6: Rainfed | O6: Cover crop planned | P6: High | Q6: High | R6: Ploughed 2025-08-10 | S6: Plant Cover Crop | T6: Bob | U6: [URL] | V6: Rest period. | W6: 20
A7: Rooibos-2 | B7: Garsland | C7: F006 | D7: Block R2 | E7: 10 | F7: 1000 | G7: Rooibos | H7: Planned | I7: 46082 | J7: 46419 | K7: 750 kg/ha | L7: Sand | M7: Drip | N7: Borehole | O7: Soil test needed | P7: Low | Q7: Low | R7: Soil Sample 2025-09-01 | S7: Prepare soil | T7: Alice | U7: [URL] | V7: Future expansion. | W7: 13.6
A8: North Pasture | B8: Cloudskraal | C8: F007 | D8: Camp 2 | E8: 200 | F8: 6500 | G8: Grazing | H8: Pasture | I8: N/A | J8: N/A | K8: 150 cattle | L8: Clay | M8: None | N8: River | O8: Winter feed | P8: Low | Q8: Low | R8: Rotated 2025-09-20 | S8: Check fences | T8: Bob | U8: [URL] | V8: Regular use. | W8: 26.4
A9: Vineyard-East | B9: Glenridge | C9: F008 | D9: Vineyard Block 1 | E9: 20 | F9: 1500 | G9: Vines | H9: Harvested | I9: 45488 | J9: 45721 | K9: 12 t/ha | L9: Granite | M9: Drip | N9: Eskom | O9: Post-harvest nutrients | P9: Low | Q9: Low | R9: Fertilized 2025-04-10 | S9: Winter Pruning | T9: Eva | U9: [URL] | V9: Excellent quality. | W9: 5.1
A10: Lucerne Patch | B10: Biekoes | C10: F009 | D10: Small Section | E10: 20 | F10: 800 | G10: Lucerne | H10: Planted | I10: 45323 | J10: 45950 | K10: 5 t/ha | L10: Clay | M10: Flood | N10: Dam | O10: Dolomitic lime | P10: Low | Q10: Medium | R10: Irrigated 2025-09-29 | S10: Harvest | T10: David | U10: [URL] | V10: Good for livestock feed. | W10: 3.2
A11: Riverbank Fields | B11: Garsland | C11: F010 | D11: Adjacent to River | E11: 15 | F11: 1500 | G11: Other | H11: Fallow | I11: N/A | J11: N/A | K11: N/A | L11: Mixed | M11: None | N11: River | O11: Erosion control needed | P11: Medium | Q11: Medium | R11: Analysed 2025-07-01 | S11: Erosion control | T11: Alice | U11: [URL] | V11: Environmental focus. | W11: 20.4

Sheet Workers

Sheet Suppliers
A1: Supplier Name | B1: Legal Entity | C1: VAT Number | D1: B-BBEE Level | E1: Registration / CSD No | F1: Primary Contact | G1: Phone | H1: Email | I1: Website | J1: Physical Address | K1: Delivery Regions | L1: Product Categories | M1: Payment Terms | N1: Preferred Supplier | O1: Incoterms / Delivery | P1: Minimum Order Qty / Value | Q1: Lead Time (days) | R1: Lead Time Variability | S1: Return Policy Summary | T1: Certifications | U1: SDS/MSDS Link | V1: Notes | W1: Reliability Score
A2: AgriSuppliers | B2: Pty Ltd | C2: 4001234567 | D2: Level 2 | E2: CSD2022-001 | F2: John Farmer | G2: +27211234567 | H2: info@agrisuppliers.co.za | I2: [URL] | J2: 123 Farm Rd, Cape Town | K2: WC, EC, NC | L2: Fertiliser, Seed, Pesticide, Herbicide, Fuel | M2: 30d EOM | N2: TRUE | O2: Delivered | P2: R 5,000 | Q2: 7 | R2: Low | S2: 30-day return for unopened products | T2: SANS, ISO 9001 | U2: [URL] | V2: Excellent service, competitive pricing | W2: 90
A3: CropCare Solutions | B3: Pty Ltd | C3: 4009876543 | D3: Level 4 | E3: CSD2022-002 | F3: Sarah Green | G3: +27217654321 | H3: sales@cropcare.co.za | I3: [URL] | J3: 45 Industry St, Bellville | K3: WC, EC | L3: Pesticide, Fungicide, Herbicide, PPE | M3: 15d | N3: TRUE | O3: Delivered | P3: R 2,000 | Q3: 10 | R3: Medium | S3: Standard 14-day return | T3: GAP Certified | U3: [URL] | V3: Specializes in organic solutions | W3: 80
A4: AgroChem | B4: CC | C4: 4005558888 | D4: Level 3 | E4: CSD2022-003 | F4: Peter Pest | G4: +27218889999 | H4: orders@agrochem.com | I4: [URL] | J4: 78 Warehouse Ave, Paarl | K4: WC | L4: Herbicide, Pesticide, Fungicide | M4: COD | N4: FALSE | O4: Ex-works | P4: R 1,000 | Q4: 5 | R4: Low | S4: No returns on opened chemicals | T4: SDS/MSDS available | U4: [URL] | V4: Good for urgent orders | W4: 45
A5: SeedMasters | B5: Pty Ltd | C5: 4001112222 | D5: Level 1 | E5: CSD2022-004 | F5: Lisa Plant | G5: +27213334444 | H5: hello@seedmasters.co.za | I5: [URL] | J5: 90 Seed Ln, Malmesbury | K5: National | L5: Seed | M5: 30d EOM | N5: TRUE | O5: Delivered | P5: R 10,000 | Q5: 14 | R5: Medium | S5: Returns only for quality defects | T5: Organic Certified, SANS | U5: [URL] | V5: Wide variety of specialized seeds | W5: 75
A6: WaterWorks | B6: Pty Ltd | C6: 4007771111 | D6: Level 5 | E6: CSD2022-005 | F6: Mark Stream | G6: +27216667777 | H6: support@waterworks.net | I6: [URL] | J6: 10 Pump Rd, Stellenbosch | K6: WC | L6: Irrigation | M6: 60d | N6: TRUE | O6: Delivered | P6: R 3,000 | Q6: 20 | R6: High | S6: 7-day return on faulty parts | T6: ISO 14001 | U6: [URL] | V6: Reliable irrigation system supplier | W6: 65
A7: PetroFuel | B7: Pty Ltd | C7: 4002223333 | D7: Level 8 | E7: N/A | F7: Nomusa Diesel | G7: +27215556666 | H7: fuel@petrofuel.co.za | I7: [URL] | J7: 50 Tanker Way, Atlantis | K7: WC, EC | L7: Fuel | M7: COD | N7: FALSE | O7: Delivered | P7: 500 L | Q7: 3 | R7: Low | S7: No returns on fuel | T7: N/A | U7: [URL] | V7: Bulk fuel delivery | W7: 30
A8: LabServices | B8: Sole Prop | C8: N/A | D8: Level 6 | E8: N/A | F8: Dr. Ana Test | G8: +27214445555 | H8: lab@labservices.co.za | I8: [URL] | J8: 20 Science Park, Somerset West | K8: WC | L8: Lab | M8: 15d | N8: FALSE | O8: Delivered | P8: R 500 | Q8: 10 | R8: Low | S8: N/A | T8: ISO 17025 | U8: [URL] | V8: Soil and water testing | W8: 65
A9: FarmTools | B9: Pty Ltd | C9: 4003334444 | D9: Level 2 | E9: CSD2022-006 | F9: Sipho Gear | G9: +27219990000 | H9: sales@farmtools.co.za | I9: [URL] | J9: 11 Tractor St, Wellington | K9: WC, NC | L9: PPE, Other (Farm Equipment Parts) | M9: 30d EOM | N9: TRUE | O9: Delivered | P9: R 1,500 | Q9: 12 | R9: Medium | S9: 30-day exchange for defective items | T9: SANS | U9: [URL] | V9: Good for specialized tools | W9: 75

Sheet Customer
A1: Customer Name | B1: Business Type | C1: Legal Entity | D1: VAT Number | E1: Registration No / Importer No | F1: Primary Contact | G1: Phone | H1: Email | I1: Website | J1: Physical Address | K1: Delivery Region / Market | L1: Preferred Products | M1: Contract Type | N1: Contract Volume (annual or per cycle, with units) | O1: Contract Price (R/unit) | P1: Current Order Pipeline (live quantity ordered, R value) | Q1: Payment Terms | R1: Payment Status | S1: Logistics / Delivery Terms | T1: Certifications Required | U1: Notes | V1: Reliability Score
A2: Tea Exporters | B2: Exporter | C2: Pty Ltd | D2: 4001112222 | E2: EXP-2025-001 | F2: Emily Green | G2: +27211234567 | H2: orders@teaexporters.com | I2: [URL] | J2: 10 Port Rd, Cape Town | K2: Export | L2: Rooibos | M2: Annual | N2: 50,000 kg | O2: 45 | P2: 10,000 kg, R450,000 | Q2: 30d EOM | R2: Good | S2: Delivered | T2: Organic, Export Clearance | U2: Long-standing export partner | V2: 90
A3: Local Winery | B3: Processor | C3: Pty Ltd | D3: 4003334444 | E3: N/A | F3: David Grape | G3: +27219876543 | H3: procurement@localwinery.co.za | I3: [URL] | J3: 20 Vine Rd, Stellenbosch | K3: Local | L3: Grapes, Wine | M3: Seasonal | N3: 100,000 kg (grapes) | O3: 12.5 | P3: 20,000 kg, R250,000 | Q3: 30 days | R3: Pending | S3: Ex-Farm | T3: HACCP | U3: Primary grape buyer | V3: 65
A4: Flour Mill | B4: Processor | C4: Pty Ltd | D4: 4005556666 | E4: N/A | F4: Sarah Grain | G4: +27212345678 | H4: purchase@flourmill.com | I4: [URL] | J4: 30 Silo Ave, Malmesbury | K4: National | L4: Grains | M4: Offtake | N4: 15,000 t (wheat) | O4: 3500 | P4: 5,000 t, R17,500,000 | Q4: 60d | R4: Good | S4: Shared Transport | T4: None | U4: Reliable bulk grain purchaser | V4: 80
A5: Butcher Shop | B5: Retailer | C5: Sole Prop | D5: N/A | E5: N/A | F5: Sipho Meat | G5: +27218765432 | H5: orders@butchershop.co.za | I5: [URL] | J5: 40 High St, Paarl | K5: Local | L5: Livestock | M5: Spot | N5: N/A | O5: 2500 | P5: 10 head, R25,000 | Q5: COD | R5: Good | S5: Delivered | T5: None | U5: Buys smaller, fresh batches | V5: 30
A6: Textile Factory | B6: Processor | C6: Pty Ltd | D6: 4007778888 | E6: EXP-2025-002 | F6: Lena Wool | G6: +27213456789 | H6: sales@textilefactory.co.za | I6: [URL] | J6: 50 Fabric Ln, Atlantis | K6: Export | L6: Wool | M6: Annual | N6: 200 bales | O6: 800 | P6: 50 bales, R40,000 | Q6: 60d EOM | R6: Pending | S6: Delivered | T6: Fairtrade, Export Clearance | U6: Seeking sustainable wool sources | V6: 80
A7: Supermarket Chain | B7: Retailer | C7: Pty Ltd | D7: 4009990000 | E7: N/A | F7: Ben Fresh | G7: +27214567890 | H7: freshproduce@superchain.com | I7: [URL] | J7: 60 Market Sq, Worcester | K7: National | L7: Vegetables, Fruit | M7: Seasonal | N7: 5,000 kg (tomatoes) | O7: 18 | P7: 1,000 kg, R18,000 | Q7: 30 days | R7: Good | S7: Delivered | T7: HACCP, Organic | U7: Keen on organic produce | V7: 70
A8: Fruit Wholesaler | B8: Wholesaler | C8: Pty Ltd | D8: 4001213141 | E8: N/A | F8: Chris Fruit | G8: +27215678901 | H8: info@fruitwholesaler.com | I8: [URL] | J8: 70 Orchard Rd, Grabouw | K8: Local | L8: Fruit | M8: Spot | N8: N/A | O8: 15 | P8: 500 kg, R7,500 | Q8: 30 days | R8: Late | S8: Ex-Farm | T8: HACCP | U8: Sometimes slow with payments | V8: 45
A9: Compost Solutions | B9: Other (Processor) | C9: Pty Ltd | D9: 4001516171 | E9: N/A | F9: Anna Waste | G9: +27216789012 | H9: sales@compostsolutions.co.za | I9: [URL] | J9: 80 Green Way, Strand | K9: Local | L9: By-products | M9: Seasonal | N9: 2,000 kg (grape pomace) | O9: 2.5 | P9: 500 kg, R1,250 | Q9: COD | R9: Good | S9: Ex-Farm | T9: None | U9: Buys farm waste for compost | V9: 40
A10: Brew Masters | B10: Processor | C10: Pty Ltd | D10: 4001819202 | E10: N/A | F10: Mark Malt | G10: +27217890123 | H10: malt@brewmasters.co.za | I10: [URL] | J10: 90 Brewery St, George | K10: National | L10: Grains (Barley) | M10: Annual | N10: 7,000 t (barley) | O10: 4000 | P10: 1,500 t, R6,000,000 | Q10: 60 days | R10: Good | S10: Delivered | T10: None | U10: Key supplier for malt barley | V10: 75
A11: Local Market Stalls | B11: Direct Consumer | C11: Sole Prop | D11: N/A | E11: N/A | F11: Zola Vendor | G11: +27210123456 | H11: zola@marketstalls.co.za | I11: [URL] | J11: 100 Town Sq, Franschhoek | K11: Local | L11: Vegetables, Fruit, Other | M11: Spot | N11: N/A | O11: 150 | P11: 10 units, R1,500 | Q11: COD | R11: Good | S11: Ex-Farm | T11: None | U11: Regular small quantity buyer | V11: 30

Sheet Outputs
A1: Output ID | B1: Date | C1: Farm Name | D1: Field Name | E1: Output Category | F1: Product Name | G1: Variety / Breed | H1: Quantity | I1: Unit | J1: Quality Grade | K1: Buyer / Customer | L1: Destination / Market | M1: Price per Unit (R) | N1: Total Value | O1: Invoice / Delivery Note Ref | P1: Certification | Q1: Logistics Partner | R1: Storage Location | S1: Costs Allocated (R) | T1: Net Margin (R) | U1: Payment Terms | V1: Payment Status | W1: Responsible Person | X1: Notes
A2: OUT-001 | B2: 45928 | C2: Green Acres | D2: North Field | E2: Rooibos | F2: Rooibos Grade A | G2: Superior Blend | H2: 5000 | I2: kg | J2: Export | K2: Tea Exporters | L2: Export | M2: 45 | N2: 225000 | O2: INV-RA-001 | P2: Organic | Q2: Global Freight | R2: Warehouse | S2: 100000 | T2: 125000 | U2: 30 days | V2: Paid | W2: John Doe | X2: Shipped to Germany
A3: OUT-002 | B3: 45925 | C3: Sunny Fields | D3: East Meadow | E3: Grapes/Wine | F3: Chenin Blanc grapes | G3: Chenin Blanc | H3: 8000 | I3: kg | J3: A | K3: Local Winery | L3: Processor | M3: 12.5 | N3: 100000 | O3: DN-CB-002 | P3: GAP | Q3: Own Transport | R3: Winery Cellar | S3: 40000 | T3: 60000 | U3: 30 days | V3: Pending | W3: Jane Smith | X3: Harvested at optimal ripeness
A4: OUT-003 | B4: 45920 | C4: Harvest Valley | D4: Central Plot | E4: Grain | F4: Wheat Grade B | G4: Southern Star | H4: 15000 | I4: t | J4: B | K4: Flour Mill | L4: Coop | M4: 3500 | N4: 52500000 | O4: INV-WG-003 | P4: None | Q4: Rail Logistics | R4: Silo | S4: 20000000 | T4: 32500000 | U4: 60 days | V4: Paid | W4: Peter Jones | X4: Bulk delivery completed
A5: OUT-004 | B5: 45918 | C5: Green Acres | D5: South Field | E5: Livestock | F5: Dorper Lamb | G5: Dorper | H5: 50 | I5: head | J5: A | K5: Butcher Shop | L5: Local | M5: 2500 | N5: 125000 | O5: DN-DL-004 | P5: None | Q5: Local Courier | R5: Cold Room | S5: 50000 | T5: 75000 | U5: COD | V5: Paid | W5: Sarah Lee | X5: Delivered fresh to market
A6: OUT-005 | B6: 45915 | C6: Sunny Fields | D6: West Pasture | E6: Wool | F6: Merino Wool Fine | G6: Merino | H6: 200 | I6: bales | J6: Export | K6: Textile Factory | L6: Export | M6: 800 | N6: 160000 | O6: INV-MW-005 | P6: Fairtrade | Q6: Ocean Cargo | R6: Warehouse | S6: 70000 | T6: 90000 | U6: 60 days | V6: Pending | W6: David Kim | X6: Sheared this season
A7: OUT-006 | B7: 45910 | C7: Harvest Valley | D7: River Bend | E7: Vegetables | F7: Tomatoes | G7: Roma | H7: 1000 | I7: kg | J7: A | K7: Supermarket | L7: Direct-to-Consumer | M7: 18 | N7: 18000 | O7: DN-TM-006 | P7: Organic | Q7: Own Transport | R7: N/A | S7: 8000 | T7: 10000 | U7: 30 days | V7: Paid | W7: Emily White | X7: Freshly picked for local stores
A8: OUT-007 | B8: 45905 | C8: Green Acres | D8: North Field | E8: Fruit | F8: Apples | G8: Granny Smith | H8: 3000 | I8: kg | J8: B | K8: Fruit Wholesaler | L8: Local | M8: 15 | N8: 45000 | O8: INV-AP-007 | P8: HACCP | Q8: Cold Chain Trans | R8: Cold Room | S8: 15000 | T8: 30000 | U8: 30 days | V8: Overdue | W8: John Doe | X8: Delayed payment expected
A9: OUT-008 | B9: 45901 | C9: Sunny Fields | D9: East Meadow | E9: By-products | F9: Grape Pomace | G9: Chenin Blanc | H9: 2000 | I9: kg | J9: C | K9: Compost Co | L9: Processor | M9: 2.5 | N9: 5000 | O9: DN-GP-008 | P9: None | Q9: Own Transport | R9: Compost Pile | S9: 1000 | T9: 4000 | U9: COD | V9: Paid | W9: Jane Smith | X9: Residue from wine production
A10: OUT-009 | B10: 45897 | C10: Harvest Valley | D10: Central Plot | E10: Grain | F10: Barley | G10: Malt Grade | H10: 7000 | I10: t | J10: A | K10: Brewery | L10: Coop | M10: 4000 | N10: 28000000 | O10: INV-BL-009 | P10: GAP | Q10: Road Haulers | R10: Silo | S10: 12000000 | T10: 16000000 | U10: 60 days | V10: Pending | W10: Peter Jones | X10: Used for brewing
A11: OUT-010 | B11: 45889 | C11: Green Acres | D11: South Field | E11: Other | F11: Firewood | G11: Eucalyptus | H11: 100 | I11: units | J11: C | K11: Local Market | L11: Direct-to-Consumer | M11: 150 | N11: 15000 | O11: DN-FW-010 | P11: None | Q11: Own Transport | R11: Wood Shed | S11: 5000 | T11: 10000 | U11: COD | V11: Paid | W11: Sarah Lee | X11: Collected from farm maintenance

Sheet Inputs
A1: Input ID | B1: Date Applied | C1: Farm Name | D1: Field Name | E1: Input Category | F1: Input Name / Product | G1: Supplier | H1: Batch / Invoice # | I1: Application Rate (per ha or per litre) | J1: Total Quantity Used | K1: Unit | L1: Application Method | M1: Purpose | N1: Labour Hrs | O1: Cost per Unit (R) | P1: Total Cost | Q1: Responsible Person | R1: Next Action / Follow-up | S1: Notes
A2: FI-001 | B2: 45915 | C2: Green Acres | D2: North Field | E2: Fertiliser | F2: Urea 46% | G2: AgriSuppliers | H2: INV-2025-001 | I2: 150 kg/ha | J2: 1500 | K2: kg | L2: Broadcast | M2: Fertility boost | N2: 4 | O2: 8.5 | P2: 12750 | Q2: John Doe | R2: Reapply in 6 months | S2: Post-harvest application
A3: FI-002 | B3: 45910 | C3: Sunny Fields | D3: East Meadow | E3: Pesticide | F3: Prosper 250 EC | G3: CropCare Solutions | H3: BAT-P250-003 | I3: 1.5 L/ha | J3: 30 | K3: L | L3: Spray | M3: Pest control | N3: 6 | O3: 350 | P3: 10500 | Q3: Jane Smith | R3: Monitor pest levels weekly | S3: Applied after initial pest sighting
A4: FI-003 | B4: 45897 | C4: Harvest Valley | D4: Central Plot | E4: Herbicide | F4: Glyphosate Ultra | G4: AgroChem | H4: INV-2025-002 | I4: 2 L/ha | J4: 80 | K4: L | L4: Spray | M4: Weed control | N4: 5 | O4: 220 | P4: 17600 | Q4: Peter Jones | R4: Apply pre-emergence next season | S4: Effective on broadleaf weeds
A5: FI-004 | B5: 45920 | C5: Green Acres | D5: South Field | E5: Seed | F5: Hybrid Maize C12 | G5: SeedMasters | H5: BAT-HMC-001 | I5: 8 kg/ha | J5: 80 | K5: packs | L5: Manual | M5: Crop establishment | N5: 10 | O5: 1200 | P5: 96000 | Q5: Sarah Lee | R5: Check germination in 14 days | S5: Planted during optimal weather
A6: FI-005 | B6: 45901 | C6: Sunny Fields | D6: West Pasture | E6: Labour | F6: Tractor Driving | G6: Farm Crew | H6: TIMESHEET-09-01 | I6: N/A | J6: 20 | K6: hrs | L6: Tractor | M6: Land preparation | N6: 20 | O6: 150 | P6: 3000 | Q6: David Kim | R6: N/A | S6: Field plowing completed
A7: FI-006 | B7: 45884 | C7: Harvest Valley | D7: River Bend | E7: Irrigation | F7: Drip System Repair | G7: WaterWorks | H7: INV-2025-003 | I7: N/A | J7: 1 | K7: hrs | L7: Drip | M7: Water management | N7: 2 | O7: 500 | P7: 1000 | Q7: Emily White | R7: Inspect system monthly | S7: Minor leak repaired
A8: FI-007 | B8: 45925 | C8: Green Acres | D8: North Field | E8: Fungicide | F8: Azoxystrobin | G8: AgroGuard | H8: BAT-AZO-002 | I8: 0.8 L/ha | J8: 8 | K8: L | L8: Spray | M8: Disease prevention | N8: 3 | O8: 450 | P8: 3600 | Q8: John Doe | R8: Reapply in 21 days | S8: Proactive disease management
A9: FI-008 | B9: 45918 | C9: Sunny Fields | D9: East Meadow | E9: Fuel | F9: Diesel | G9: PetroFuel | H9: REC-10045 | I9: N/A | J9: 100 | K9: L | L9: Tractor | M9: Equipment operation | N9: N/A | O9: 18.5 | P9: 1850 | Q9: Jane Smith | R9: Top up tank next week | S9: Used for sprayer operations
A10: FI-009 | B10: 45899 | C10: Harvest Valley | D10: Central Plot | E10: Other | F10: Soil Sampling | G10: LabServices | H10: INV-2025-004 | I10: N/A | J10: 1 | K10: packs | L10: Manual | M10: Soil health assessment | N10: 8 | O10: 750 | P10: 750 | Q10: Peter Jones | R10: Receive lab results by 2025-10-15 | S10: Samples sent for nutrient analysis
A11: FI-010 | B11: 45912 | C11: Green Acres | D11: South Field | E11: Fertiliser | F11: Potassium Sulphate | G11: AgriSuppliers | H11: INV-2025-005 | I11: 80 kg/ha | J11: 800 | K11: kg | L11: Broadcast | M11: Nutrient supplementation | N11: 3 | O11: 12 | P11: 9600 | Q11: Sarah Lee | R11: Monitor crop response | S11: Applied before flowering

Sheet Equipment
A1: Equipment ID | B1: Farm Name | C1: Equipment Type | D1: Make | E1: Model | F1: Year | G1: Serial Number | H1: Status | I1: Last Service Date | J1: Next Service Due (Date) | K1: Condition | L1: Ownership | M1: Acquisition Date | N1: Purchase Price (R) | O1: Supplier / Dealer | P1: Warranty Expiry | Q1: Responsible Person | R1: Notes
A2: ME-001 | B2: Green Acres | C2: Sprayer | D2: Hardi | E2: Navigator 4000 | F2: 2022 | G2: HARD-N4K-123 | H2: Active | I2: 45809 | J2: 46174 | K2: Good | L2: Own | M2: 44671 | N2: 380000 | O2: CropCare Solutions | P2: 46497 | Q2: John Doe | R2: Trailed sprayer, 4000L capacity
A3: ME-002 | B3: Sunny Fields | C3: Cultivator | D3: Vaderstad | E3: Carrier 420 | F3: 2023 | G3: VAD-C420-456 | H3: Active | I3: N/A | J3: N/A | K3: Excellent | L3: Own | M3: 45179 | N3: 250000 | O3: AgriSuppliers | P3: 47006 | Q3: Jane Smith | R3: Flexible stubble cultivator
A4: ME-003 | B4: Harvest Valley | C4: Baler | D4: Krone | E4: Comprima V150 | F4: 2021 | G4: KRO-CV150-789 | H4: In Repair | I4: 45853 | J4: 46218 | K4: Needs Repair | L4: Own | M4: 44260 | N4: 420000 | O4: FarmEquipment Co | P4: 46086 | Q4: Peter Jones | R4: Round baler, minor gearbox issue
A5: ME-004 | B5: Green Acres | C5: Generator | D5: Cummins | E5: C110D5 | F5: 2019 | G5: CUM-C110D5-012 | H5: Standby | I5: 45672 | J5: 46037 | K5: Good | L5: Own | M5: 43748 | N5: 220000 | O5: Generator World | P5: N/A | Q5: Sarah Lee | R5: Emergency power backup for packing shed
A6: ME-005 | B6: Sunny Fields | C6: Pump | D6: Grundfos | E6: SP 17-10 | F6: 2020 | G6: GF-SP17-10-345 | H6: Active | I6: 45736 | J6: 46101 | K6: Good | L6: Own | M6: 44044 | N6: 60000 | O6: WaterWorks | P6: 45870 | Q6: David Kim | R6: Borehole pump, due for replacement
A7: ME-006 | B7: Harvest Valley | C7: Harvester | D7: Claas | E7: Lexion 760 | F7: 2024 | G7: CLA-L760-678 | H7: Active | I7: N/A | J7: 46113 | K7: Excellent | L7: Lease | M7: 45383 | N7: 3500000 | O7: Premium Harvesters | P7: 47209 | Q7: Emily White | R7: New lease, high capacity combine
A8: ME-007 | B8: Green Acres | C8: Disc Harrow | D8: Lemken | E8: Heliodor 9 | F8: 2022 | G8: LEM-H9-901 | H8: Active | I8: N/A | J8: N/A | K8: Excellent | L8: Own | M8: 44880 | N8: 180000 | O8: AgriSuppliers | P8: 46706 | Q8: John Doe | R8: Used for seedbed preparation
A9: ME-008 | B9: Sunny Fields | C9: Loader | D9: Caterpillar | E9: 906M | F9: 2020 | G9: CAT-906M-234 | H9: Active | I9: 45752 | J9: 46117 | K9: Good | L9: Own | M9: 44022 | N9: 700000 | O9: EarthMoving Solutions | P9: N/A | Q9: Jane Smith | R9: Versatile for material handling
A10: ME-009 | B10: Harvest Valley | C10: Shredder | D10: Fecon | E10: FTX100 | F10: 2023 | G10: FEC-FTX100-567 | H10: Active | I10: 45901 | J10: 46266 | K10: Good | L10: Own | M10: 44946 | N10: 320000 | O10: Forestry Equipment | P10: 46772 | Q10: Peter Jones | R10: Used for clearing brush and pruning
A11: ME-010 | B11: Green Acres | C11: Planter | D11: Amazone | E11: Citan 12001-C | F11: 2024 | G11: AMZ-C12001-890 | H11: Active | I11: N/A | J11: N/A | K11: Excellent | L11: Own | M11: 45332 | N11: 550000 | O11: AgriSuppliers | P11: 47159 | Q11: Sarah Lee | R11: Precision seed drill for grains

Sheet Equipment 2
A1: Asset ID | B1: Asset Type | C1: Make | D1: Model | E1: Year | F1: Serial/VIN | G1: Registration/Plate | H1: Farm Name | I1: Location / Field | J1: Status | K1: Owner/Lease | L1: Acquisition Date | M1: Supplier / Dealer | N1: Purchase Price (R) | O1: Est. Current Value (R) | P1: Depreciation Method | Q1: Useful Life (years) | R1: Meter Type | S1: Current Meter Reading | T1: Last Service Date | U1: Last Service Meter | V1: Service Interval (Hours) | W1: Next Service Due (Hours) | X1: Next Service Date | Y1: Fuel Type | Z1: Avg Fuel Use (L/hr or L/100km) | AA1: Tyre Size / Count | AB1: Implement Width (m) | AC1: PTO/Power (kW/HP) | AD1: Hydraulic/Notes | AE1: Service Provider | AF1: Warranty Expiry | AG1: Insurance Policy # | AH1: Documents | AI1: Condition | AJ1: Criticality | AK1: Downtime (hrs YTD) | AL1: Opex YTD (R) | AM1: Capex YTD (R) | AN1: Notes
A2: EQ-001 | B2: Tractor | C2: John Deere | D2: 6120M | E2: 2023 | F2: JD6120M-S1234 | G2: CA123-456 | H2: Green Acres | I2: North Field | J2: Active | K2: Own | L2: 45000 | M2: AgriSuppliers | N2: 1200000 | O2: 1080000 | P2: Straight | Q2: 10 | R2: Hours | S2: 1550 | T2: 45787 | U2: 1000 | V2: 500 | W2: 1500 | X2: 45971 | Y2: Diesel | Z2: 12 L/hr | AA2: 460/85R38 / 4 | AB2: N/A | AC2: 90 kW / 120 HP | AD2: Standard 3-point hitch, 2 SCV | AE2: FarmMechanics | AF2: 46096 | AG2: INS-JD-001 | AH2: [URL] | AI2: Good | AJ2: High | AK2: 20 | AL2: 25000 | AM2: 0 | AN2: Main workhorse tractor for crop cultivation
A3: EQ-002 | B3: Implement | C3: Kverneland | D3: 5-furrow Plough | E3: 2022 | F3: KV-PLOUGH-5-XYZ | G3: N/A | H3: Sunny Fields | I3: East Meadow | J3: Active | K3: Own | L3: 44774 | M3: AgriSuppliers | N3: 150000 | O3: 120000 | P3: Straight | Q3: 15 | R3: none | S3: N/A | T3: N/A | U3: N/A | V3: N/A | W3: N/A | X3: N/A | Y3: N/A | Z3: N/A | AA3: N/A | AB3: 2.5 | AC3: N/A | AD3: Reversible plough for primary tillage | AE3: FarmMechanics | AF3: 46600 | AG3: INS-KV-002 | AH3: [URL] | AI3: Excellent | AJ3: Medium | AK3: 5 | AL3: 5000 | AM3: 0 | AN3: Used for primary tillage
A4: EQ-003 | B4: Vehicle | C4: Toyota | D4: Hilux 2.8 GD-6 | E4: 2024 | F4: VIN-HILUX-ABC | G4: CK111-222 | H4: Harvest Valley | I4: N/A | J4: Active | K4: Own | L4: 45311 | M4: Toyota Dealership | N4: 650000 | O4: 600000 | P4: Straight | Q4: 8 | R4: km | S4: 25000 | T4: 45839 | U4: 20000 | V4: 10000 | W4: 30000 | X4: 46023 | Y4: Diesel | Z4: 8 L/100km | AA4: 265/65R17 / 4 | AB4: N/A | AC4: N/A | AD4: Farm supervisor vehicle, off-road capable | AE4: Toyota Service | AF4: 46407 | AG4: INS-HIL-003 | AH4: [URL] | AI4: Good | AJ4: High | AK4: 10 | AL4: 12000 | AM4: 0 | AN4: Essential for farm logistics and supervision
A5: EQ-004 | B5: Pump | C5: Grundfos | D5: CR15-5 | E5: 2021 | F5: GF-CR15-5-123 | G5: N/A | H5: Green Acres | I5: Dam A | J5: In Repair | K5: Own | L5: 44505 | M5: WaterWorks | N5: 45000 | O5: 20000 | P5: Straight | Q5: 12 | R5: Hours | S5: 8500 | T5: 45580 | U5: 8000 | V5: 1000 | W5: 9000 | X5: 45945 | Y5: Electric | Z5: N/A | AA5: N/A | AB5: N/A | AC5: 7.5 kW | AD5: Centrifugal pump, currently awaiting parts | AE5: WaterWorks | AF5: 46331 | AG5: INS-GF-004 | AH5: [URL] | AI5: Needs Repair | AJ5: Critical | AK5: 120 | AL5: 8000 | AM5: 0 | AN5: Main irrigation pump, urgent repair needed
A6: EQ-005 | B6: Pivot | C6: Valley | D6: 8120 | E6: 2020 | F6: VALL-8120-QWER | G6: N/A | H6: Sunny Fields | I6: Pivot 1 | J6: Active | K6: Lease | L6: 43983 | M6: Valley Dealer | N6: 750000 | O6: 500000 | P6: Straight | Q6: 20 | R6: Hours | S6: 12000 | T6: 45736 | U6: 11000 | V6: 2000 | W6: 13000 | X6: 46101 | Y6: Electric | Z6: N/A | AA6: N/A | AB6: 400 | AC6: N/A | AD6: 8-tower pivot system, covers 50 ha | AE6: Valley Service | AF6: 46022 | AG6: INS-PV-005 | AH6: [URL] | AI6: Good | AJ6: High | AK6: 30 | AL6: 18000 | AM6: 0 | AN6: Under lease agreement, essential for irrigation
A7: EQ-006 | B7: Generator | C7: Cummins | D7: C110D5 | E7: 2019 | F7: CUMM-C110D5-FGHI | G7: N/A | H7: Harvest Valley | I7: Workshop | J7: Standby | K7: Own | L7: 43748 | M7: Generator World | N7: 220000 | O7: 100000 | P7: Straight | Q7: 15 | R7: Hours | S7: 550 | T7: 45672 | U7: 500 | V7: 250 | W7: 750 | X7: 46037 | Y7: Diesel | Z7: 15 L/hr | AA7: N/A | AB7: N/A | AC7: 88 kW / 110 kVA | AD7: Emergency backup power, runs weekly test | AE7: GenTech Solutions | AF7: 45575 | AG7: INS-GEN-006 | AH7: [URL] | AI7: Good | AJ7: Medium | AK7: 5 | AL7: 3000 | AM7: 0 | AN7: Warranty expired, but well maintained
A8: EQ-007 | B8: Sprayer | C8: Hardi | D8: Navigator 4000 | E8: 2022 | F8: HARD-NAV-JKL | G8: N/A | H8: Green Acres | I8: North Field | J8: Active | K8: Own | L8: 44671 | M8: CropCare Solutions | N8: 380000 | O8: 320000 | P8: Units-of-Use | Q8: 10 | R8: Hours | S8: 800 | T8: 45809 | U8: 500 | V8: 300 | W8: 800 | X8: 45992 | Y8: N/A | Z8: N/A | AA8: N/A | AB8: 24 | AC8: N/A | AD8: Trailed sprayer, 4000L tank capacity | AE8: CropCare Solutions | AF8: 46497 | AG8: INS-HAR-007 | AH8: [URL] | AI8: Excellent | AJ8: High | AK8: 10 | AL8: 15000 | AM8: 0 | AN8: Precision spraying equipment
A9: EQ-008 | B9: Tool | C9: Bosch | D9: Angle Grinder | E9: 2024 | F9: BOSCH-AG-MNP | G9: N/A | H9: Sunny Fields | I9: Workshop | J9: Active | K9: Own | L9: 45332 | M9: FarmTools | N9: 1500 | O9: 1400 | P9: Straight | Q9: 5 | R9: none | S9: N/A | T9: N/A | U9: N/A | V9: N/A | W9: N/A | X9: N/A | Y9: Electric | Z9: N/A | AA9: N/A | AB9: N/A | AC9: N/A | AD9: Corded angle grinder, general workshop use | AE9: FarmTools | AF9: 46428 | AG9: N/A | AH9: [URL] | AI9: Good | AJ9: Low | AK9: 0 | AL9: 100 | AM9: 0 | AN9: General workshop tool
A10: EQ-009 | B10: Other | C10: Custom Build | D10: Water Trailer | E10: 2023 | F10: CUST-WT-QRS | G10: N/A | H10: Harvest Valley | I10: N/A | J10: Active | K10: Own | L10: 45108 | M10: Local Fabricator | N10: 25000 | O10: 22000 | P10: Straight | Q10: 10 | R10: none | S10: N/A | T10: N/A | U10: N/A | V10: N/A | W10: N/A | X10: N/A | Y10: N/A | Z10: N/A | AA10: N/A | AB10: N/A | AC10: N/A | AD10: 1000L water tank on trailer | AE10: N/A | AF10: N/A | AG10: INS-CBT-009 | AH10: [URL] | AI10: Good | AJ10: Medium | AK10: 0 | AL10: 500 | AM10: 0 | AN10: Used for transporting water to fields
A11: EQ-010 | B11: Tractor | C11: Massey | D11: Ferguson 5710S | E11: 2020 | F11: MF5710S-TUVW | G11: CW789-012 | H11: Green Acres | I11: South Field | J11: In Repair | K11: Own | L11: 44075 | M11: AgriSuppliers | N11: 850000 | O11: 600000 | P11: Straight | Q11: 12 | R11: Hours | S11: 4500 | T11: 45698 | U11: 4000 | V11: 500 | W11: 4500 | X11: 45879 | Y11: Diesel | Z11: 10 L/hr | AA11: 420/85R34 / 4 | AB11: N/A | AC11: 75 kW / 100 HP | AD11: Minor engine issue, awaiting inspection | AE11: FarmMechanics | AF11: 45901 | AG11: INS-MF-010 | AH11: [URL] | AI11: Needs Repair | AJ11: High | AK11: 80 | AL11: 18000 | AM11: 0 | AN11: Secondary tractor, currently not operational

Sheet Sheep Flock
A1: Farm / Paddock Name | B1: Flock ID / Name | C1: Breed / Strain | D1: Head Count | E1: Rams | F1: Ewes | G1: Lambs | H1: Avg Age (months) | I1: Avg Weight (kg) | J1: Body Condition Score (avg, 1–5) | K1: Mortality (last 30 days) | L1: Mortality Reason | M1: Health Treatments Given | N1: Vaccination Status | O1: Deworming Status | P1: Reproduction Cycle | Q1: Lambing % | R1: Weaning % | S1: Wool / Fleece Weight (kg per head) | T1: Shearing Date | U1: Feed / Supplement | V1: Grazing Area | W1: Water Source | X1: Input Costs (R/head) | Y1: Output Value (R/head) | Z1: Net Margin | AA1: Responsible Person | AB1: Notes
A2: Green Pastures | B2: Breeding Ewes | C2: Merino | D2: 450 | E2: 15 | F2: 300 | G2: 135 | H2: 48 | I2: 65 | J2: 3.5 | K2: 1 | L2: Disease | M2: Deworming, Antibiotics | N2: Up to date | O2: Due | P2: Pregnant | Q2: 1.3 | R2: 1.15 | S2: 4.8 | T2: 45884 | U2: Lucerne & Grain | V2: North Field | W2: Borehole | X2: 120 | Y2: 250 | Z2: 130 | AA2: Sarah Jones | AB2: Good health, some ewes due for deworming.
A3: River Bend | B3: Replacement Lambs | C3: Dorper | D3: 220 | E3: 0 | F3: 0 | G3: 220 | H3: 8 | I3: 35 | J3: 3 | K3: 2 | L3: Accidents | M3: Vitamin boost | N3: Up to date | O3: Up to date | P3: Weaning | Q3: 0 | R3: 0 | S3: 0 | T3: N/A | U3: Starter Pellets | V3: East Paddock | W3: River | X3: 80 | Y3: 150 | Z3: 70 | AA3: Tom Green | AB3: Growing well, preparing for breeding next year.
A4: Mountain View | B4: Rams | C4: Merino | D4: 20 | E4: 20 | F4: 0 | G4: 0 | H4: 60 | I4: 90 | J4: 4 | K4: 0 | L4: N/A | M4: Hoof trimming | N4: Up to date | O4: Up to date | P4: Not mated | Q4: 0 | R4: 0 | S4: 6.2 | T4: 45858 | U4: High Protein Pellets | V4: Small Enclosure | W4: Spring | X4: 150 | Y4: 0 | Z4: -150 | AA4: Jane Doe | AB4: Excellent condition.
A5: Sunny Hills | B5: Sale Group | C5: Dorper | D5: 180 | E5: 10 | F5: 50 | G5: 120 | H5: 10 | I5: 40 | J5: 3.2 | K5: 3 | L5: Predators | M5: None | N5: Up to date | O5: Up to date | P5: N/A | Q5: 0 | R5: 0 | S5: 0 | T5: N/A | U5: Finishing Feed | V5: Holding Pen | W5: Dam | X5: 95 | Y5: 180 | Z5: 85 | AA5: Peter Black | AB5: Ready for market next week.
A6: Green Pastures | B6: Young Ewes | C6: Dorper | D6: 150 | E6: 0 | F6: 150 | G6: 0 | H6: 24 | I6: 55 | J6: 3.7 | K6: 4 | L6: Other | M6: Multivitamin injection | N6: Due | O6: Up to date | P6: Not mated | Q6: 0 | R6: 0 | S6: 0 | T6: N/A | U6: Hay & Mineral Lick | V6: West Paddock | W6: Borehole | X6: 100 | Y6: 0 | Z6: -100 | AA6: Sarah Jones | AB6: Awaiting ram introduction.
A7: River Bend | B7: Lambing Ewes | C7: Merino | D7: 200 | E7: 5 | F7: 200 | G7: 190 | H7: 54 | I7: 70 | J7: 3.8 | K7: 3 | L7: Disease | M7: Fly strike treatment | N7: Up to date | O7: Due | P7: Lambing | Q7: 0.95 | R7: 0.8 | S7: 5 | T7: 45870 | U7: Pre-lambing Ration | V7: Nursery Field | W7: River | X7: 130 | Y7: 260 | Z7: 130 | AA7: Tom Green | AB7: Many new lambs, monitoring ewes closely.
A8: Mountain View | B8: Weaner Lambs | C8: Merino | D8: 100 | E8: 0 | F8: 0 | G8: 100 | H8: 6 | I8: 28 | J8: 2.9 | K8: 1 | L8: Accidents | M8: Coccidiostat | N8: Up to date | O8: Up to date | P8: Weaning | Q8: 0 | R8: 0 | S8: 0 | T8: N/A | U8: Lamb Grower Pellets | V8: South Field | W8: Spring | X8: 70 | Y8: 140 | Z8: 70 | AA8: Jane Doe | AB8: Recently weaned, adjusting well.
A9: Sunny Hills | B9: Old Ewes | C9: Dorper | D9: 80 | E9: 0 | F9: 80 | G9: 0 | H9: 72 | I9: 60 | J9: 3.1 | K9: 2 | L9: Disease | M9: Arthritis medication | N9: Due | O9: Due | P9: Not mated | Q9: 0 | R9: 0 | S9: 0 | T9: 45843 | U9: Maintenance Feed | V9: Old Ewe Paddock | W9: Dam | X9: 110 | Y9: 0 | Z9: -110 | AA9: Peter Black | AB9: Cull group for end of year.
A10: Green Pastures | B10: Mixed Lambs | C10: Merino/Dorper | D10: 180 | E10: 0 | F10: 0 | G10: 180 | H10: 7 | I10: 32 | J10: 3.1 | K10: 2 | L10: Predators | M10: None | N10: Up to date | O10: Up to date | P10: N/A | Q10: 0 | R10: 0 | S10: 0 | T10: N/A | U10: Mixed Pellets | V10: Mid Field | W10: Borehole | X10: 85 | Y10: 160 | Z10: 75 | AA10: Sarah Jones | AB10: Regular checks for predator activity.

Sheet Rooibos - JOHAN BRAND - Werklik
A1: PRODUKSIE DATA VAN CLOUDSKRAAL BOERDERY PER PLAAS, LAND EN GESKATTE OPBRENGS EN WERKLIKE OES IN KILOGRAMME.
A3: PLAASNAAM | B3: LANDNAAM | C3: LANDNO | D3: GEPLANT | E3: HEKTAAR | F3: 2004 WERKLIK | G3: 2005 WERKLIK | H3: 2006_WERKLIK | I3: 2007_WERKLIK | J3: 2008_WERKLIK | K3: 2009_WERKLIK | L3: 2010_WERKLIK | M3: 2011_WERKLIK | N3: 2012_WERKLIK | O3: 2013_WERKLIK | P3: 2014_WERKLIK | Q3: 2015_WERKLIK | R3: 2016_WERKLIK | S3: 2017_WERKLIK | T3: 2018_WERKLIK | U3: 2019_WERKLIK | V3: 2020_WERKLIK | W3: 2021_WERKLIK | X3: 2022_WERKLIK | Y3: 2023_WERKLIK | Z3: 2024_WERKLIK | AA3: 25_WERKLIK
A4: Biekoes | B4: Latboskamp | C4: B7 | D4: 2021 | E4: 22.958092 | F4: N.A | G4: N.A | H4: N.A | I4: N.A | J4: 0 | K4: 6000 | L4: 5000 | M4: 0 | N4: 0 | O4: 0 | P4: 0 | Q4: 0 | R4: 0 | S4: 12000 | T4: 0 | U4: 8000 | V4: 6000 | W4: 0 | X4: 0 | Y4: 4000 | Z4: 4000 | AA4: 4000
A5: Cloudskraal | B5: Pleisterbosrug | C5: C3 | D5: 2021 | E5: 31.037026 | F5: N.A | G5: N.A | H5: N.A | I5: N.A | J5: 12000 | K5: 4000 | L5: 0 | M5: 0 | N5: 0 | O5: 7000 | P5: 13000 | Q5: 10000 | R5: 0 | S5: 0 | T5: 0 | U5: 6000 | V5: 2000 | W5: 0 | X5: 0 | Y5: 12000 | Z5: 18000 | AA5: 18000
A6: Biekoes | B6: Eerste Land | C6: B1 | D6: 2022 | E6: 21.198753 | F6: N.A | G6: N.A | H6: N.A | I6: N.A | J6: 0 | K6: 0 | L6: 0 | M6: 8000 | N6: 0 | O6: 0 | P6: 0 | Q6: 0 | R6: 0 | S6: 16000 | T6: 0 | U6: 12000 | V6: 5000 | W6: 0 | X6: 0 | Y6: 0 | Z6: 6000 | AA6: 5000
A7: Biekoes | B7: Straatklip | C7: B3 | D7: 2022 | E7: 17.032996 | F7: N.A | G7: N.A | H7: N.A | I7: N.A | J7: 0 | K7: 4000 | L7: 0 | M7: 0 | N7: 0 | O7: 0 | P7: 0 | Q7: 0 | R7: 12000 | S7: 17000 | T7: 0 | U7: 5000 | V7: 0 | W7: 0 | X7: 0 | Y7: 0 | Z7: 7500 | AA7: 8000
A8: Cloudskraal | B8: Groenvlei | C8: C11 | D8: 2022 | E8: 41.979349 | F8: N.A | G8: N.A | H8: N.A | I8: N.A | J8: 15000 | K8: 20000 | L8: 25000 | M8: 10000 | N8: 5000 | O8: 0 | P8: 9000 | Q8: 15000 | R8: 30000 | S8: 20000 | T8: 0 | U8: 5000 | V8: 3000 | W8: 0 | X8: 0 | Y8: 0 | Z8: 16000 | AA8: 30000
A9: Cloudskraal | B9: Volkshuise | C9: C15 | D9: 2022 | E9: 7.293002 | F9: N.A | G9: N.A | H9: N.A | I9: N.A | J9: 0 | K9: 0 | L9: 0 | M9: 0 | N9: 0 | O9: 0 | P9: 0 | Q9: 0 | R9: 3500 | S9: 3500 | T9: 0 | U9: 2000 | V9: 0 | W9: 0 | X9: 0 | Y9: 0 | Z9: 2000 | AA9: 2000
A10: Cloudskraal | B10: Onderdam | C10: C17 | D10: 2022 | E10: 16.8566 | F10: N.A | G10: N.A | H10: N.A | I10: N.A | J10: 0 | K10: 0 | L10: 0 | M10: 0 | N10: 0 | O10: 0 | P10: 2000 | Q10: 6000 | R10: 11000 | S10: 7000 | T10: 0 | U10: 1000 | V10: 0 | W10: 12000 | X10: 0 | Y10: 0 | Z10: 7000 | AA10: 5000
A11: Cloudskraal | B11: Eerste Spilpunt | C11: C8 | D11: 2022 | E11: 21.626902 | F11: N.A | G11: N.A | H11: N.A | I11: N.A | J11: 8000 | K11: 0 | L11: 0 | M11: 0 | N11: 0 | O11: 0 | P11: 8000 | Q11: 8000 | R11: 4000 | S11: 0 | T11: 0 | U11: 6000 | V11: 15000 | W11: 15000 | X11: 0 | Y11: 0 | Z11: 8000 | AA11: 12000
A12: Glenridge | B12: Sandkamp | C12: G4 | D12: 2022 | E12: 52.153611 | F12: N.A | G12: N.A | H12: N.A | I12: N.A | J12: 5000 | K12: 0 | L12: 0 | M12: 25000 | N12: 20000 | O12: 15000 | P12: 10000 | Q12: 0 | R12: 0 | S12: 21000 | T12: 0 | U12: 6000 | V12: 2000 | W12: 8000 | X12: 0 | Y12: 0 | Z12: 31000 | AA12: 31000
A13: Glenridge | B13: Vleikamp B | C13: G8 | D13: 2022 | E13: 23.028313 | F13: N.A | G13: N.A | H13: N.A | I13: N.A | J13: 9000 | K13: 0 | L13: 0 | M13: 0 | N13: 0 | O13: 0 | P13: 0 | Q13: 0 | R13: 0 | S13: 4000 | T13: 0 | U13: 8000 | V13: 7000 | W13: 7000 | X13: 0 | Y13: 0 | Z13: 12000 | AA13: 10000
A14: Biekoes | B14: Tuinkamp | C14: B14 | D14: 2023 | E14: 8.6880705 | F14: N.A | G14: N.A | H14: N.A | I14: N.A | J14: 0 | K14: 0 | L14: 0 | M14: 0 | N14: 0 | O14: 0 | P14: 0 | Q14: 0 | R14: 0 | S14: 0 | T14: 0 | U14: 0 | V14: 0 | W14: 0 | X14: 0 | Y14: 0 | Z14: 0 | AA14: 2000
A15: Biekoes | B15: Bokant Dam | C15: B6 | D15: 2023 | E15: 42.898925 | F15: N.A | G15: N.A | H15: N.A | I15: N.A | J15: 0 | K15: 7000 | L15: 5000 | M15: 0 | N15: 0 | O15: 0 | P15: 0 | Q15: 0 | R15: 0 | S15: 25000 | T15: 0 | U15: 20000 | V15: 8000 | W15: 0 | X15: 0 | Y15: 0 | Z15: 0 | AA15: 12000
... A39: Glenridge | B39: Roosklawerkamp | C39: G6 | D39: 2027 | E39: 66.66814 | F39: N.A | G39: N.A | H39: N.A | I39: N.A | J39: 0 | K39: 0 | L39: 0 | M39: 0 | N39: 0 | O39: 10000 | P39: 15000 | Q39: 8000 | R39: 0 | S39: 0 | T39: 0 | U39: 0 | V39: 0 | W39: 10000 | X39: 20000 | Y39: 15000 | Z39: 12000 | AA39: 0
A40: Biekoes | B40: Donkiekamp | C40: B10 | D40: Braak | E40: 15.962332 | F40: N.A | G40: N.A | H40: N.A | I40: N.A | J40: 0 | K40: 0 | L40: 0 | M40: 0 | N40: 0 | O40: 0 | P40: 0 | Q40: 0 | R40: 0 | S40: 1000 | T40: 0 | U40: 2000 | V40: 0 | W40: 0 | X40: 0 | Y40: 0 | Z40: 0 | AA40: 0
A41: Biekoes | B41: Agter Huiskamp | C41: B11 | D41: Braak | E41: 15.497613 | F41: N.A | G41: N.A | H41: N.A | I41: N.A | J41: 0 | K41: 6000 | L41: 5000 | M41: 0 | N41: 0 | O41: 0 | P41: 0 | Q41: 0 | R41: 0 | S41: 8000 | T41: 0 | U41: 0 | V41: 0 | W41: 0 | X41: 0 | Y41: 0 | Z41: 0 | AA41: 0
A42: Biekoes | B42: Voor Huiskamp | C42: B13 | D42: Braak | E42: 27.417025 | F42: N.A | G42: N.A | H42: N.A | I42: N.A | J42: 0 | K42: 0 | L42: 0 | M42: 0 | N42: 0 | O42: 0 | P42: 0 | Q42: 0 | R42: 0 | S42: 2000 | T42: 0 | U42: 0 | V42: 0 | W42: 0 | X42: 0 | Y42: 0 | Z42: 0 | AA42: 0
A43: Cloudskraal | B43: By Begraafplaas | C43: C16 | D43: Braak | E43: 8.7379009 | F43: N.A | G43: N.A | H43: N.A | I43: N.A | J43: 0 | K43: 0 | L43: 0 | M43: 0 | N43: 0 | O43: 0 | P43: 0 | Q43: 0 | R43: 0 | S43: 0 | T43: 0 | U43: 1000 | V43: 0 | W43: 0 | X43: 0 | Y43: 0 | Z43: 0 | AA43: 0
A44: Glenridge | B44: Garskamp | C44: G10 | D44: Braak | E44: 10.953934 | F44: N.A | G44: N.A | H44: N.A | I44: N.A | J44: 1500 | K44: 0 | L44: 0 | M44: 0 | N44: 0 | O44: 2500 | P44: 2000 | Q44: 0 | R44: 0 | S44: 0 | T44: 0 | U44: 0 | V44: 0 | W44: 0 | X44: 0 | Y44: 0 | Z44: 0 | AA44: 0
A45: Glenridge | B45: Bokant Bloekoms | C45: G11 | D45: Braak | E45: 14.3042 | F45: N.A | G45: N.A | H45: N.A | I45: N.A | J45: 0 | K45: 0 | L45: 0 | M45: 0 | N45: 0 | O45: 6000 | P45: 4000 | Q45: 3000 | R45: 1500 | S45: 0 | T45: 0 | U45: 2000 | V45: 2000 | W45: 4000 | X45: 0 | Y45: 0 | Z45: 0 | AA45: 0
A46: Glenridge | B46: Klipland | C46: G12 | D46: Braak | E46: 4.6495434 | F46: N.A | G46: N.A | H46: N.A | I46: N.A | J46: 0 | K46: 0 | L46: 0 | M46: 0 | N46: 0 | O46: 2000 | P46: 0 | Q46: 0 | R46: 0 | S46: 0 | T46: 0 | U46: 0 | V46: 0 | W46: 0 | X46: 0 | Y46: 0 | Z46: 0 | AA46: 0
A47: Glenridge | B47: Teerpadland | C47: G7a | D47: Braak | E47: 7.6130991 | F47: N.A | G47: N.A | H47: N.A | I47: N.A | J47: 0 | K47: 0 | L47: 0 | M47: 0 | N47: 0 | O47: 1500 | P47: 10000 | Q47: 3000 | R47: 0 | S47: 3000 | T47: 1000 | U47: 1500 | V47: 0 | W47: 0 | X47: 0 | Y47: 0 | Z47: 0 | AA47: 0
A48: Glenridge | B48: Popelierland | C48: G7b | D48: Braak | E48: 1.2286475 | F48: N.A | G48: N.A | H48: N.A | I48: N.A | J48: 0 | K48: 0 | L48: 0 | M48: 0 | N48: 0 | O48: 1500 | P48: 10000 | Q48: 3000 | R48: 0 | S48: 1000 | T48: 500 | U48: 200 | V48: 0 | W48: 0 | X48: 0 | Y48: 0 | Z48: 0 | AA48: 0
A49: Glenridge | B49: Noordland | C49: G7c | D49: Braak | E49: 0.79330274 | F49: N.A | G49: N.A | H49: N.A | I49: N.A | J49: 0 | K49: 0 | L49: 0 | M49: 0 | N49: 0 | O49: 1500 | P49: 10000 | Q49: 3000 | R49: 0 | S49: 1000 | T49: 500 | U49: 500 | V49: 0 | W49: 0 | X49: 0 | Y49: 0 | Z49: 0 | AA49: 0
A50: Glenridge | B50: Plantjiesland | C50: G7d | D50: Braak | E50: 8.1720683 | F50: N.A | G50: N.A | H50: N.A | I50: N.A | J50: 0 | K50: 0 | L50: 0 | M50: 0 | N50: 0 | O50: 1500 | P50: 10000 | Q50: 3000 | R50: 0 | S50: 3000 | T50: 1000 | U50: 1000 | V50: 0 | W50: 0 | X50: 0 | Y50: 0 | Z50: 0 | AA50: 0
A51: Glenridge | B51: Deur-ry-land | C51: G7e | D51: Braak | E51: 3.2858996 | F51: N.A | G51: N.A | H51: N.A | I51: N.A | J51: 0 | K51: 0 | L51: 0 | M51: 0 | N51: 0 | O51: 1500 | P51: 10000 | Q51: 3000 | R51: 0 | S51: 0 | T51: 1000 | U51: 2000 | V51: 0 | W51: 0 | X51: 0 | Y51: 0 | Z51: 0 | AA51: 0
... A56: Garsland | B56: Stoorland | C56: GA6 | D56: Braak | E56: 3.0312657 | F56: N.A | G56: N.A | H56: N.A | I56: N.A | J56: 5000 | K56: 2000 | L56: 0 | M56: 0 | N56: 0 | O56: 0 | P56: 0 | Q56: 0 | R56: 0 | S56: 0 | T56: 0 | U56: 0 | V56: 0 | W56: 0 | X56: 0 | Y56: 0 | Z56: 0 | AA56: 0
D57: =SUM(Johan_Brand_Skatting_en_Werklik[GEPLANT]) -> 72868 | E57: =SUM(Johan_Brand_Skatting_en_Werklik[HEKTAAR]) -> 1049.3503 | I57: =SUM(Johan_Brand_Skatting_en_Werklik[2007_WERKLIK]) -> 0 | J57: =SUM(Johan_Brand_Skatting_en_Werklik[2008_WERKLIK]) -> 213000 | K57: =SUM(Johan_Brand_Skatting_en_Werklik[2009_WERKLIK]) -> 118000 | L57: =SUM(Johan_Brand_Skatting_en_Werklik[2010_WERKLIK]) -> 172000 | M57: =SUM(Johan_Brand_Skatting_en_Werklik[2011_WERKLIK]) -> 196000 | N57: =SUM(Johan_Brand_Skatting_en_Werklik[2012_WERKLIK]) -> 151000 | O57: =SUM(Johan_Brand_Skatting_en_Werklik[2013_WERKLIK]) -> 133500 | P57: =SUM(Johan_Brand_Skatting_en_Werklik[2014_WERKLIK]) -> 191500 | Q57: =SUM(Johan_Brand_Skatting_en_Werklik[2015_WERKLIK]) -> 124000 | R57: =SUM(Johan_Brand_Skatting_en_Werklik[2016_WERKLIK]) -> 203000 | S57: =SUM(Johan_Brand_Skatting_en_Werklik[2017_WERKLIK]) -> 321500 | T57: =SUM(Johan_Brand_Skatting_en_Werklik[2018_WERKLIK]) -> 17000 | U57: =SUM(Johan_Brand_Skatting_en_Werklik[2019_WERKLIK]) -> 194200 | V57: =SUM(Johan_Brand_Skatting_en_Werklik[2020_WERKLIK]) -> 158000 | W57: =SUM(Johan_Brand_Skatting_en_Werklik[2021_WERKLIK]) -> 193500 | X57: =SUM(Johan_Brand_Skatting_en_Werklik[2022_WERKLIK]) -> 110000 | Y57: =SUM(Johan_Brand_Skatting_en_Werklik[2023_WERKLIK]) -> 112000 | Z57: =SUM(Johan_Brand_Skatting_en_Werklik[2024_WERKLIK]) -> 190000 | AA57: =SUM(Johan_Brand_Skatting_en_Werklik[25_WERKLIK]) -> 244500
A59: PLAASNAAM | B59: LANDNAAM | C59: LANDNO | D59: GEPLANT | E59: HEKTAAR | F59: 2004 WERKLIK | G59: 2005 WERKLIK | H59: 2006_WERKLIK | I59: 2007_WERKLIK | J59: 2008_WERKLIK | K59: 2009_WERKLIK | L59: 2010_WERKLIK | M59: 2011_WERKLIK | N59: 2012_WERKLIK | O59: 2013_WERKLIK | P59: 2014_WERKLIK | Q59: 2015_WERKLIK | R59: 2016_WERKLIK | S59: 2017_WERKLIK | T59: 2018_WERKLIK | U59: 2019_WERKLIK | V59: 2020_WERKLIK | W59: 2021_WERKLIK | X59: 2022_WERKLIK | Y59: 2023_WERKLIK | Z59: 2024_WERKLIK | AA59: 25_WERKLIK
A60: Biekoes | B60: Spilpuntkamp | C60: B2 | D60: 2026 | E60: 18.110613 | F60: N.A | G60: N.A | H60: N.A | I60: N.A | J60: 0 | K60: 0 | L60: 331.29746 | M60: 220.86497 | N60: 0 | O60: 0 | P60: 0 | Q60: 0 | R60: 441.72994 | S60: 1380.4061 | T60: 0 | U60: 552.16243 | V60: 0 | W60: 0 | X60: 0 | Y60: 0 | Z60: 0 | AA60: 0
A61: Biekoes | B61: Eerste Land | C61: B1 | D61: 2022 | E61: 21.198753 | F61: N.A | G61: N.A | H61: N.A | I61: N.A | J61: 0 | K61: 0 | L61: 0 | M61: 377.38068 | N61: 0 | O61: 0 | P61: 0 | Q61: 0 | R61: 0 | S61: 754.76136 | T61: 0 | U61: 566.07102 | V61: 235.86293 | W61: 0 | X61: 0 | Y61: 0 | Z61: 283.03551 | AA61: 235.86293
A62: Biekoes | B62: Windpompkamp | C62: B4 | D62: 2026 | E62: 11.609562 | F62: N.A | G62: N.A | H62: N.A | I62: N.A | J62: 0 | K62: 86.135893 | L62: 0 | M62: 0 | N62: 0 | O62: 0 | P62: 0 | Q62: 0 | R62: 0 | S62: 258.40768 | T62: 0 | U62: 172.27179 | V62: 172.27179 | W62: 0 | X62: 0 | Y62: 0 | Z62: 86.135893 | AA62: 344.54357
A63: Cloudskraal | B63: Om Groenvlei | C63: C9 | D63: 2026 | E63: 29.471117 | F63: N.A | G63: N.A | H63: N.A | I63: N.A | J63: 848.28817 | K63: 237.52069 | L63: 0 | M63: 610.76748 | N63: 475.04137 | O63: 407.17832 | P63: 0 | Q63: 0 | R63: 1017.9458 | S63: 1017.9458 | T63: 0 | U63: 0 | V63: 0 | W63: 0 | X63: 0 | Y63: 305.38374 | Z63: 508.9729 | AA63: 508.9729
A64: Cloudskraal | B64: Groenvlei | C64: C11 | D64: 2022 | E64: 41.979349 | F64: N.A | G64: N.A | H64: N.A | I64: N.A | J64: 357.31855 | K64: 476.42473 | L64: 595.53091 | M64: 238.21237 | N64: 119.10618 | O64: 0 | P64: 214.39113 | Q64: 357.31855 | R64: 714.6371 | S64: 476.42473 | T64: 0 | U64: 119.10618 | V64: 71.46371 | W64: 0 | X64: 0 | Y64: 0 | Z64: 381.13979 | AA64: 714.6371
A65: Glenridge | B65: Driehoekkamp | C65: G1 | D65: 2026 | E65: 16.552962 | F65: N.A | G65: N.A | H65: N.A | I65: N.A | J65: 302.06075 | K65: 181.23645 | L65: 604.1215 | M65: 362.4729 | N65: 0 | O65: 0 | P65: 90.618225 | Q65: 302.06075 | R65: 302.06075 | S65: 604.1215 | T65: 0 | U65: 120.8243 | V65: 422.88505 | W65: 724.9458 | X65: 181.23645 | Y65: 0 | Z65: 0 | AA65: 0
A66: Glenridge | B66: Vleikamp B | C66: G8 | D66: 2022 | E66: 23.028313 | F66: N.A | G66: N.A | H66: N.A | I66: N.A | J66: 390.82324 | K66: 0 | L66: 0 | M66: 0 | N66: 0 | O66: 0 | P66: 0 | Q66: 0 | R66: 0 | S66: 173.69922 | T66: 0 | U66: 347.39844 | V66: 303.97363 | W66: 303.97363 | X66: 0 | Y66: 0 | Z66: 521.09765 | AA66: 434.24804
A67: Glenridge | B67: Baken se land | C67: G3 | D67: 2025 | E67: 53.627997 | F67: N.A | G67: N.A | H67: N.A | I67: N.A | J67: 186.46977 | K67: 55.94093 | L67: 0 | M67: 372.93953 | N67: 372.93953 | O67: 279.70465 | P67: 186.46977 | Q67: 0 | R67: 0 | S67: 149.17581 | T67: 0 | U67: 559.4093 | V67: 186.46977 | W67: 0 | X67: 372.93953 | Y67: 559.4093 | Z67: 484.82139 | AA67: 0
A68: Glenridge | B68: Sandkamp | C68: G4 | D68: 2022 | E68: 52.153611 | F68: N.A | G68: N.A | H68: N.A | I68: N.A | J68: 95.87064 | K68: 0 | L68: 0 | M68: 479.3532 | N68: 383.48256 | O68: 287.61192 | P68: 191.74128 | Q68: 0 | R68: 0 | S68: 402.65669 | T68: 0 | U68: 115.04477 | V68: 38.348256 | W68: 153.39302 | X68: 0 | Y68: 0 | Z68: 594.39797 | AA68: 594.39797
A69: Glenridge | B69: By Resovoir | C69: G14 | D69: 2026 | E69: 6.7325786 | F69: N.A | G69: N.A | H69: N.A | I69: N.A | J69: 0 | K69: 0 | L69: 0 | M69: 0 | N69: 0 | O69: 445.5945 | P69: 445.5945 | Q69: 148.5315 | R69: 0 | S69: 0 | T69: 0 | U69: 0 | V69: 148.5315 | W69: 445.5945 | X69: 0 | Y69: 0 | Z69: 0 | AA69: 519.86025
A70: Glenridge | B70: Teen Pierre | C70: G13 | D70: 2026 | E70: 21.956941 | F70: N.A | G70: N.A | H70: N.A | I70: N.A | J70: 136.63105 | K70: 91.087369 | L70: 0 | M70: 0 | N70: 500.98053 | O70: 683.15527 | P70: 500.98053 | Q70: 227.71842 | R70: 0 | S70: 182.17474 | T70: 0 | U70: 273.26211 | V70: 182.17474 | W70: 91.087369 | X70: 455.43684 | Y70: 273.26211 | Z70: 318.80579 | AA70: 182.17474
A71: Glenridge | B71: Bokant Bloekoms | C71: G11 | D71: Braak | E71: 14.3042 | F71: N.A | G71: N.A | H71: N.A | I71: N.A | J71: 0 | K71: 0 | L71: 0 | M71: 0 | N71: 0 | O71: 419.45722 | P71: 279.63815 | Q71: 209.72861 | R71: 104.8643 | S71: 0 | T71: 0 | U71: 139.81907 | V71: 139.81907 | W71: 279.63815 | X71: 0 | Y71: 0 | Z71: 0 | AA71: 0
A72: Cloudskraal | B72: Teen Kromvlei | C72: C1 | D72: 2023 | E72: 30.751305 | F72: N.A | G72: N.A | H72: N.A | I72: N.A | J72: 130.07578 | K72: 97.556834 | L72: 0 | M72: 0 | N72: 0 | O72: 130.07578 | P72: 97.556834 | Q72: 0 | R72: 0 | S72: 65.037889 | T72: 0 | U72: 65.037889 | V72: 97.556834 | W72: 0 | X72: 0 | Y72: 0 | Z72: 0 | AA72: 585.341
A73: Cloudskraal | B73: Agter Pomp | C73: C5 | D73: 2024 | E73: 32.66615 | F73: N.A | G73: N.A | H73: N.A | I73: N.A | J73: 673.48004 | K73: 0 | L73: 765.31822 | M73: 551.02912 | N73: 551.02912 | O73: 244.90183 | P73: 0 | Q73: 0 | R73: 1102.0582 | S73: 918.38187 | T73: 0 | U73: 0 | V73: 91.838187 | W73: 229.59547 | X73: 306.12729 | Y73: 183.67637 | Z73: 0 | AA73: 0
A74: Cloudskraal | B74: Links van vlei | C74: C6 | D74: 2024 | E74: 8.5061747 | F74: N.A | G74: N.A | H74: N.A | I74: N.A | J74: 293.90415 | K74: 0 | L74: 470.24663 | M74: 352.68497 | N74: 0 | O74: 0 | P74: 0 | Q74: 0 | R74: 470.24663 | S74: 352.68497 | T74: 0 | U74: 0 | V74: 235.12332 | W74: 352.68497 | X74: 352.68497 | Y74: 117.56166 | Z74: 0 | AA74: 0
A75: Cloudskraal | B75: Uilklip | C75: C13 | D75: 2027 | E75: 27.339304 | F75: N.A | G75: N.A | H75: N.A | I75: N.A | J75: 438.92852 | K75: 146.30951 | L75: 0 | M75: 0 | N75: 548.66065 | O75: 548.66065 | P75: 146.30951 | Q75: 0 | R75: 0 | S75: 0 | T75: 0 | U75: 365.77376 | V75: 256.04163 | W75: 329.19639 | X75: 0 | Y75: 0 | Z75: 365.77376 | AA75: 365.77376
A76: Cloudskraal | B76: Heelagter | C76: C19 | D76: 2023 | E76: 33.530577 | F76: N.A | G76: N.A | H76: N.A | I76: N.A | J76: 715.76461 | K76: 0 | L76: 447.35288 | M76: 596.47051 | N76: 447.35288 | O76: 0 | P76: 178.94115 | Q76: 298.23525 | R76: 298.23525 | S76: 0 | T76: 0 | U76: 0 | V76: 447.35288 | W76: 447.35288 | X76: 149.11763 | Y76: 0 | Z76: 0 | AA76: 656.11756
A77: Cloudskraal | B77: Tweede Spilpunt | C77: C18 | D77: 2025 | E77: 21.68274 | F77: N.A | G77: N.A | H77: N.A | I77: N.A | J77: 0 | K77: 0 | L77: 737.91413 | M77: 507.31596 | N77: 230.59817 | O77: 0 | P77: 0 | Q77: 0 | R77: 92.239266 | S77: 276.7178 | T77: 0 | U77: 276.7178 | V77: 0 | W77: 138.3589 | X77: 322.83743 | Y77: 322.83743 | Z77: 0 | AA77: 0
A78: Cloudskraal | B78: By Begraafplaas | C78: C16 | D78: Braak | E78: 8.7379009 | F78: N.A | G78: N.A | H78: N.A | I78: N.A | J78: 0 | K78: 0 | L78: 0 | M78: 0 | N78: 0 | O78: 0 | P78: 0 | Q78: 0 | R78: 0 | S78: 0 | T78: 0 | U78: 114.44396 | V78: 0 | W78: 0 | X78: 0 | Y78: 0 | Z78: 0 | AA78: 0
A79: Cloudskraal | B79: Volkshuise | C79: C15 | D79: 2022 | E79: 7.293002 | F79: N.A | G79: N.A | H79: N.A | I79: N.A | J79: 0 | K79: 0 | L79: 0 | M79: 0 | N79: 0 | O79: 0 | P79: 0 | Q79: 0 | R79: 479.91211 | S79: 479.91211 | T79: 0 | U79: 274.23549 | V79: 0 | W79: 0 | X79: 0 | Y79: 0 | Z79: 274.23549 | AA79: 274.23549
A80: Cloudskraal | B80: Eerste Spilpunt | C80: C8 | D80: 2022 | E80: 21.626902 | F80: N.A | G80: N.A | H80: N.A | I80: N.A | J80: 369.90966 | K80: 0 | L80: 0 | M80: 0 | N80: 0 | O80: 0 | P80: 369.90966 | Q80: 369.90966 | R80: 184.95483 | S80: 0 | T80: 0 | U80: 277.43225 | V80: 693.58062 | W80: 693.58062 | X80: 0 | Y80: 0 | Z80: 369.90966 | AA80: 554.86449
A81: Cloudskraal | B81: Pleisterbosrug | C81: C3 | D81: 2021 | E81: 31.037026 | F81: N.A | G81: N.A | H81: N.A | I81: N.A | J81: 386.63498 | K81: 128.87833 | L81: 0 | M81: 0 | N81: 0 | O81: 225.53707 | P81: 418.85456 | Q81: 322.19582 | R81: 0 | S81: 0 | T81: 0 | U81: 193.31749 | V81: 64.439163 | W81: 0 | X81: 0 | Y81: 386.63498 | Z81: 579.95247 | AA81: 579.95247
A82: Cloudskraal | B82: Hardekop | C82: C2 | D82: 2024 | E82: 21.015682 | F82: N.A | G82: N.A | H82: N.A | I82: N.A | J82: 713.75271 | K82: 571.00217 | L82: 713.75271 | M82: 285.50108 | N82: 0 | O82: 0 | P82: 761.33622 | Q82: 571.00217 | R82: 380.66811 | S82: 0 | T82: 0 | U82: 0 | V82: 285.50108 | W82: 713.75271 | X82: 0 | Y82: 237.91757 | Z82: 0 | AA82: 142.75054
A83: Glenridge | B83: Langland by Bloekoms | C83: G9 | D83: 2026 | E83: 18.753786 | F83: N.A | G83: N.A | H83: N.A | I83: N.A | J83: 159.9677 | K83: 106.64513 | L83: 0 | M83: 0 | N83: 0 | O83: 213.29026 | P83: 533.22565 | Q83: 533.22565 | R83: 159.9677 | S83: 0 | T83: 0 | U83: 159.9677 | V83: 266.61283 | W83: 319.93539 | X83: 426.58052 | Y83: 213.29026 | Z83: 0 | AA83: 0
A84: Glenridge | B84: Garskamp | C84: G10 | D84: Braak | E84: 10.953934 | F84: N.A | G84: N.A | H84: N.A | I84: N.A | J84: 136.93711 | K84: 0 | L84: 0 | M84: 0 | N84: 0 | O84: 228.22852 | P84: 182.58281 | Q84: 0 | R84: 0 | S84: 0 | T84: 0 | U84: 0 | V84: 0 | W84: 0 | X84: 0 | Y84: 0 | Z84: 0 | AA84: 0
A85: Glenridge | B85: Klipland | C85: G12 | D85: Braak | E85: 4.6495434 | F85: N.A | G85: N.A | H85: N.A | I85: N.A | J85: 0 | K85: 0 | L85: 0 | M85: 0 | N85: 0 | O85: 430.14976 | P85: 0 | Q85: 0 | R85: 0 | S85: 0 | T85: 0 | U85: 0 | V85: 0 | W85: 0 | X85: 0 | Y85: 0 | Z85: 0 | AA85: 0
A86: Garsland | B86: Denneboomland | C86: GA4 | D86: Braak | E86: 2.2378144 | F86: N.A | G86: N.A | H86: N.A | I86: N.A | J86: 0 | K86: 0 | L86: 0 | M86: 0 | N86: 0 | O86: 0 | P86: 0 | Q86: 0 | R86: 0 | S86: 0 | T86: 0 | U86: 0 | V86: 0 | W86: 0 | X86: 0 | Y86: 0 | Z86: 0 | AA86: 0
A87: Garsland | B87: Driehoekkamp | C87: GA2 | D87: 2025 | E87: 9.3738299 | F87: N.A | G87: N.A | H87: N.A | I87: N.A | J87: 533.39991 | K87: 213.35996 | L87: 0 | M87: 640.07989 | N87: 426.71993 | O87: 213.35996 | P87: 0 | Q87: 0 | R87: 426.71993 | S87: 640.07989 | T87: 160.01997 | U87: 0 | V87: 426.71993 | W87: 640.07989 | X87: 0 | Y87: 106.67998 | Z87: 0 | AA87: 0
A88: Garsland | B88: Spilpuntland | C88: GA3 | D88: 2023 | E88: 14.306519 | F88: N.A | G88: N.A | H88: N.A | I88: N.A | J88: 559.18565 | K88: 139.79641 | L88: 0 | M88: 559.18565 | N88: 209.69462 | O88: 139.79641 | P88: 0 | Q88: 0 | R88: 0 | S88: 489.28744 | T88: 314.54193 | U88: 314.54193 | V88: 69.898206 | W88: 349.49103 | X88: 0 | Y88: 0 | Z88: 0 | AA88: 419.38924
A89: Glenridge | B89: Vleikamp A | C89: G2 | D89: 2026 | E89: 21.868015 | F89: N.A | G89: N.A | H89: N.A | I89: N.A | J89: 411.55999 | K89: 0 | L89: 0 | M89: 365.8311 | N89: 365.8311 | O89: 91.457775 | P89: 91.457775 | Q89: 228.64444 | R89: 228.64444 | S89: 228.64444 | T89: 0 | U89: 137.18666 | V89: 365.8311 | W89: 548.74665 | X89: 0 | Y89: 0 | Z89: 0 | AA89: 0
A90: Cloudskraal | B90: Regs van vlei | C90: C7 | D90: 2025 | E90: 27.682425 | F90: N.A | G90: N.A | H90: N.A | I90: N.A | J90: 0 | K90: 361.24002 | L90: 722.48005 | M90: 541.86004 | N90: 288.99202 | O90: 0 | P90: 0 | Q90: 0 | R90: 433.48803 | S90: 433.48803 | T90: 0 | U90: 0 | V90: 108.37201 | W90: 433.48803 | X90: 650.23204 | Y90: 325.11602 | Z90: 0 | AA90: 0
A91: Glenridge | B91: Roosklawerkamp | C91: G6 | D91: 2027 | E91: 66.66814 | F91: N.A | G91: N.A | H91: N.A | I91: N.A | J91: 0 | K91: 0 | L91: 0 | M91: 0 | N91: 0 | O91: 149.99669 | P91: 224.99503 | Q91: 119.99735 | R91: 0 | S91: 0 | T91: 0 | U91: 0 | V91: 0 | W91: 149.99669 | X91: 299.99337 | Y91: 224.99503 | Z91: 179.99602 | AA91: 0
A92: Cloudskraal | B92: Onderdam | C92: C17 | D92: 2022 | E92: 16.8566 | F92: N.A | G92: N.A | H92: N.A | I92: N.A | J92: 0 | K92: 0 | L92: 0 | M92: 0 | N92: 0 | O92: 0 | P92: 118.64789 | Q92: 355.94368 | R92: 652.56341 | S92: 415.26762 | T92: 0 | U92: 59.323946 | V92: 0 | W92: 711.88735 | X92: 0 | Y92: 0 | Z92: 415.26762 | AA92: 296.61973
A93: Cloudskraal | B93: Langland | C93: C12 | D93: 2023 | E93: 20.644499 | F93: N.A | G93: N.A | H93: N.A | I93: N.A | J93: 0 | K93: 339.07337 | L93: 775.02485 | M93: 484.39053 | N93: 242.19527 | O93: 0 | P93: 96.878107 | Q93: 387.51243 | R93: 484.39053 | S93: 242.19527 | T93: 0 | U93: 145.31716 | V93: 387.51243 | W93: 581.26864 | X93: 0 | Y93: 0 | Z93: 0 | AA93: 484.39053
A94: Biekoes | B94: Hardekop | C94: B8 | D94: 2026 | E94: 34.192859 | F94: N.A | G94: N.A | H94: N.A | I94: N.A | J94: 0 | K94: 0 | L94: 0 | M94: 0 | N94: 0 | O94: 0 | P94: 0 | Q94: 0 | R94: 0 | S94: 380.19634 | T94: 0 | U94: 292.45872 | V94: 116.98349 | W94: 0 | X94: 0 | Y94: 0 | Z94: 219.34404 | AA94: 292.45872
A95: Biekoes | B95: Bokant Dam | C95: B6 | D95: 2023 | E95: 42.898925 | F95: N.A | G95: N.A | H95: N.A | I95: N.A | J95: 0 | K95: 163.17425 | L95: 116.55304 | M95: 0 | N95: 0 | O95: 0 | P95: 0 | Q95: 0 | R95: 0 | S95: 582.76518 | T95: 0 | U95: 466.21214 | V95: 186.48486 | W95: 0 | X95: 0 | Y95: 0 | Z95: 0 | AA95: 279.72729
A96: Biekoes | B96: Latboskamp | C96: B7 | D96: 2021 | E96: 22.958092 | F96: N.A | G96: N.A | H96: N.A | I96: N.A | J96: 0 | K96: 261.34576 | L96: 217.78813 | M96: 0 | N96: 0 | O96: 0 | P96: 0 | Q96: 0 | R96: 0 | S96: 522.69152 | T96: 0 | U96: 348.46101 | V96: 261.34576 | W96: 0 | X96: 0 | Y96: 174.23051 | Z96: 174.23051 | AA96: 174.23051
A97: Biekoes | B97: Agter Huiskamp | C97: B11 | D97: Braak | E97: 15.497613 | F97: N.A | G97: N.A | H97: N.A | I97: N.A | J97: 0 | K97: 387.15639 | L97: 322.63032 | M97: 0 | N97: 0 | O97: 0 | P97: 0 | Q97: 0 | R97: 0 | S97: 516.20852 | T97: 0 | U97: 0 | V97: 0 | W97: 0 | X97: 0 | Y97: 0 | Z97: 0 | AA97: 0
A98: Biekoes | B98: Stoorkamp | C98: B9 | D98: 2026 | E98: 35.395201 | F98: N.A | G98: N.A | H98: N.A | I98: N.A | J98: 0 | K98: 197.76692 | L98: 141.26209 | M98: 0 | N98: 0 | O98: 0 | P98: 0 | Q98: 0 | R98: 0 | S98: 0 | T98: 0 | U98: 197.76692 | V98: 226.01934 | W98: 141.26209 | X98: 0 | Y98: 0 | Z98: 0 | AA98: 0
A99: Biekoes | B99: Straatklip | C99: B3 | D99: 2022 | E99: 17.032996 | F99: N.A | G99: N.A | H99: N.A | I99: N.A | J99: 0 | K99: 234.83832 | L99: 0 | M99: 0 | N99: 0 | O99: 0 | P99: 0 | Q99: 0 | R99: 704.51495 | S99: 998.06285 | T99: 0 | U99: 293.5479 | V99: 0 | W99: 0 | X99: 0 | Y99: 0 | Z99: 440.32184 | AA99: 469.67663
A100: Garsland | B100: Huiskamp | C100: GA5 | D100: Braak | E100: 5.9436036 | F100: N.A | G100: N.A | H100: N.A | I100: N.A | J100: 841.24049 | K100: 336.4962 | L100: 0 | M100: 0 | N100: 0 | O100: 0 | P100: 0 | Q100: 0 | R100: 0 | S100: 0 | T100: 504.7443 | U100: 757.11644 | V100: 504.7443 | W100: 420.62025 | X100: 0 | Y100: 0 | Z100: 0 | AA100: 0
A101: Garsland | B101: Noordkamp | C101: GA1 | D101: Braak | E101: 14.273504 | F101: N.A | G101: N.A | H101: N.A | I101: N.A | J101: 350.2994 | K101: 140.11976 | L101: 0 | M101: 0 | N101: 0 | O101: 0 | P101: 0 | Q101: 0 | R101: 280.23952 | S101: 560.47904 | T101: 210.17964 | U101: 140.11976 | V101: 70.05988 | W101: 175.1497 | X101: 0 | Y101: 0 | Z101: 0 | AA101: 0
A102: Garsland | B102: Stoorland | C102: GA6 | D102: Braak | E102: 3.0312657 | F102: N.A | G102: N.A | H102: N.A | I102: N.A | J102: 1649.476 | K102: 659.79039 | L102: 0 | M102: 0 | N102: 0 | O102: 0 | P102: 0 | Q102: 0 | R102: 0 | S102: 0 | T102: 0 | U102: 0 | V102: 0 | W102: 0 | X102: 0 | Y102: 0 | Z102: 0 | AA102: 0
A103: Glenridge | B103: Teerpadland | C103: G7a | D103: Braak | E103: 7.6130991 | F103: N.A | G103: N.A | H103: N.A | I103: N.A | J103: 0 | K103: 0 | L103: 0 | M103: 0 | N103: 0 | O103: 197.02883 | P103: 1313.5255 | Q103: 394.05766 | R103: 0 | S103: 394.05766 | T103: 131.35255 | U103: 197.02883 | V103: 0 | W103: 0 | X103: 0 | Y103: 0 | Z103: 0 | AA103: 0
A104: Glenridge | B104: Popelierland | C104: G7b | D104: Braak | E104: 1.2286475 | F104: N.A | G104: N.A | H104: N.A | I104: N.A | J104: 0 | K104: 0 | L104: 0 | M104: 0 | N104: 0 | O104: 1220.8546 | Q104: 2441.7093 | R104: 0 | S104: 813.90309 | T104: 406.95155 | U104: 162.78062 | V104: 0 | W104: 0 | X104: 0 | Y104: 0 | Z104: 0 | AA104: 0
A105: Glenridge | B105: Noordland | C105: G7c | D105: Braak | E105: 0.79330274 | F105: N.A | G105: N.A | H105: N.A | I105: N.A | J105: 0 | K105: 0 | L105: 0 | M105: 0 | N105: 0 | O105: 1890.8292 | Q105: 3781.6585 | R105: 0 | S105: 1260.5528 | T105: 630.27641 | U105: 630.27641 | V105: 0 | W105: 0 | X105: 0 | Y105: 0 | Z105: 0 | AA105: 0
A106: Glenridge | B106: Plantjiesland | C106: G7d | D106: Braak | E106: 8.1720683 | F106: N.A | G106: N.A | H106: N.A | I106: N.A | J106: 0 | K106: 0 | L106: 0 | M106: 0 | N106: 0 | O106: 183.55206 | P106: 1223.6804 | Q106: 367.10413 | R106: 0 | S106: 367.10413 | T106: 122.36804 | U106: 122.36804 | V106: 0 | W106: 0 | X106: 0 | Y106: 0 | Z106: 0 | AA106: 0
A107: Glenridge | B107: Deur-ry-land | C107: G7e | D107: Braak | E107: 3.2858996 | F107: N.A | G107: N.A | H107: N.A | I107: N.A | J107: 0 | K107: 0 | L107: 0 | M107: 0 | N107: 0 | O107: 456.496 | P107: 3043.3067 | Q107: 912.992 | R107: 0 | S107: 0 | T107: 304.33067 | U107: 608.66133 | V107: 0 | W107: 0 | X107: 0 | Y107: 0 | Z107: 0 | AA107: 0
A108: Glenridge | B108: Puntland | C108: G7f | D108: Braak | E108: 4.258856 | F108: N.A | G108: N.A | H108: N.A | I108: N.A | J108: 0 | K108: 0 | L108: 0 | M108: 0 | N108: 0 | O108: 352.20726 | P108: 2348.0484 | Q108: 704.41452 | R108: 0 | S108: 0 | T108: 234.80484 | U108: 0 | V108: 0 | W108: 0 | X108: 0 | Y108: 0 | Z108: 0 | AA108: 0
A109: Biekoes | B109: Donkiekamp | C109: B10 | D109: Braak | E109: 15.962332 | F109: N.A | G109: N.A | H109: N.A | I109: N.A | J109: 0 | K109: 0 | L109: 0 | M109: 0 | N109: 0 | O109: 0 | P109: 0 | Q109: 0 | R109: 0 | S109: 62.647487 | T109: 0 | U109: 125.29497 | V109: 0 | W109: 0 | X109: 0 | Y109: 0 | Z109: 0 | AA109: 0
A110: Biekoes | B110: Teen Grasberg | C110: B12 | D110: 2026 | E110: 11.799041 | F110: N.A | G110: N.A | H110: N.A | I110: N.A | J110: 0 | K110: 0 | L110: 0 | M110: 0 | N110: 0 | O110: 0 | P110: 0 | Q110: 0 | R110: 0 | S110: 0 | T110: 0 | U110: 0 | V110: 254.25796 | W110: 423.76326 | X110: 508.51591 | Y110: 254.25796 | Z110: 0 | AA110: 0
A111: Biekoes | B111: Voor Huiskamp | C111: B13 | D111: Braak | E111: 27.417025 | F111: N.A | G111: N.A | H111: N.A | I111: N.A | J111: 0 | K111: 0 | L111: 0 | M111: 0 | N111: 0 | O111: 0 | P111: 0 | Q111: 0 | R111: 0 | S111: 72.947375 | T111: 0 | U111: 0 | V111: 0 | W111: 0 | X111: 0 | Y111: 0 | Z111: 0 | AA111: 0
A112: Biekoes | B112: Tuinkamp | C112: B14 | D112: 2023 | E112: 8.6880705 | F112: N.A | G112: N.A | H112: N.A | I112: N.A | J112: 0 | K112: 0 | L112: 0 | M112: 0 | N112: 0 | O112: 0 | P112: 0 | Q112: 0 | R112: 0 | S112: 0 | T112: 0 | U112: 0 | V112: 0 | W112: 0 | X112: 0 | Y112: 0 | Z112: 0 | AA112: 230.20071
D113: =SUM(Table1[GEPLANT]) -> 72868 | E113: =SUM(Table1[HEKTAAR]) -> 1049.3503 | I113: =SUM(Table1[2007_WERKLIK]) -> 0 | J113: =AVERAGEIF(Table1[2008_WERKLIK], ">0") -> 464.43386 | K113: =AVERAGEIF(Table1[2009_WERKLIK], ">0") -> 244.03895 | L113: =AVERAGEIF(Table1[2010_WERKLIK], ">0") -> 497.23378 | M113: =AVERAGEIF(Table1[2011_WERKLIK], ">0") -> 443.90235 | N113: =AVERAGEIF(Table1[2012_WERKLIK], ">0") -> 368.75885 | O113: =AVERAGEIF(Table1[2013_WERKLIK], ">0") -> 410.39672 | P113: =AVERAGEIF(Table1[2014_WERKLIK], ">0") -> 567.76912 | Q113: =AVERAGEIF(Table1[2015_WERKLIK], ">0") -> 651.69802 | R113: =AVERAGEIF(Table1[2016_WERKLIK], ">0") -> 448.00404 | S113: =AVERAGEIF(Table1[2017_WERKLIK], ">0") -> 499.18445 | T113: =AVERAGEIF(Table1[2018_WERKLIK], ">0") -> 301.95699 | U113: =AVERAGEIF(Table1[2019_WERKLIK], ">0") -> 276.87882 | V113: =AVERAGEIF(Table1[2020_WERKLIK], ">0") -> 236.06697 | W113: =AVERAGEIF(Table1[2021_WERKLIK], ">0") -> 391.95373 | X113: =AVERAGEIF(Table1[2022_WERKLIK], ">0") -> 365.97291 | Y113: =AVERAGEIF(Table1[2023_WERKLIK], ">0") -> 263.23235 | Z113: =AVERAGEIF(Table1[2024_WERKLIK], ">0") -> 364.5552 | AA113: =AVERAGEIF(Table1[25_WERKLIK], ">0") -> 406.10549
O116: =O107*35 -> 15977.36

Sheet Rooibos - Johan Brand - Oeskatt
A1: PRODUKSIE DATA VAN CLOUDSKRAAL BOERDERY PER PLAAS, LAND EN GESKATTE OPBRENGS EN WERKLIKE OES IN KILOGRAMME.
F2: 2004
A3: PLAASNAAM | B3: LANDNAAM | C3: LANDNO | D3: GEPLANT | E3: HEKTAAR | F3: 2004 OESSKAT | G3: 2005 OESSKAT | H3: 2006 OESSKAT | I3: 2007_OESSKAT | J3: 2008_OESSKAT | K3: 2009_OESSKAT | L3: 2010_OESSKAT | M3: 2011_OESSKAT | N3: 2012_OESSKAT | O3: 2013_OESSKAT | P3: 2014_OESSKAT | Q3: 2015_OESSKAT | R3: 2016_OESSKAT | S3: 2017_OESSKAT | T3: 2018_OESSKAT | U3: 2019_OESSKAT | V3: 2020_OESSKAT | W3: 2021_OESSKAT | X3: 2022_OESSKAT | Y3: 2023_OESSKAT | Z3: 2024_OESSKAT | AA3: 2025_OESSKAT | AB3: 2026_OESSKAT | AC3: 2027_OESSKAT | AD3: 2028_OESSKAT
A4: Biekoes | B4: Spilpuntkamp | C4: B2 | D4: 2026 | E4: 18.110613 | F4: 0 | G4: 0 | H4: 15000 | I4: N.A | J4: 0 | K4: 0 | L4: 6000 | M4: 1000 | N4: 4000 | O4: 2000 | P4: 2000 | Q4: 2000 | R4: 4500 | S4: 34000 | T4: 9000 | U4: 10000 | V4: 0 | W4: 0 | X4: 15000 | Y4: 0 | Z4: 2000 | AA4: 0 | AB4: 0 | AC4: 2000 | AD4: 9000
A5: Biekoes | B5: Eerste Land | C5: B1 | D5: 2022 | E5: 21.198753 | F5: 0 | G5: 0 | H5: 0 | I5: N.A | J5: 0 | K5: 0 | L5: 0 | M5: 8000 | N5: 8000 | O5: 8000 | P5: 6000 | Q5: 0 | R5: 0 | S5: 16000 | T5: 16000 | U5: 12000 | V5: 5000 | W5: 0 | X5: 0 | Y5: 0 | Z5: 6000 | AA5: 4000 | AB5: 5000 | AC5: 0 | AD5: 0
A6: Biekoes | B6: Windpompkamp | C6: B4 | D6: 2026 | E6: 11.609562 | F6: 0 | G6: 0 | H6: 5000 | I6: N.A | J6: 3000 | K6: 2000 | L6: 0 | M6: 0 | N6: 0 | O6: 1000 | P6: 0 | Q6: 0 | R6: 0 | S6: 3000 | T6: 3000 | U6: 2000 | V6: 2000 | W6: 0 | X6: 1000 | Y6: 3000 | Z6: 1000 | AA6: 4000 | AB6: 0 | AC6: 1000 | AD6: 5000
A7: Cloudskraal | B7: Om Groenvlei | C7: C9 | D7: 2026 | E7: 29.471117 | F7: 0 | G7: 0 | H7: 25000 | I7: N.A | J7: 25000 | K7: 10000 | L7: 0 | M7: 18000 | N7: 18000 | O7: 12000 | P7: 0 | Q7: 3000 | R7: 12000 | S7: 30000 | T7: 8000 | U7: 0 | V7: 0 | W7: 3000 | X7: 3000 | Y7: 9000 | Z7: 15000 | AA7: 15000 | AB7: 0 | AC7: 0 | AD7: 0
A8: Cloudskraal | B8: Groenvlei | C8: C11 | D8: 2022 | E8: 41.979349 | F8: 24000 | G8: 15000 | H8: 15000 | I8: N.A | J8: 15000 | K8: 25000 | L8: 20000 | M8: 10000 | N8: 5000 | O8: 0 | P8: 0 | Q8: 30000 | R8: 15000 | S8: 20000 | T8: 10000 | U8: 5000 | V8: 5000 | W8: 3000 | X8: 0 | Y8: 0 | Z8: 16000 | AA8: 24000 | AB8: 20000 | AC8: 0 | AD8: 0
A9: Glenridge | B9: Driehoekkamp | C9: G1 | D9: 2026 | E9: 16.552962 | F9: 12000 | G9: 10000 | H9: 3000 | I9: N.A | J9: 5000 | K9: 5000 | L9: 3000 | M9: 6000 | N9: 0 | O9: 0 | P9: 0 | Q9: 8000 | R9: 5000 | S9: 12000 | T9: 5000 | U9: 2000 | V9: 7000 | W9: 12000 | X9: 5000 | Y9: 0 | Z9: 0 | AA9: 0 | AB9: 0 | AC9: 7000 | AD9: 0
A10: Glenridge | B10: Vleikamp B | C10: G8 | D10: 2022 | E10: 23.028313 | F10: 1000 | G10: 0 | H10: 25000 | I10: N.A | J10: 9000 | K10: 0 | L10: 0 | M10: 0 | N10: 0 | O10: 0 | P10: 0 | Q10: 0 | R10: 0 | S10: 5000 | T10: 3 | U10: 8000 | V10: 7000 | W10: 7000 | X10: 7000 | Y10: 0 | Z10: 12000 | AA10: 10000 | AB10: 5000 | AC10: 0 | AD10: 0
A11: Glenridge | B11: Baken se land | C11: G3 | D11: 2025 | E11: 53.627997 | F11: 0 | G11: 0 | H11: 0 | I11: N.A | J11: 10000 | K11: 10000 | L11: 0 | M11: 20000 | N11: 20000 | O11: 15000 | P11: 10000 | Q11: 0 | R11: 0 | S11: 10000 | T11: 25000 | U11: 30000 | V11: 20000 | W11: 0 | X11: 27000 | Y11: 30000 | Z11: 26000 | AA11: 0 | AB11: 0 | AC11: 0 | AD11: 0
A12: Glenridge | B12: Sandkamp | C12: G4 | D12: 2022 | E12: 52.153611 | F12: 7000 | G12: 0 | H12: 10000 | I12: N.A | J12: 18000 | K12: 0 | L12: 0 | M12: 25000 | N12: 20000 | O12: 15000 | P12: 10000 | Q12: 0 | R12: 0 | S12: 25000 | T12: 20000 | U12: 6000 | V12: 6000 | W12: 8000 | X12: 0 | Y12: 0 | Z12: 31000 | AA12: 31000 | AB12: 15000 | AC12: 10000 | AD12: 0
A13: Glenridge | B13: By Resovoir | C13: G14 | D13: 2026 | E13: 6.7325786 | F13: 1000 | G13: 1000 | H13: 0 | I13: N.A | J13: 0 | K13: 0 | L13: 0 | M13: 0 | N13: 0 | O13: 3000 | P13: 3000 | Q13: 3000 | R13: 0 | S13: 0 | T13: 0 | U13: 0 | V13: 1000 | W13: 3000 | X13: 0 | Y13: 0 | Z13: 0 | AA13: 3500 | AB13: 3500 | AC13: 2000 | AD13: 0
A14: Glenridge | B14: Teen Pierre | C14: G13 | D14: 2026 | E14: 21.956941 | F14: 0 | G14: 0 | H14: 15000 | I14: N.A | J14: 11000 | K14: 11000 | L14: 0 | M14: 11000 | N14: 11000 | O14: 15000 | P14: 11000 | Q14: 6000 | R14: 0 | S14: 4000 | T14: 8000 | U14: 6000 | V14: 4000 | W14: 2000 | X14: 11000 | Y14: 6000 | Z14: 7000 | AA14: 4000 | AB14: 0 | AC14: 0 | AD14: 0
A15: Glenridge | B15: Bokant Bloekoms | C15: G11 | D15: Braak | E15: 14.3042 | F15: 6000 | G15: 2000 | H15: 1000 | I15: N.A | J15: 0 | K15: 0 | L15: 0 | M15: 0 | N15: 0 | O15: 6000 | P15: 8000 | Q15: 3000 | R15: 1500 | S15: 0 | T15: 0 | U15: 2000 | V15: 2000 | W15: 4000 | X15: 5000 | Y15: 0 | Z15: 0 | AA15: 0 | AB15: 0 | AC15: 0 | AD15: 0
A16: Cloudskraal | B16: Teen Kromvlei | C16: C1 | D16: 2023 | E16: 30.751305 | F16: 0 | G16: 0 | H16: 0 | I16: N.A | J16: 4000 | K16: 4000 | L16: 0 | M16: 0 | N16: 0 | O16: 4000 | P16: 3000 | Q16: 0 | R16: 0 | S16: 2000 | T16: 6000 | U16: 2000 | V16: 3000 | W16: 7500 | X16: 0 | Y16: 0 | Z16: 0 | AA16: 13000 | AB16: 21000 | AC16: 0 | AD16: 0
A17: Cloudskraal | B17: Agter Pomp | C17: C5 | D17: 2024 | E17: 32.66615 | F17: 0 | G17: 0 | H17: 30000 | I17: N.A | J17: 22000 | K17: 5000 | L17: 12000 | M17: 18000 | N17: 18000 | O17: 0 | P17: 0 | Q17: 3000 | R17: 15000 | S17: 36000 | T17: 8000 | U17: 0 | V17: 3000 | W17: 7500 | X17: 10000 | Y17: 6000 | Z17: 0 | AA17: 0 | AB17: 15000 | AC17: 25000 | AD17: 0
A18: Cloudskraal | B18: Links van vlei | C18: C6 | D18: 2024 | E18: 8.5061747 | F18: 0 | G18: 0 | H18: 6000 | I18: N.A | J18: 2500 | K18: 1000 | L18: 4000 | M18: 3000 | N18: 0 | O18: 0 | P18: 0 | Q18: 1000 | R18: 3500 | S18: 3500 | T18: 2000 | U18: 0 | V18: 2000 | W18: 3000 | X18: 3000 | Y18: 1000 | Z18: 0 | AA18: 0 | AB18: 2500 | AC18: 6000 | AD18: 0
A19: Cloudskraal | B19: Uilklip | C19: C13 | D19: 2027 | E19: 27.339304 | F19: 3000 | G19: 0 | H19: 0 | I19: N.A | J19: 12000 | K19: 10000 | L19: 0 | M19: 0 | N19: 15000 | O19: 15000 | P19: 4000 | Q19: 0 | R19: 0 | S19: 3000 | T19: 12000 | U19: 10000 | V19: 7000 | W19: 9000 | X19: 0 | Y19: 0 | Z19: 10000 | AA19: 10000 | AB19: 0 | AC19: 0 | AD19: 0
A20: Cloudskraal | B20: Heelagter | C20: C19 | D20: 2023 | E20: 33.530577 | F20: 0 | G20: 0 | H20: 0 | I20: N.A | J20: 24000 | K20: 5000 | L20: 20000 | M20: 20000 | N20: 15000 | O20: 6000 | P20: 9000 | Q20: 14000 | R20: 7000 | S20: 7000 | T20: 0 | U20: 0 | V20: 25000 | W20: 15000 | X20: 12000 | Y20: 0 | Z20: 0 | AA20: 22000 | AB20: 20000 | AC20: 15000 | AD20: 0
A21: Cloudskraal | B21: Tweede Spilpunt | C21: C18 | D21: 2025 | E21: 21.68274 | F21: 2000 | G21: 0 | H21: 0 | I21: N.A | J21: 0 | K21: 3000 | L21: 11000 | M21: 11000 | N21: 6000 | O21: 0 | P21: 0 | Q21: 0 | R21: 0 | S21: 6000 | T21: 8000 | U21: 6000 | V21: 0 | W21: 3000 | X21: 7000 | Y21: 7000 | Z21: 0 | AA21: 0 | AB21: 0 | AC21: 0 | AD21: 0
A22: Cloudskraal | B22: By Begraafplaas | C22: C16 | D22: Braak | E22: 8.7379009 | F22: 6000 | G22: 5000 | H22: 4500 | I22: N.A | J22: 0 | K22: 0 | L22: 0 | M22: 0 | N22: 0 | O22: 0 | P22: 0 | Q22: 0 | R22: 0 | S22: 0 | T22: 0 | U22: 1000 | V22: 0 | W22: 0 | X22: 0 | Y22: 0 | Z22: 0 | AA22: 0 | AB22: 0 | AC22: 0 | AD22: 0
A23: Cloudskraal | B23: Volkshuise | C23: C15 | D23: 2022 | E23: 7.293002 | F23: 1000 | G23: 1000 | H23: 3000 | I23: N.A | J23: 0 | K23: 0 | L23: 0 | M23: 0 | N23: 0 | O23: 0 | P23: 0 | Q23: 1000 | R23: 2500 | S23: 3500 | T23: 1000 | U23: 2000 | V23: 0 | W23: 0 | X23: 2000 | Y23: 0 | Z23: 2000 | AA23: 2000 | AB23: 1000 | AC23: 0 | AD23: 0
A24: Cloudskraal | B24: Eerste Spilpunt | C24: C8 | D24: 2022 | E24: 21.626902 | F24: 2500 | G24: 0 | H24: 15000 | I24: N.A | J24: 8000 | K24: 0 | L24: 0 | M24: 0 | N24: 0 | O24: 0 | P24: 12000 | Q24: 8000 | R24: 4000 | S24: 0 | T24: 0 | U24: 6000 | V24: 15000 | W24: 15000 | X24: 0 | Y24: 0 | Z24: 8000 | AA24: 12000 | AB24: 8000 | AC24: 0 | AD24: 0
A25: Cloudskraal | B25: Pleisterbosrug | C25: C3 | D25: 2021 | E25: 31.037026 | F25: 0 | G25: 0 | H25: 8000 | I25: N.A | J25: 12000 | K25: 4000 | L25: 0 | M25: 0 | N25: 0 | O25: 7000 | P25: 18000 | Q25: 10000 | R25: 8000 | S25: 3000 | T25: 3000 | U25: 6000 | V25: 6000 | W25: 0 | X25: 0 | Y25: 10000 | Z25: 18000 | AA25: 18000 | AB25: 10000 | AC25: 0 | AD25: 0
A26: Cloudskraal | B26: Hardekop | C26: C2 | D26: 2024 | E26: 21.015682 | F26: 5000 | G26: 5000 | H26: 5000 | I26: N.A | J26: 15000 | K26: 15000 | L26: 10000 | M26: 8000 | N26: 0 | O26: 0 | P26: 8000 | Q26: 16000 | R26: 6000 | S26: 5000 | T26: 0 | U26: 0 | V26: 3000 | W26: 15000 | X26: 11000 | Y26: 5000 | Z26: 0 | AA26: 3000 | AB26: 12000 | AC26: 12000 | AD26: 0
A27: Glenridge | B27: Langland by Bloekoms | C27: G9 | D27: 2026 | E27: 18.753786 | F27: 0 | G27: 0 | H27: 0 | I27: N.A | J27: 3000 | K27: 2000 | L27: 0 | M27: 0 | N27: 0 | O27: 4000 | P27: 10000 | Q27: 10000 | R27: 3000 | S27: 0 | T27: 0 | U27: 3000 | V27: 5000 | W27: 6000 | X27: 8000 | Y27: 4000 | Z27: 0 | AA27: 0 | AB27: 0 | AC27: 0 | AD27: 0
A28: Glenridge | B28: Garskamp | C28: G10 | D28: Braak | E28: 10.953934 | F28: 5000 | G28: 0 | H28: 0 | I28: N.A | J28: 1500 | K28: 1000 | L28: 0 | M28: 0 | N28: 0 | O28: 2500 | P28: 2500 | Q28: 0 | R28: 0 | S28: 0 | T28: 0 | U28: 0 | V28: 1000 | W28: 0 | X28: 0 | Y28: 0 | Z28: 0 | AA28: 0 | AB28: 0 | AC28: 0 | AD28: 0
A29: Glenridge | B29: Klipland | C29: G12 | D29: Braak | E29: 4.6495434 | F29: 5000 | G29: 1000 | H29: 0 | I29: N.A | J29: 0 | K29: 0 | L29: 0 | M29: 0 | N29: 0 | O29: 2000 | P29: 2000 | Q29: 0 | R29: 0 | S29: 0 | T29: 0 | U29: 0 | V29: 0 | W29: 0 | X29: 0 | Y29: 0 | Z29: 0 | AA29: 0 | AB29: 0 | AC29: 0 | AD29: 0
A30: Garsland | B30: Denneboomland | C30: GA4 | D30: Braak | E30: 2.2378144 | F30: 0 | G30: 0 | H30: 0 | I30: N.A | J30: 0 | K30: 0 | L30: 0 | M30: 0 | N30: 0 | O30: 0 | P30: 0 | Q30: 0 | R30: 0 | S30: 0 | T30: 0 | U30: 0 | V30: 0 | W30: 0 | X30: 0 | Y30: 0 | Z30: 0 | AA30: 0 | AB30: 0 | AC30: 0 | AD30: 0
A31: Garsland | B31: Driehoekkamp | C31: GA2 | D31: 2025 | E31: 9.3738299 | F31: 0 | G31: 4000 | H31: 9000 | I31: N.A | J31: 6000 | K31: 2000 | L31: 0 | M31: 5000 | N31: 6000 | O31: 2000 | P31: 0 | Q31: 1000 | R31: 2500 | S31: 6000 | T31: 2000 | U31: 1000 | V31: 5000 | W31: 6000 | X31: 3000 | Y31: 1000 | Z31: 0 | AA31: 0 | AB31: 0 | AC31: 0 | AD31: 0
A32: Garsland | B32: Spilpuntland | C32: GA3 | D32: 2023 | E32: 14.306519 | F32: 0 | G32: 0 | H32: 7000 | I32: N.A | J32: 10000 | K32: 2000 | L32: 0 | M32: 8000 | N32: 5000 | O32: 2000 | P32: 0 | Q32: 0 | R32: 0 | S32: 7000 | T32: 5000 | U32: 4500 | V32: 2000 | W32: 5000 | X32: 0 | Y32: 0 | Z32: 0 | AA32: 4200 | AB32: 6000 | AC32: 3000 | AD32: 0
A33: Glenridge | B33: Vleikamp A | C33: G2 | D33: 2026 | E33: 21.868015 | F33: 1000 | G33: 0 | H33: 25000 | I33: N.A | J33: 9000 | K33: 0 | L33: 0 | M33: 10000 | N33: 8000 | O33: 2000 | P33: 0 | Q33: 5000 | R33: 5000 | S33: 5000 | T33: 2000 | U33: 3000 | V33: 8000 | W33: 12000 | X33: 0 | Y33: 0 | Z33: 0 | AA33: 0 | AB33: 0 | AC33: 0 | AD33: 0
A34: Cloudskraal | B34: Regs van vlei | C34: C7 | D34: 2025 | E34: 27.682425 | F34: 0 | G34: 6000 | H34: 8000 | I34: N.A | J34: 0 | K34: 15000 | L34: 15000 | M34: 15000 | N34: 8000 | O34: 0 | P34: 0 | Q34: 3000 | R34: 6000 | S34: 12000 | T34: 8000 | U34: 0 | V34: 3000 | W34: 12000 | X34: 18000 | Y34: 9000 | Z34: 0 | AA34: 0 | AB34: 0 | AC34: 0 | AD34: 0
A35: Glenridge | B35: Roosklawerkamp | C35: G6 | D35: 2027 | E35: 66.66814 | F35: 0 | G35: 0 | H35: 0 | I35: N.A | J35: 0 | K35: 0 | L35: 0 | M35: 0 | N35: 0 | O35: 10000 | P35: 25000 | Q35: 15000 | R35: 0 | S35: 0 | T35: 0 | U35: 0 | V35: 10000 | W35: 10000 | X35: 20000 | Y35: 15000 | Z35: 12000 | AA35: 0 | AB35: 0 | AC35: 0 | AD35: 0
A36: Cloudskraal | B36: Onderdam | C36: C17 | D36: 2022 | E36: 16.8566 | F36: 3000 | G36: 3000 | H36: 0 | I36: N.A | J36: 0 | K36: 0 | L36: 0 | M36: 0 | N36: 0 | O36: 0 | P36: 0 | Q36: 6000 | R36: 5000 | S36: 7000 | T36: 3000 | U36: 1000 | V36: 6000 | W36: 12000 | X36: 0 | Y36: 0 | Z36: 7000 | AA36: 5000 | AB36: 2000 | AC36: 0 | AD36: 0
A37: Cloudskraal | B37: Langland | C37: C12 | D37: 2023 | E37: 20.644499 | F37: 12000 | G37: 8000 | H37: 7000 | I37: N.A | J37: 16000 | K37: 10000 | L37: 7000 | M37: 10000 | N37: 5000 | O37: 0 | P37: 0 | Q37: 8000 | R37: 8000 | S37: 5000 | T37: 3000 | U37: 3000 | V37: 8000 | W37: 12000 | X37: 8000 | Y37: 0 | Z37: 0 | AA37: 8000 | AB37: 5000 | AC37: 5000 | AD37: 0
A38: Biekoes | B38: Hardekop | C38: B8 | D38: 2026 | E38: 34.192859 | F38: 0 | G38: 0 | H38: 0 | I38: N.A | J38: 0 | K38: 0 | L38: 0 | M38: 0 | N38: 0 | O38: 0 | P38: 0 | Q38: 0 | R38: 0 | S38: 13000 | T38: 6000 | U38: 10000 | V38: 4000 | W38: 0 | X38: 2000 | Y38: 6000 | Z38: 7500 | AA38: 10000 | AB38: 0 | AC38: 5000 | AD38: 20000
A39: Biekoes | B39: Bokant Dam | C39: B6 | D39: 2023 | E39: 42.898925 | F39: 0 | G39: 0 | H39: 0 | I39: N.A | J39: 12000 | K39: 10000 | L39: 5000 | M39: 4000 | N39: 0 | O39: 0 | P39: 0 | Q39: 0 | R39: 0 | S39: 25000 | T39: 12000 | U39: 20000 | V39: 8000 | W39: 0 | X39: 0 | Y39: 0 | Z39: 0 | AA39: 0 | AB39: 12000 | AC39: 0 | AD39: 0
A40: Biekoes | B40: Latboskamp | C40: B7 | D40: 2021 | E40: 22.958092 | F40: 0 | G40: 0 | H40: 0 | I40: N.A | J40: 6000 | K40: 8000 | L40: 7000 | M40: 3000 | N40: 0 | O40: 0 | P40: 0 | Q40: 12000 | R40: 0 | S40: 12000 | T40: 10000 | U40: 8000 | V40: 6000 | W40: 0 | X40: 2000 | Y40: 4000 | Z40: 4000 | AA40: 4000 | AB40: 4000 | AC40: 0 | AD40: 0
A41: Biekoes | B41: Agter Huiskamp | C41: B11 | D41: Braak | E41: 15.497613 | F41: 0 | G41: 0 | H41: 0 | I41: N.A | J41: 6000 | K41: 8000 | L41: 7000 | M41: 3000 | N41: 0 | O41: 0 | P41: 0 | Q41: 0 | R41: 0 | S41: 10000 | T41: 2000 | U41: 0 | V41: 0 | W41: 0 | X41: 0 | Y41: 0 | Z41: 0 | AA41: 0 | AB41: 0 | AC41: 0 | AD41: 0
A42: Biekoes | B42: Stoorkamp | C42: B9 | D42: 2026 | E42: 35.395201 | F42: 0 | G42: 0 | H42: 0 | I42: N.A | J42: 12000 | K42: 10000 | L42: 5000 | M42: 4000 | N42: 0 | O42: 0 | P42: 0 | Q42: 0 | R42: 0 | S42: 0 | T42: 0 | U42: 7000 | V42: 8000 | W42: 5000 | X42: 0 | Y42: 0 | Z42: 0 | AA42: 0 | AB42: 0 | AC42: 0 | AD42: 0
A43: Biekoes | B43: Straatklip | C43: B3 | D43: 2022 | E43: 17.032996 | F43: 0 | G43: 0 | H43: 9000 | I43: N.A | J43: 9000 | K43: 5000 | L43: 0 | M43: 0 | N43: 0 | O43: 0 | P43: 5000 | Q43: 2000 | R43: 12000 | S43: 17300 | T43: 4000 | U43: 5000 | V43: 0 | W43: 0 | X43: 0 | Y43: 0 | Z43: 7500 | AA43: 8000 | AB43: 8000 | AC43: 0 | AD43: 0
A44: Garsland | B44: Huiskamp | C44: GA5 | D44: Braak | E44: 5.9436036 | F44: 0 | G44: 4000 | H44: 6000 | I44: N.A | J44: 6000 | K44: 2000 | L44: 0 | M44: 0 | N44: 0 | O44: 0 | P44: 0 | Q44: 0 | R44: 3500 | S44: 1500 | T44: 3000 | U44: 4500 | V44: 4000 | W44: 2500 | X44: 0 | Y44: 0 | Z44: 0 | AA44: 0 | AB44: 0 | AC44: 0 | AD44: 0
A45: Garsland | B45: Noordkamp | C45: GA1 | D45: Braak | E45: 14.273504 | F45: 0 | G45: 4000 | H45: 6000 | I45: N.A | J45: 6000 | K45: 2000 | L45: 0 | M45: 0 | N45: 0 | O45: 0 | P45: 0 | Q45: 1000 | R45: 3500 | S45: 8000 | T45: 3000 | U45: 2000 | V45: 0 | W45: 2500 | X45: 0 | Y45: 0 | Z45: 0 | AA45: 0 | AB45: 0 | AC45: 0 | AD45: 0
A46: Garsland | B46: Stoorland | C46: GA6 | D46: Braak | E46: 3.0312657 | F46: 0 | G46: 4000 | H46: 6000 | I46: N.A | J46: 6000 | K46: 2000 | L46: 0 | M46: 0 | N46: 0 | O46: 0 | P46: 0 | Q46: 1000 | R46: 0 | S46: 1000 | T46: 0 | U46: 0 | V46: 0 | W46: 0 | X46: 0 | Y46: 0 | Z46: 0 | AA46: 0 | AB46: 0 | AC46: 0 | AD46: 0
A47: Glenridge | B47: Teerpadland | C47: G7a | D47: Braak | E47: 7.6130991 | F47: 0 | G47: 3000 | H47: 3000 | I47: N.A | J47: 1000 | K47: 0 | L47: 0 | M47: 0 | N47: 0 | O47: 1500 | P47: 2500 | Q47: 5000 | R47: 0 | S47: 4000 | T47: 1000 | U47: 1500 | V47: 1500 | W47: 0 | X47: 0 | Y47: 0 | Z47: 0 | AA47: 0 | AB47: 0 | AC47: 0 | AD47: 0
A48: Glenridge | B48: Popelierland | C48: G7b | D48: Braak | E48: 1.2286475 | F48: 0 | G48: 3000 | H48: 3000 | I48: N.A | J48: 1000 | K48: 0 | L48: 0 | M48: 0 | N48: 0 | O48: 1500 | P48: 2500 | Q48: 5000 | R48: 0 | S48: 1000 | T48: 1000 | U48: 200 | V48: 200 | W48: 0 | X48: 0 | Y48: 0 | Z48: 0 | AA48: 0 | AB48: 0 | AC48: 0 | AD48: 0
A49: Glenridge | B49: Noordland | C49: G7c | D49: Braak | E49: 0.79330274 | F49: 0 | G49: 3000 | H49: 3000 | I49: N.A | J49: 1000 | K49: 0 | L49: 0 | M49: 0 | N49: 0 | O49: 1500 | P49: 2500 | Q49: 5000 | R49: 0 | S49: 1000 | T49: 1000 | U49: 500 | V49: 500 | W49: 0 | X49: 0 | Y49: 0 | Z49: 0 | AA49: 15000 | AB49: 0 | AC49: 0 | AD49: 0
A50: Glenridge | B50: Plantjiesland | C50: G7d | D50: Braak | E50: 8.1720683 | F50: 0 | G50: 3000 | H50: 3000 | I50: N.A | J50: 1000 | K50: 0 | L50: 0 | M50: 0 | N50: 0 | O50: 1500 | P50: 2500 | Q50: 5000 | R50: 0 | S50: 4000 | T50: 1000 | U50: 1000 | V50: 1000 | W50: 0 | X50: 0 | Y50: 0 | Z50: 0 | AA50: 0 | AB50: 0 | AC50: 0 | AD50: 0
A51: Glenridge | B51: Deur-ry-land | C51: G7e | D51: Braak | E51: 3.2858996 | F51: 0 | G51: 3000 | H51: 3000 | I51: N.A | J51: 1000 | K51: 0 | L51: 0 | M51: 0 | N51: 0 | O51: 1500 | P51: 2500 | Q51: 5000 | R51: 0 | S51: 1000 | T51: 1000 | U51: 2000 | V51: 2000 | W51: 0 | X51: 0 | Y51: 0 | Z51: 0 | AA51: 0 | AB51: 0 | AC51: 0 | AD51: 0
A52: Glenridge | B52: Puntland | C52: G7f | D52: Braak | E52: 4.258856 | F52: 0 | G52: 3000 | H52: 3000 | I52: N.A | J52: 1000 | K52: 0 | L52: 0 | M52: 0 | N52: 0 | O52: 1500 | P52: 2500 | Q52: 5000 | R52: 0 | S52: 1000 | T52: 1000 | U52: 0 | V52: 0 | W52: 0 | X52: 0 | Y52: 0 | Z52: 0 | AA52: 0 | AB52: 0 | AC52: 0 | AD52: 0
A53: Biekoes | B53: Donkiekamp | C53: B10 | D53: Braak | E53: 15.962332 | F53: 0 | G53: 0 | H53: 0 | I53: N.A | J53: 0 | K53: 0 | L53: 0 | M53: 5000 | N53: 0 | O53: 0 | P53: 0 | Q53: 0 | R53: 0 | S53: 1000 | T53: 2000 | U53: 2000 | V53: 0 | W53: 0 | X53: 0 | Y53: 0 | Z53: 0 | AA53: 0 | AB53: 0 | AC53: 0 | AD53: 0
A54: Biekoes | B54: Teen Grasberg | C54: B12 | D54: 2026 | E54: 11.799041 | F54: 0 | G54: 0 | H54: 0 | I54: N.A | J54: 0 | K54: 0 | L54: 0 | M54: 5000 | N54: 0 | O54: 0 | P54: 0 | Q54: 0 | R54: 0 | S54: 0 | T54: 0 | U54: 0 | V54: 3000 | W54: 5000 | X54: 6000 | Y54: 4000 | Z54: 0 | AA54: 0 | AB54: 0 | AC54: 0 | AD54: 0
A55: Biekoes | B55: Voor Huiskamp | C55: B13 | D55: Braak | E55: 27.417025 | F55: 0 | G55: 0 | H55: 0 | I55: N.A | J55: 0 | K55: 0 | L55: 0 | M55: 5000 | N55: 0 | O55: 0 | P55: 0 | Q55: 0 | R55: 0 | S55: 2000 | T55: 1000 | U55: 0 | V55: 0 | W55: 0 | X55: 0 | Y55: 0 | Z55: 0 | AA55: 0 | AB55: 0 | AC55: 0 | AD55: 0
A56: Biekoes | B56: Tuinkamp | C56: B14 | D56: 2023 | E56: 8.6880705 | F56: 0 | G56: 0 | H56: 0 | I56: N.A | J56: 0 | K56: 0 | L56: 0 | M56: 0 | N56: 0 | O56: 0 | P56: 0 | Q56: 0 | R56: 0 | S56: 0 | T56: 0 | U56: 0 | V56: 0 | W56: 0 | X56: 0 | Y56: 0 | Z56: 0 | AA56: 2000 | AB56: 3000 | AC56: 0 | AD56: 0
D57: =SUM(Johan_Brand_Skatting_en_Werklik_2[GEPLANT]) -> 72868 | E57: =SUM(Johan_Brand_Skatting_en_Werklik_2[HEKTAAR]) -> 1049.3503 | G57: =SUM(Johan_Brand_Skatting_en_Werklik_2[2005 OESSKAT]) -> 91000 | H57: =SUM(Johan_Brand_Skatting_en_Werklik_2[2006 OESSKAT]) -> 286500 | I57: =SUM(Johan_Brand_Skatting_en_Werklik_2[2007_OESSKAT]) -> 0 | J57: =SUM(Johan_Brand_Skatting_en_Werklik_2[2008_OESSKAT]) -> 310000 | K57: =SUM(Johan_Brand_Skatting_en_Werklik_2[2009_OESSKAT]) -> 189000 | L57: =SUM(Johan_Brand_Skatting_en_Werklik_2[2010_OESSKAT]) -> 132000 | M57: =SUM(Johan_Brand_Skatting_en_Werklik_2[2011_OESSKAT]) -> 236000 | N57: =SUM(Johan_Brand_Skatting_en_Werklik_2[2012_OESSKAT]) -> 172000 | O57: =SUM(Johan_Brand_Skatting_en_Werklik_2[2013_OESSKAT]) -> 142500 | P57: =SUM(Johan_Brand_Skatting_en_Werklik_2[2014_OESSKAT]) -> 163500 | Q57: =SUM(Johan_Brand_Skatting_en_Werklik_2[2015_OESSKAT]) -> 202000 | R57: =SUM(Johan_Brand_Skatting_en_Werklik_2[2016_OESSKAT]) -> 132500 | S57: =SUM(Johan_Brand_Skatting_en_Werklik_2[2017_OESSKAT]) -> 372800 | T57: =SUM(Johan_Brand_Skatting_en_Werklik_2[2018_OESSKAT]) -> 216003 | U57: =SUM(Johan_Brand_Skatting_en_Werklik_2[2019_OESSKAT]) -> 195200 | V57: =SUM(Johan_Brand_Skatting_en_Werklik_2[2020_OESSKAT]) -> 209200 | W57: =SUM(Johan_Brand_Skatting_en_Werklik_2[2021_OESSKAT]) -> 207000 | X57: =SUM(Johan_Brand_Skatting_en_Werklik_2[2022_OESSKAT]) -> 186000 | Y57: =SUM(Johan_Brand_Skatting_en_Werklik_2[2023_OESSKAT]) -> 120000 | Z57: =SUM(Johan_Brand_Skatting_en_Werklik_2[2024_OESSKAT]) -> 192000 | AA57: =SUM(Johan_Brand_Skatting_en_Werklik_2[2025_OESSKAT]) -> 231700 | AB57: =SUM(Johan_Brand_Skatting_en_Werklik_2[2026_OESSKAT]) -> 178000 | AC57: =SUM(Johan_Brand_Skatting_en_Werklik_2[2027_OESSKAT]) -> 93000 | AD57: =SUM(Johan_Brand_Skatting_en_Werklik_2[2028_OESSKAT]) -> 34000
A60: PLAASNAAM | B60: LANDNAAM | C60: LANDNO | D60: GEPLANT | E60: HEKTAAR | F60: 2004 OESSKAT | G60: 2005 OESSKAT | H60: 2006 OESSKAT | I60: 2007_OESSKAT | J60: 2008_OESSKAT | K60: 2009_OESSKAT | L60: 2010_OESSKAT | M60: 2011_OESSKAT | N60: 2012_OESSKAT | O60: 2013_OESSKAT | P60: 2014_OESSKAT | Q60: 2015_OESSKAT | R60: 2016_OESSKAT | S60: 2017_OESSKAT | T60: 2018_OESSKAT | U60: 2019_OESSKAT | V60: 2020_OESSKAT | W60: 2021_OESSKAT | X60: 2022_OESSKAT | Y60: 2023_OESSKAT | Z60: 2024_OESSKAT | AA60: 2025_OESSKAT | AB60: 2026_OESSKAT | AC60: 2027_OESSKAT | AD60: 2028_OESSKAT
A61: Biekoes | B61: Spilpuntkamp | C61: B2 | D61: 2026 | E61: 18.110613 | F61: 0 | G61: 0 | H61: 15000 | I61: N.A | J61: 0 | K61: 0 | L61: 6000 | M61: 1000 | N61: 4000 | O61: 2000 | P61: 2000 | Q61: 2000 | R61: 4500 | S61: 34000 | T61: 9000 | U61: 10000 | V61: 0 | W61: 0 | X61: 15000 | Y61: 0 | Z61: 2000 | AA61: 0 | AB61: 0 | AC61: 2000 | AD61: 9000
A62: Biekoes | B62: Eerste Land | C62: B1 | D62: 2022 | E62: 21.198753 | F62: 0 | G62: 0 | H62: 0 | I62: N.A | J62: 0 | K62: 0 | L62: 0 | M62: 8000 | N62: 8000 | O62: 8000 | P62: 6000 | Q62: 0 | R62: 0 | S62: 16000 | T62: 16000 | U62: 12000 | V62: 5000 | W62: 0 | X62: 0 | Y62: 0 | Z62: 6000 | AA62: 4000 | AB62: 5000 | AC62: 0 | AD62: 0
A63: Biekoes | B63: Windpompkamp | C63: B4 | D63: 2026 | E63: 11.609562 | F63: 0 | G63: 0 | H63: 5000 | I63: N.A | J63: 3000 | K63: 2000 | L63: 0 | M63: 0 | N63: 0 | O63: 1000 | P63: 0 | Q63: 0 | R63: 0 | S63: 3000 | T63: 3000 | U63: 2000 | V63: 2000 | W63: 0 | X63: 1000 | Y63: 3000 | Z63: 1000 | AA63: 4000 | AB63: 0 | AC63: 1000 | AD63: 5000
A64: Cloudskraal | B64: Om Groenvlei | C64: C9 | D64: 2026 | E64: 29.471117 | F64: 0 | G64: 0 | H64: 25000 | I64: N.A | J64: 25000 | K64: 10000 | L64: 0 | M64: 18000 | N64: 18000 | O64: 12000 | P64: 0 | Q64: 3000 | R64: 12000 | S64: 30000 | T64: 8000 | U64: 0 | V64: 0 | W64: 3000 | X64: 3000 | Y64: 9000 | Z64: 15000 | AA64: 15000 | AB64: 0 | AC64: 0 | AD64: 0
A65: Cloudskraal | B65: Groenvlei | C65: C11 | D65: 2022 | E65: 41.979349 | F65: 24000 | G65: 15000 | H65: 15000 | I65: N.A | J65: 15000 | K65: 25000 | L65: 20000 | M65: 10000 | N65: 5000 | O65: 0 | P65: 0 | Q65: 30000 | R65: 15000 | S65: 20000 | T65: 10000 | U65: 5000 | V65: 5000 | W65: 3000 | X65: 0 | Y65: 0 | Z65: 16000 | AA65: 24000 | AB65: 20000 | AC65: 0 | AD65: 0
A66: Glenridge | B66: Driehoekkamp | C66: G1 | D66: 2026 | E66: 16.552962 | F66: 12000 | G66: 10000 | H66: 3000 | I66: N.A | J66: 5000 | K66: 5000 | L66: 3000 | M66: 6000 | N66: 0 | O66: 0 | P66: 0 | Q66: 8000 | R66: 5000 | S66: 12000 | T66: 5000 | U66: 2000 | V66: 7000 | W66: 12000 | X66: 5000 | Y66: 0 | Z66: 0 | AA66: 0 | AB66: 0 | AC66: 7000 | AD66: 0
A67: Glenridge | B67: Vleikamp B | C67: G8 | D67: 2022 | E67: 23.028313 | F67: 1000 | G67: 0 | H67: 25000 | I67: N.A | J67: 9000 | K67: 0 | L67: 0 | M67: 0 | N67: 0 | O67: 0 | P67: 0 | Q67: 0 | R67: 0 | S67: 5000 | T67: 3 | U67: 8000 | V67: 7000 | W67: 7000 | X67: 7000 | Y67: 0 | Z67: 12000 | AA67: 10000 | AB67: 5000 | AC67: 0 | AD67: 0
A68: Glenridge | B68: Baken se land | C68: G3 | D68: 2025 | E68: 53.627997 | F68: 0 | G68: 0 | H68: 0 | I68: N.A | J68: 10000 | K68: 10000 | L68: 0 | M68: 20000 | N68: 20000 | O68: 15000 | P68: 10000 | Q68: 0 | R68: 0 | S68: 10000 | T68: 25000 | U68: 30000 | V68: 20000 | W68: 0 | X68: 27000 | Y68: 30000 | Z68: 26000 | AA68: 0 | AB68: 0 | AC68: 0 | AD68: 0
A69: Glenridge | B69: Sandkamp | C69: G4 | D69: 2022 | E69: 52.153611 | F69: 7000 | G69: 0 | H69: 10000 | I69: N.A | J69: 18000 | K69: 0 | L69: 0 | M69: 25000 | N69: 20000 | O69: 15000 | P69: 10000 | Q69: 0 | R69: 0 | S69: 25000 | T69: 20000 | U69: 6000 | V69: 6000 | W69: 8000 | X69: 0 | Y69: 0 | Z69: 31000 | AA69: 31000 | AB69: 15000 | AC69: 10000 | AD69: 0
A70: Glenridge | B70: By Resovoir | C70: G14 | D70: 2026 | E70: 6.7325786 | F70: 1000 | G70: 1000 | H70: 0 | I70: N.A | J70: 0 | K70: 0 | L70: 0 | M70: 0 | N70: 0 | O70: 3000 | P70: 3000 | Q70: 3000 | R70: 0 | S70: 0 | T70: 0 | U70: 0 | V70: 1000 | W70: 3000 | X70: 0 | Y70: 0 | Z70: 0 | AA70: 3500 | AB70: 3500 | AC70: 2000 | AD70: 0
A71: Glenridge | B71: Teen Pierre | C71: G13 | D71: 2026 | E71: 21.956941 | F71: 0 | G71: 0 | H71: 15000 | I71: N.A | J71: 11000 | K71: 11000 | L71: 0 | M71: 11000 | N71: 11000 | O71: 15000 | P71: 11000 | Q71: 6000 | R71: 0 | S71: 4000 | T71: 8000 | U71: 6000 | V71: 4000 | W71: 2000 | X71: 11000 | Y71: 6000 | Z71: 7000 | AA71: 4000 | AB71: 0 | AC71: 0 | AD71: 0
A72: Glenridge | B72: Bokant Bloekoms | C72: G11 | D72: Braak | E72: 14.3042 | F72: 6000 | G72: 2000 | H72: 1000 | I72: N.A | J72: 0 | K72: 0 | L72: 0 | M72: 0 | N72: 0 | O72: 6000 | P72: 8000 | Q72: 3000 | R72: 1500 | S72: 0 | T72: 0 | U72: 2000 | V72: 2000 | W72: 4000 | X72: 5000 | Y72: 0 | Z72: 0 | AA72: 0 | AB72: 0 | AC72: 0 | AD72: 0
A73: Cloudskraal | B73: Teen Kromvlei | C73: C1 | D73: 2023 | E73: 30.751305 | F73: 0 | G73: 0 | H73: 0 | I73: N.A | J73: 4000 | K73: 4000 | L73: 0 | M73: 0 | N73: 0 | O73: 4000 | P73: 3000 | Q73: 0 | R73: 0 | S73: 2000 | T73: 6000 | U73: 2000 | V73: 3000 | W73: 7500 | X73: 0 | Y73: 0 | Z73: 0 | AA73: 13000 | AB73: 21000 | AC73: 0 | AD73: 0
A74: Cloudskraal | B74: Agter Pomp | C74: C5 | D74: 2024 | E74: 32.66615 | F74: 0 | G74: 0 | H74: 30000 | I74: N.A | J74: 22000 | K74: 5000 | L74: 12000 | M74: 18000 | N74: 18000 | O74: 0 | P74: 0 | Q74: 3000 | R74: 15000 | S74: 36000 | T74: 8000 | U74: 0 | V74: 3000 | W74: 7500 | X74: 10000 | Y74: 6000 | Z74: 0 | AA74: 0 | AB74: 15000 | AC74: 25000 | AD74: 0
A75: Cloudskraal | B75: Links van vlei | C75: C6 | D75: 2024 | E75: 8.5061747 | F75: 0 | G75: 0 | H75: 6000 | I75: N.A | J75: 2500 | K75: 1000 | L75: 4000 | M75: 3000 | N75: 0 | O75: 0 | P75: 0 | Q75: 1000 | R75: 3500 | S75: 3500 | T75: 2000 | U75: 0 | V75: 2000 | W75: 3000 | X75: 3000 | Y75: 1000 | Z75: 0 | AA75: 0 | AB75: 2500 | AC75: 6000 | AD75: 0
A76: Cloudskraal | B76: Uilklip | C76: C13 | D76: 2027 | E76: 27.339304 | F76: 3000 | G76: 0 | H76: 0 | I76: N.A | J76: 12000 | K76: 10000 | L76: 0 | M76: 0 | N76: 15000 | O76: 15000 | P76: 4000 | Q76: 0 | R76: 0 | S76: 3000 | T76: 12000 | U76: 10000 | V76: 7000 | W76: 9000 | X76: 0 | Y76: 0 | Z76: 10000 | AA76: 10000 | AB76: 0 | AC76: 0 | AD76: 0
A77: Cloudskraal | B77: Heelagter | C77: C19 | D77: 2023 | E77: 33.530577 | F77: 0 | G77: 0 | H77: 0 | I77: N.A | J77: 24000 | K77: 5000 | L77: 20000 | M77: 20000 | N77: 15000 | O77: 6000 | P77: 9000 | Q77: 14000 | R77: 7000 | S77: 7000 | T77: 0 | U77: 0 | V77: 25000 | W77: 15000 | X77: 12000 | Y77: 0 | Z77: 0 | AA77: 22000 | AB77: 20000 | AC77: 15000 | AD77: 0
A78: Cloudskraal | B78: Tweede Spilpunt | C78: C18 | D78: 2025 | E78: 21.68274 | F78: 2000 | G78: 0 | H78: 0 | I78: N.A | J78: 0 | K78: 3000 | L78: 11000 | M78: 11000 | N78: 6000 | O78: 0 | P78: 0 | Q78: 0 | R78: 0 | S78: 6000 | T78: 8000 | U78: 6000 | V78: 0 | W78: 3000 | X78: 7000 | Y78: 7000 | Z78: 0 | AA78: 0 | AB78: 0 | AC78: 0 | AD78: 0
A79: Cloudskraal | B79: By Begraafplaas | C79: C16 | D79: Braak | E79: 8.7379009 | F79: 6000 | G79: 5000 | H79: 4500 | I79: N.A | J79: 0 | K79: 0 | L79: 0 | M79: 0 | N79: 0 | O79: 0 | P79: 0 | Q79: 0 | R79: 0 | S79: 0 | T79: 0 | U79: 1000 | V79: 0 | W79: 0 | X79: 0 | Y79: 0 | Z79: 0 | AA79: 0 | AB79: 0 | AC79: 0 | AD79: 0
A80: Cloudskraal | B80: Volkshuise | C80: C15 | D80: 2022 | E80: 7.293002 | F80: 1000 | G80: 1000 | H80: 3000 | I80: N.A | J80: 0 | K80: 0 | L80: 0 | M80: 0 | N80: 0 | O80: 0 | P80: 0 | Q80: 1000 | R80: 2500 | S80: 3500 | T80: 1000 | U80: 2000 | V80: 0 | W80: 0 | X80: 2000 | Y80: 0 | Z80: 2000 | AA80: 2000 | AB80: 1000 | AC80: 0 | AD80: 0
A81: Cloudskraal | B81: Eerste Spilpunt | C81: C8 | D81: 2022 | E81: 21.626902 | F81: 2500 | G81: 0 | H81: 15000 | I81: N.A | J81: 8000 | K81: 0 | L81: 0 | M81: 0 | N81: 0 | O81: 0 | P81: 12000 | Q81: 8000 | R81: 4000 | S81: 0 | T81: 0 | U81: 6000 | V81: 15000 | W81: 15000 | X81: 0 | Y81: 0 | Z81: 8000 | AA81: 12000 | AB81: 8000 | AC81: 0 | AD81: 0
A82: Cloudskraal | B82: Pleisterbosrug | C82: C3 | D82: 2021 | E82: 31.037026 | F82: 0 | G82: 0 | H82: 8000 | I82: N.A | J82: 12000 | K82: 4000 | L82: 0 | M82: 0 | N82: 0 | O82: 7000 | P82: 18000 | Q82: 10000 | R82: 8000 | S82: 3000 | T82: 3000 | U82: 6000 | V82: 6000 | W82: 0 | X82: 0 | Y82: 10000 | Z82: 18000 | AA82: 18000 | AB82: 10000 | AC82: 0 | AD82: 0
A83: Cloudskraal | B83: Hardekop | C83: C2 | D83: 2024 | E83: 21.015682 | F83: 5000 | G83: 5000 | H83: 5000 | I83: N.A | J83: 15000 | K83: 15000 | L83: 10000 | M83: 8000 | N83: 0 | O83: 0 | P83: 8000 | Q83: 16000 | R83: 6000 | S83: 5000 | T83: 0 | U83: 0 | V83: 3000 | W83: 15000 | X83: 11000 | Y83: 5000 | Z83: 0 | AA83: 3000 | AB83: 12000 | AC83: 12000 | AD83: 0
A84: Glenridge | B84: Langland by Bloekoms | C84: G9 | D84: 2026 | E84: 18.753786 | F84: 0 | G84: 0 | H84: 0 | I84: N.A | J84: 3000 | K84: 2000 | L84: 0 | M84: 0 | N84: 0 | O84: 4000 | P84: 10000 | Q84: 10000 | R84: 3000 | S84: 0 | T84: 0 | U84: 3000 | V84: 5000 | W84: 6000 | X84: 8000 | Y84: 4000 | Z84: 0 | AA84: 0 | AB84: 0 | AC84: 0 | AD84: 0
A85: Glenridge | B85: Garskamp | C85: G10 | D85: Braak | E85: 10.953934 | F85: 5000 | G85: 0 | H85: 0 | I85: N.A | J85: 1500 | K85: 1000 | L85: 0 | M85: 0 | N85: 0 | O85: 2500 | P85: 2500 | Q85: 0 | R85: 0 | S85: 0 | T85: 0 | U85: 0 | V85: 1000 | W85: 0 | X85: 0 | Y85: 0 | Z85: 0 | AA85: 0 | AB85: 0 | AC85: 0 | AD85: 0
A86: Glenridge | B86: Klipland | C86: G12 | D86: Braak | E86: 4.6495434 | F86: 5000 | G86: 1000 | H86: 0 | I86: N.A | J86: 0 | K86: 0 | L86: 0 | M86: 0 | N86: 0 | O86: 2000 | P86: 2000 | Q86: 0 | R86: 0 | S86: 0 | T86: 0 | U86: 0 | V86: 0 | W86: 0 | X86: 0 | Y86: 0 | Z86: 0 | AA86: 0 | AB86: 0 | AC86: 0 | AD86: 0
A87: Garsland | B87: Denneboomland | C87: GA4 | D87: Braak | E87: 2.2378144 | F87: 0 | G87: 0 | H87: 0 | I87: N.A | J87: 0 | K87: 0 | L87: 0 | M87: 0 | N87: 0 | O87: 0 | P87: 0 | Q87: 0 | R87: 0 | S87: 0 | T87: 0 | U87: 0 | V87: 0 | W87: 0 | X87: 0 | Y87: 0 | Z87: 0 | AA87: 0 | AB87: 0 | AC87: 0 | AD87: 0
A88: Garsland | B88: Driehoekkamp | C88: GA2 | D88: 2025 | E88: 9.3738299 | F88: 0 | G88: 4000 | H88: 9000 | I88: N.A | J88: 6000 | K88: 2000 | L88: 0 | M88: 5000 | N88: 6000 | O88: 2000 | P88: 0 | Q88: 1000 | R88: 2500 | S88: 6000 | T88: 2000 | U88: 1000 | V88: 5000 | W88: 6000 | X88: 3000 | Y88: 1000 | Z88: 0 | AA88: 0 | AB88: 0 | AC88: 0 | AD88: 0
A89: Garsland | B89: Spilpuntland | C89: GA3 | D89: 2023 | E89: 14.306519 | F89: 0 | G89: 0 | H89: 7000 | I89: N.A | J89: 10000 | K89: 2000 | L89: 0 | M89: 8000 | N89: 5000 | O89: 2000 | P89: 0 | Q89: 0 | R89: 0 | S89: 7000 | T89: 5000 | U89: 4500 | V89: 2000 | W89: 5000 | X89: 0 | Y89: 0 | Z89: 0 | AA89: 4200 | AB89: 6000 | AC89: 3000 | AD89: 0
A90: Glenridge | B90: Vleikamp A | C90: G2 | D90: 2026 | E90: 21.868015 | F90: 1000 | G90: 0 | H90: 25000 | I90: N.A | J90: 9000 | K90: 0 | L90: 0 | M90: 10000 | N90: 8000 | O90: 2000 | P90: 0 | Q90: 5000 | R90: 5000 | S90: 5000 | T90: 2000 | U90: 3000 | V90: 8000 | W90: 12000 | X90: 0 | Y90: 0 | Z90: 0 | AA90: 0 | AB90: 0 | AC90: 0 | AD90: 0
A91: Cloudskraal | B91: Regs van vlei | C91: C7 | D91: 2025 | E91: 27.682425 | F91: 0 | G91: 6000 | H91: 8000 | I91: N.A | J91: 0 | K91: 15000 | L91: 15000 | M91: 15000 | N91: 8000 | O91: 0 | P91: 0 | Q91: 3000 | R91: 6000 | S91: 12000 | T91: 8000 | U91: 0 | V91: 3000 | W91: 12000 | X91: 18000 | Y91: 9000 | Z91: 0 | AA91: 0 | AB91: 0 | AC91: 0 | AD91: 0
A92: Glenridge | B92: Roosklawerkamp | C92: G6 | D92: 2027 | E92: 66.66814 | F92: 0 | G92: 0 | H92: 0 | I92: N.A | J92: 0 | K92: 0 | L92: 0 | M92: 0 | N92: 0 | O92: 10000 | P92: 25000 | Q92: 15000 | R92: 0 | S92: 0 | T92: 0 | U92: 0 | V92: 10000 | W92: 10000 | X92: 20000 | Y92: 15000 | Z92: 12000 | AA92: 0 | AB92: 0 | AC92: 0 | AD92: 0
A93: Cloudskraal | B93: Onderdam | C93: C17 | D93: 2022 | E93: 16.8566 | F93: 3000 | G93: 3000 | H93: 0 | I93: N.A | J93: 0 | K93: 0 | L93: 0 | M93: 0 | N93: 0 | O93: 0 | P93: 0 | Q93: 6000 | R93: 5000 | S93: 7000 | T93: 3000 | U93: 1000 | V93: 6000 | W93: 12000 | X93: 0 | Y93: 0 | Z93: 7000 | AA93: 5000 | AB93: 2000 | AC93: 0 | AD93: 0
A94: Cloudskraal | B94: Langland | C94: C12 | D94: 2023 | E94: 20.644499 | F94: 12000 | G94: 8000 | H94: 7000 | I94: N.A | J94: 16000 | K94: 10000 | L94: 7000 | M94: 10000 | N94: 5000 | O94: 0 | P94: 0 | Q94: 8000 | R94: 8000 | S94: 5000 | T94: 3000 | U94: 3000 | V94: 8000 | W94: 12000 | X94: 8000 | Y94: 0 | Z94: 0 | AA94: 8000 | AB94: 5000 | AC94: 5000 | AD94: 0
A95: Biekoes | B95: Hardekop | C95: B8 | D95: 2026 | E95: 34.192859 | F95: 0 | G95: 0 | H95: 0 | I95: N.A | J95: 0 | K95: 0 | L95: 0 | M95: 0 | N95: 0 | O95: 0 | P95: 0 | Q95: 0 | R95: 0 | S95: 13000 | T95: 6000 | U95: 10000 | V95: 4000 | W95: 0 | X95: 2000 | Y95: 6000 | Z95: 7500 | AA95: 10000 | AB95: 0 | AC95: 5000 | AD95: 20000
A96: Biekoes | B96: Bokant Dam | C96: B6 | D96: 2023 | E96: 42.898925 | F96: 0 | G96: 0 | H96: 0 | I96: N.A | J96: 12000 | K96: 10000 | L96: 5000 | M96: 4000 | N96: 0 | O96: 0 | P96: 0 | Q96: 0 | R96: 0 | S96: 25000 | T96: 12000 | U96: 20000 | V96: 8000 | W96: 0 | X96: 0 | Y96: 0 | Z96: 0 | AA96: 0 | AB96: 12000 | AC96: 0 | AD96: 0
A97: Biekoes | B97: Latboskamp | C97: B7 | D97: 2021 | E97: 22.958092 | F97: 0 | G97: 0 | H97: 0 | I97: N.A | J97: 6000 | K97: 8000 | L97: 7000 | M97: 3000 | N97: 0 | O97: 0 | P97: 0 | Q97: 12000 | R97: 0 | S97: 12000 | T97: 10000 | U97: 8000 | V97: 6000 | W97: 0 | X97: 2000 | Y97: 4000 | Z97: 4000 | AA97: 4000 | AB97: 4000 | AC97: 0 | AD97: 0
A98: Biekoes | B98: Agter Huiskamp | C98: B11 | D98: Braak | E98: 15.497613 | F98: 0 | G98: 0 | H98: 0 | I98: N.A | J98: 6000 | K98: 8000 | L98: 7000 | M98: 3000 | N98: 0 | O98: 0 | P98: 0 | Q98: 0 | R98: 0 | S98: 10000 | T98: 2000 | U98: 0 | V98: 0 | W98: 0 | X98: 0 | Y98: 0 | Z98: 0 | AA98: 0 | AB98: 0 | AC98: 0 | AD98: 0
A99: Biekoes | B99: Stoorkamp | C99: B9 | D99: 2026 | E99: 35.395201 | F99: 0 | G99: 0 | H99: 0 | I99: N.A | J99: 12000 | K99: 10000 | L99: 5000 | M99: 4000 | N99: 0 | O99: 0 | P99: 0 | Q99: 0 | R99: 0 | S99: 0 | T99: 0 | U99: 7000 | V99: 8000 | W99: 5000 | X99: 0 | Y99: 0 | Z99: 0 | AA99: 0 | AB99: 0 | AC99: 0 | AD99: 0
A100: Biekoes | B100: Straatklip | C100: B3 | D100: 2022 | E100: 17.032996 | F100: 0 | G100: 0 | H100: 9000 | I100: N.A | J100: 9000 | K100: 5000 | L100: 0 | M100: 0 | N100: 0 | O100: 0 | P100: 5000 | Q100: 2000 | R100: 12000 | S100: 17300 | T100: 4000 | U100: 5000 | V100: 0 | W100: 0 | X100: 0 | Y100: 0 | Z100: 7500 | AA100: 8000 | AB100: 8000 | AC100: 0 | AD100: 0
A101: Garsland | B101: Huiskamp | C101: GA5 | D101: Braak | E101: 5.9436036 | F101: 0 | G101: 4000 | H101: 6000 | I101: N.A | J101: 6000 | K101: 2000 | L101: 0 | M101: 0 | N101: 0 | O101: 0 | P101: 0 | Q101: 0 | R101: 3500 | S101: 1500 | T101: 3000 | U101: 4500 | V101: 4000 | W101: 2500 | X101: 0 | Y101: 0 | Z101: 0 | AA101: 0 | AB101: 0 | AC101: 0 | AD101: 0
A102: Garsland | B102: Noordkamp | C102: GA1 | D102: Braak | E102: 14.273504 | F102: 0 | G102: 4000 | H102: 6000 | I102: N.A | J102: 6000 | K102: 2000 | L102: 0 | M102: 0 | N102: 0 | O102: 0 | P102: 0 | Q102: 1000 | R102: 3500 | S102: 8000 | T102: 3000 | U102: 2000 | V102: 0 | W102: 2500 | X102: 0 | Y102: 0 | Z102: 0 | AA102: 0 | AB102: 0 | AC102: 0 | AD102: 0
...

Sheet Copy of Oeskatting
A1: PRODUKSIE DATA VAN CLOUDSKRAAL BOERDERY PER PLAAS, LAND EN GESKATTE OPBRENGS EN WERKLIKE OES IN KILOGRAMME.
F2: 2004
A3: PLAASNAAM | B3: LANDNAAM | C3: LANDNO | D3: GEPLANT | E3: HEKTAAR | F3: 2004 OESSKAT | G3: Column 31 | H3: 2005 OESSKAT | I3: Column 32 | J3: 2006 OESSKAT | K3: Column 33 | L3: 2007_OESSKAT | M3: Column 34 | N3: 2008_OESSKAT | O3: Column 35 | P3: 2009_OESSKAT | Q3: Column 36 | R3: 2010_OESSKAT | S3: Column 37 | T3: 2011_OESSKAT | U3: Column 38 | V3: 2012_OESSKAT | W3: Column 39 | X3: 2013_OESSKAT | Y3: Column 40 | Z3: 2014_OESSKAT | AA3: Column 41 | AB3: 2015_OESSKAT | AC3: Column 42 | AD3: 2016_OESSKAT | AE3: Column 43 | AF3: 2017_OESSKAT | AG3: Column 44 | AH3: 2018_OESSKAT | AI3: Column 45 | AJ3: 2019_OESSKAT | AK3: Column 46 | AL3: 2020_OESSKAT | AM3: Column 47 | AN3: 2021_OESSKAT | AO3: Column 48 | AP3: 2022_OESSKAT | AQ3: Column 49 | AR3: 2023_OESSKAT | AS3: Column 50 | AT3: 2024_OESSKAT | AU3: Column 51 | AV3: 2025_OESSKAT | AW3: Column 52 | AX3: 2026_OESSKAT | AY3: 2027_OESSKAT | AZ3: 2028_OESSKAT
A4: Biekoes | B4: Spilpuntkamp | C4: B2 | D4: 2026 | E4: 18.110613 | F4: 0 | H4: 0 | J4: 15000 | L4: N.A | N4: 0 | P4: 0 | R4: 6000 | T4: 1000 | V4: 4000 | X4: 2000 | Z4: 2000 | AB4: 2000 | AD4: 4500 | AF4: 34000 | AH4: 9000 | AJ4: 10000 | AL4: 0 | AN4: 0 | AP4: 15000 | AR4: 0 | AT4: 2000 | AV4: 0 | AX4: 0 | AY4: 2000 | AZ4: 9000
A5: Biekoes | B5: Eerste Land | C5: B1 | D5: 2022 | E5: 21.198753 | F5: 0 | H5: 0 | J5: 0 | L5: N.A | N5: 0 | P5: 0 | R5: 0 | T5: 8000 | V5: 8000 | X5: 8000 | Z5: 6000 | AB5: 0 | AD5: 0 | AF5: 16000 | AH5: 16000 | AJ5: 12000 | AL5: 5000 | AN5: 0 | AP5: 0 | AR5: 0 | AT5: 6000 | AV5: 4000 | AX5: 5000 | AY5: 0 | AZ5: 0
A6: Biekoes | B6: Windpompkamp | C6: B4 | D6: 2026 | E6: 11.609562 | F6: 0 | H6: 0 | J6: 5000 | L6: N.A | N6: 3000 | P6: 2000 | R6: 0 | T6: 0 | V6: 0 | X6: 1000 | Z6: 0 | AB6: 0 | AD6: 0 | AF6: 3000 | AH6: 3000 | AJ6: 2000 | AL6: 2000 | AN6: 0 | AP6: 1000 | AR6: 3000 | AT6: 1000 | AV6: 4000 | AX6: 0 | AY6: 1000 | AZ6: 5000
A7: Cloudskraal | B7: Om Groenvlei | C7: C9 | D7: 2026 | E7: 29.471117 | F7: 0 | H7: 0 | J7: 25000 | L7: N.A | N7: 25000 | P7: 10000 | R7: 0 | T7: 18000 | V7: 18000 | X7: 12000 | Z7: 0 | AB7: 3000 | AD7: 12000 | AF7: 30000 | AH7: 8000 | AJ7: 0 | AL7: 0 | AN7: 3000 | AP7: 3000 | AR7: 9000 | AT7: 15000 | AV7: 15000 | AX7: 0 | AY7: 0 | AZ7: 0
A8: Cloudskraal | B8: Groenvlei | C8: C11 | D8: 2022 | E8: 41.979349 | F8: 24000 | H8: 15000 | J8: 15000 | L8: N.A | N8: 15000 | P8: 25000 | R8: 20000 | T8: 10000 | V8: 5000 | X8: 0 | Z8: 0 | AB8: 30000 | AD8: 15000 | AF8: 20000 | AH8: 10000 | AJ8: 5000 | AL8: 5000 | AN8: 3000 | AP8: 0 | AR8: 0 | AT8: 16000 | AV8: 24000 | AX8: 20000 | AY8: 0 | AZ8: 0
A9: Glenridge | B9: Driehoekkamp | C9: G1 | D9: 2026 | E9: 16.552962 | F9: 12000 | H9: 10000 | J9: 3000 | L9: N.A | N9: 5000 | P9: 5000 | R9: 3000 | T9: 6000 | V9: 0 | X9: 0 | Z9: 0 | AB9: 8000 | AD9: 5000 | AF9: 12000 | AH9: 5000 | AJ9: 2000 | AL9: 7000 | AN9: 12000 | AP9: 5000 | AR9: 0 | AT9: 0 | AV9: 0 | AX9: 0 | AY9: 7000 | AZ9: 0
A10: Glenridge | B10: Vleikamp B | C10: G8 | D10: 2022 | E10: 23.028313 | F10: 1000 | H10: 0 | J10: 25000 | L10: N.A | N10: 9000 | P10: 0 | R10: 0 | T10: 0 | V10: 0 | X10: 0 | Z10: 0 | AB10: 0 | AD10: 0 | AF10: 5000 | AH10: 3 | AJ10: 8000 | AL10: 7000 | AN10: 7000 | AP10: 7000 | AR10: 0 | AT10: 12000 | AV10: 10000 | AX10: 5000 | AY10: 0 | AZ10: 0
A11: Glenridge | B11: Baken se land | C11: G3 | D11: 2025 | E11: 53.627997 | F11: 0 | H11: 0 | J11: 0 | L11: N.A | N11: 10000 | P11: 10000 | R11: 0 | T11: 20000 | V11: 20000 | X11: 15000 | Z11: 10000 | AB11: 0 | AD11: 0 | AF11: 10000 | AH11: 25000 | AJ11: 30000 | AL11: 20000 | AN11: 0 | AP11: 27000 | AR11: 30000 | AT11: 26000 | AV11: 0 | AX11: 0 | AY11: 0 | AZ11: 0
A12: Glenridge | B12: Sandkamp | C12: G4 | D12: 2022 | E12: 52.153611 | F12: 7000 | H12: 0 | J12: 10000 | L12: N.A | N12: 18000 | P12: 0 | R12: 0 | T12: 25000 | V12: 20000 | X12: 15000 | Z12: 10000 | AB12: 0 | AD12: 0 | AF12: 25000 | AH12: 20000 | AJ12: 6000 | AL12: 6000 | AN12: 8000 | AP12: 0 | AR12: 0 | AT12: 31000 | AV12: 31000 | AX12: 15000 | AY12: 10000 | AZ12: 0
A13: Glenridge | B13: By Resovoir | C13: G14 | D13: 2026 | E13: 6.7325786 | F13: 1000 | H13: 1000 | J13: 0 | L13: N.A | N13: 0 | P13: 0 | R13: 0 | T13: 0 | V13: 0 | X13: 3000 | Z13: 3000 | AB13: 3000 | AD13: 0 | AF13: 0 | AH13: 0 | AJ13: 0 | AL13: 1000 | AN13: 3000 | AP13: 0 | AR13: 0 | AT13: 0 | AV13: 3500 | AX13: 3500 | AY13: 2000 | AZ13: 0
A14: Glenridge | B14: Teen Pierre | C14: G13 | D14: 2026 | E14: 21.956941 | F14: 0 | H14: 0 | J14: 15000 | L14: N.A | N14: 11000 | P14: 11000 | R14: 0 | T14: 11000 | V14: 11000 | X14: 15000 | Z14: 11000 | AB14: 6000 | AD14: 0 | AF14: 4000 | AH14: 8000 | AJ14: 6000 | AL14: 4000 | AN14: 2000 | AP14: 11000 | AR14: 6000 | AT14: 7000 | AV14: 4000 | AX14: 0 | AY14: 0 | AZ14: 0
A15: Glenridge | B15: Bokant Bloekoms | C15: G11 | D15: Braak | E15: 14.3042 | F15: 6000 | H15: 2000 | J15: 1000 | L15: N.A | N15: 0 | P15: 0 | R15: 0 | T15: 0 | V15: 0 | X15: 6000 | Z15: 8000 | AB15: 3000 | AD15: 1500 | AF15: 0 | AH15: 0 | AJ15: 2000 | AL15: 2000 | AN15: 4000 | AP15: 5000 | AR15: 0 | AT15: 0 | AV15: 0 | AX15: 0 | AY15: 0 | AZ15: 0
A16: Cloudskraal | B16: Teen Kromvlei | C16: C1 | D16: 2023 | E16: 30.751305 | F16: 0 | H16: 0 | J16: 0 | L16: N.A | N16: 4000 | P16: 4000 | R16: 0 | T16: 0 | V16: 0 | X16: 4000 | Z16: 3000 | AB16: 0 | AD16: 0 | AF16: 2000 | AH16: 6000 | AJ16: 2000 | AL16: 3000 | AN16: 7500 | AP16: 0 | AR16: 0 | AT16: 0 | AV16: 13000 | AX16: 21000 | AY16: 0 | AZ16: 0
A17: Cloudskraal | B17: Agter Pomp | C17: C5 | D17: 2024 | E17: 32.66615 | F17: 0 | H17: 0 | J17: 30000 | L17: N.A | N17: 22000 | P17: 5000 | R17: 12000 | T17: 18000 | V17: 18000 | X17: 0 | Z17: 0 | AB17: 3000 | AD17: 15000 | AF17: 36000 | AH17: 8000 | AJ17: 0 | AL17: 3000 | AN17: 7500 | AP17: 10000 | AR17: 6000 | AT17: 0 | AV17: 0 | AX17: 15000 | AY17: 25000 | AZ17: 0
A18: Cloudskraal | B18: Links van vlei | C18: C6 | D18: 2024 | E18: 8.5061747 | F18: 0 | H18: 0 | J18: 6000 | L18: N.A | N18: 2500 | P18: 1000 | R18: 4000 | T18: 3000 | V18: 0 | X18: 0 | Z18: 0 | AB18: 1000 | AD18: 3500 | AF18: 3500 | AH18: 2000 | AJ18: 0 | AL18: 2000 | AN18: 3000 | AP18: 3000 | AR18: 1000 | AT18: 0 | AV18: 0 | AX18: 2500 | AY18: 6000 | AZ18: 0
A19: Cloudskraal | B19: Uilklip | C19: C13 | D19: 2027 | E19: 27.339304 | F19: 3000 | H19: 0 | J19: 0 | L19: N.A | N19: 12000 | P19: 10000 | R19: 0 | T19: 0 | V19: 15000 | X19: 15000 | Z19: 4000 | AB19: 0 | AD19: 0 | AF19: 3000 | AH19: 12000 | AJ19: 10000 | AL19: 7000 | AN19: 9000 | AP19: 0 | AR19: 0 | AT19: 10000 | AV19: 10000 | AX19: 0 | AY19: 0 | AZ19: 0
A20: Cloudskraal | B20: Heelagter | C20: C19 | D20: 2023 | E20: 33.530577 | F20: 0 | H20: 0 | J20: 0 | L20: N.A | N20: 24000 | P20: 5000 | R20: 20000 | T20: 20000 | V20: 15000 | X20: 6000 | Z20: 9000 | AB20: 14000 | AD20: 7000 | AF20: 7000 | AH20: 0 | AJ20: 0 | AL20: 25000 | AN20: 15000 | AP20: 12000 | AR20: 0 | AT20: 0 | AV20: 22000 | AX20: 20000 | AY20: 15000 | AZ20: 0
A21: Cloudskraal | B21: Tweede Spilpunt | C21: C18 | D21: 2025 | E21: 21.68274 | F21: 2000 | H21: 0 | J21: 0 | L21: N.A | N21: 0 | P21: 3000 | R21: 11000 | T21: 11000 | V21: 6000 | X21: 0 | Z21: 0 | AB21: 0 | AD21: 0 | AF21: 6000 | AH21: 8000 | AJ21: 6000 | AL21: 0 | AN21: 3000 | AP21: 7000 | AR21: 7000 | AT21: 0 | AV21: 0 | AX21: 0 | AY21: 0 | AZ21: 0
A22: Cloudskraal | B22: By Begraafplaas | C22: C16 | D22: Braak | E22: 8.7379009 | F22: 6000 | H22: 5000 | J22: 4500 | L22: N.A | N22: 0 | P22: 0 | R22: 0 | T22: 0 | V22: 0 | X22: 0 | Z22: 0 | AB22: 0 | AD22: 0 | AF22: 0 | AH22: 0 | AJ22: 1000 | AL22: 0 | AN22: 0 | AP22: 0 | AR22: 0 | AT22: 0 | AV22: 0 | AX22: 0 | AY22: 0 | AZ22: 0
A23: Cloudskraal | B23: Volkshuise | C23: C15 | D23: 2022 | E23: 7.293002 | F23: 1000 | H23: 1000 | J23: 3000 | L23: N.A | N23: 0 | P23: 0 | R23: 0 | T23: 0 | V23: 0 | X23: 0 | Z23: 0 | AB23: 1000 | AD23: 2500 | AF23: 3500 | AH23: 1000 | AJ23: 2000 | AL23: 0 | AN23: 0 | AP23: 2000 | AR23: 0 | AT23: 2000 | AV23: 2000 | AX23: 1000 | AY23: 0 | AZ23: 0
A24: Cloudskraal | B24: Eerste Spilpunt | C24: C8 | D24: 2022 | E24: 21.626902 | F24: 2500 | H24: 0 | J24: 15000 | L24: N.A | N24: 8000 | P24: 0 | R24: 0 | T24: 0 | V24: 0 | X24: 0 | Z24: 12000 | AB24: 8000 | AD24: 4000 | AF24: 0 | AH24: 0 | AJ24: 6000 | AL24: 15000 | AN24: 15000 | AP24: 0 | AR24: 0 | AT24: 8000 | AV24: 12000 | AX24: 8000 | AY24: 0 | AZ24: 0
A25: Cloudskraal | B25: Pleisterbosrug | C25: C3 | D25: 2021 | E25: 31.037026 | F25: 0 | H25: 0 | J25: 8000 | L25: N.A | N25: 12000 | P25: 4000 | R25: 0 | T25: 0 | V25: 0 | X25: 7000 | Z25: 18000 | AB25: 10000 | AD25: 8000 | AF25: 3000 | AH25: 3000 | AJ25: 6000 | AL25: 6000 | AN25: 0 | AP25: 0 | AR25: 10000 | AT25: 18000 | AV25: 18000 | AX25: 10000 | AY25: 0 | AZ25: 0
A26: Cloudskraal | B26: Hardekop | C26: C2 | D26: 2024 | E26: 21.015682 | F26: 5000 | H26: 5000 | J26: 5000 | L26: N.A | N26: 15000 | P26: 15000 | R26: 10000 | T26: 8000 | V26: 0 | X26: 0 | Z26: 8000 | AB26: 16000 | AD26: 6000 | AF26: 5000 | AH26: 0 | AJ26: 0 | AL26: 3000 | AN26: 15000 | AP26: 11000 | AR26: 5000 | AT26: 0 | AV26: 3000 | AX26: 12000 | AY26: 12000 | AZ26: 0
A27: Glenridge | B27: Langland by Bloekoms | C27: G9 | D27: 2026 | E27: 18.753786 | F27: 0 | H27: 0 | J27: 0 | L27: N.A | N27: 3000 | P27: 2000 | R27: 0 | T27: 0 | V27: 0 | X27: 4000 | Z27: 10000 | AB27: 10000 | AD27: 3000 | AF27: 0 | AH27: 0 | AJ27: 3000 | AL27: 5000 | AN27: 6000 | AP27: 8000 | AR27: 4000 | AT27: 0 | AV27: 0 | AX27: 0 | AY27: 0 | AZ27: 0
A28: Glenridge | B28: Garskamp | C28: G10 | D28: Braak | E28: 10.953934 | F28: 5000 | H28: 0 | J28: 0 | L28: N.A | N28: 1500 | P28: 1000 | R28: 0 | T28: 0 | V28: 0 | X28: 2500 | Z28: 2500 | AB28: 0 | AD28: 0 | AF28: 0 | AH28: 0 | AJ28: 0 | AL28: 1000 | AN28: 0 | AP28: 0 | AR28: 0 | AT28: 0 | AV28: 0 | AX28: 0 | AY28: 0 | AZ28: 0
A29: Glenridge | B29: Klipland | C29: G12 | D29: Braak | E29: 4.6495434 | F29: 5000 | H29: 1000 | J29: 0 | L29: N.A | N29: 0 | P29: 0 | R29: 0 | T29: 0 | V29: 0 | X29: 2000 | Z29: 2000 | AB29: 0 | AD29: 0 | AF29: 0 | AH29: 0 | AJ29: 0 | AL29: 0 | AN29: 0 | AP29: 0 | AR29: 0 | AT29: 0 | AV29: 0 | AX29: 0 | AY29: 0 | AZ29: 0
A30: Garsland | B30: Denneboomland | C30: GA4 | D30: Braak | E30: 2.2378144 | F30: 0 | H30: 0 | J30: 0 | L30: N.A | N30: 0 | P30: 0 | R30: 0 | T30: 0 | V30: 0 | X30: 0 | Z30: 0 | AB30: 0 | AD30: 0 | AF30: 0 | AH30: 0 | AJ30: 0 | AL30: 0 | AN30: 0 | AP30: 0 | AR30: 0 | AT30: 0 | AV30: 0 | AX30: 0 | AY30: 0 | AZ30: 0
A31: Garsland | B31: Driehoekkamp | C31: GA2 | D31: 2025 | E31: 9.3738299 | F31: 0 | H31: 4000 | J31: 9000 | L31: N.A | N31: 6000 | P31: 2000 | R31: 0 | T31: 5000 | V31: 6000 | X31: 2000 | Z31: 0 | AB31: 1000 | AD31: 2500 | AF31: 6000 | AH31: 2000 | AJ31: 1000 | AL31: 5000 | AN31: 6000 | AP31: 3000 | AR31: 1000 | AT31: 0 | AV31: 0 | AX31: 0 | AY31: 0 | AZ31: 0
A32: Garsland | B32: Spilpuntland | C32: GA3 | D32: 2023 | E32: 14.306519 | F32: 0 | H32: 0 | J32: 7000 | L32: N.A | N32: 10000 | P32: 2000 | R32: 0 | T32: 8000 | V32: 5000 | X32: 2000 | Z32: 0 | AB32: 0 | AD32: 0 | AF32: 7000 | AH32: 5000 | AJ32: 4500 | AL32: 2000 | AN32: 5000 | AP32: 0 | AR32: 0 | AT32: 0 | AV32: 4200 | AX32: 6000 | AY32: 3000 | AZ32: 0
A33: Glenridge | B33: Vleikamp A | C33: G2 | D33: 2026 | E33: 21.868015 | F33: 1000 | H33: 0 | J33: 25000 | L33: N.A | N33: 9000 | P33: 0 | R33: 0 | T33: 10000 | V33: 8000 | X33: 2000 | Z33: 0 | AB33: 5000 | AD33: 5000 | AF33: 5000 | AH33: 2000 | AJ33: 3000 | AL33: 8000 | AN33: 12000 | AP33: 0 | AR33: 0 | AT33: 0 | AV33: 0 | AX33: 0 | AY33: 0 | AZ33: 0
A34: Cloudskraal | B34: Regs van vlei | C34: C7 | D34: 2025 | E34: 27.682425 | F34: 0 | H34: 6000 | J34: 8000 | L34: N.A | N34: 0 | P34: 15000 | R34: 15000 | T34: 15000 | V34: 8000 | X34: 0 | Z34: 0 | AB34: 3000 | AD34: 6000 | AF34: 12000 | AH34: 8000 | AJ34: 0 | AL34: 3000 | AN34: 12000 | AP34: 18000 | AR34: 9000 | AT34: 0 | AV34: 0 | AX34: 0 | AY34: 0 | AZ34: 0
A35: Glenridge | B35: Roosklawerkamp | C35: G6 | D35: 2027 | E35: 66.66814 | F35: 0 | H35: 0 | J35: 0 | L35: N.A | N35: 0 | P35: 0 | R35: 0 | T35: 0 | V35: 0 | X35: 10000 | Z35: 25000 | AB35: 15000 | AD35: 0 | AF35: 0 | AH35: 0 | AJ35: 0 | AL35: 10000 | AN35: 10000 | AP35: 20000 | AR35: 15000 | AT35: 12000 | AV35: 0 | AX35: 0 | AY35: 0 | AZ35: 0
A36: Cloudskraal | B36: Onderdam | C36: C17 | D36: 2022 | E36: 16.8566 | F36: 3000 | H36: 3000 | J36: 0 | L36: N.A | N36: 0 | P36: 0 | R36: 0 | T36: 0 | V36: 0 | X36: 0 | Z36: 0 | AB36: 6000 | AD36: 5000 | AF36: 7000 | AH36: 3000 | AJ36: 1000 | AL36: 6000 | AN36: 12000 | AP36: 0 | AR36: 0 | AT36: 7000 | AV36: 5000 | AX36: 2000 | AY36: 0 | AZ36: 0
A37: Cloudskraal | B37: Langland | C37: C12 | D37: 2023 | E37: 20.644499 | F37: 12000 | H37: 8000 | J37: 7000 | L37: N.A | N37: 16000 | P37: 10000 | R37: 7000 | T37: 10000 | V37: 5000 | X37: 0 | Z37: 0 | AB37: 8000 | AD37: 8000 | AF37: 5000 | AH37: 3000 | AJ37: 3000 | AL37: 8000 | AN37: 12000 | AP37: 8000 | AR37: 0 | AT37: 0 | AV37: 8000 | AX37: 5000 | AY37: 5000 | AZ37: 0
A38: Biekoes | B38: Hardekop | C38: B8 | D38: 2026 | E38: 34.192859 | F38: 0 | H38: 0 | J38: 0 | L38: N.A | N38: 0 | P38: 0 | R38: 0 | T38: 0 | V38: 0 | X38: 0 | Z38: 0 | AB38: 0 | AD38: 0 | AF38: 13000 | AH38: 6000 | AJ38: 10000 | AL38: 4000 | AN38: 0 | AP38: 2000 | AR38: 6000 | AT38: 7500 | AV38: 10000 | AX38: 0 | AY38: 5000 | AZ38: 20000
A39: Biekoes | B39: Bokant Dam | C39: B6 | D39: 2023 | E39: 42.898925 | F39: 0 | H39: 0 | J39: 0 | L39: N.A | N39: 12000 | P39: 10000 | R39: 5000 | T39: 4000 | V39: 0 | X39: 0 | Z39: 0 | AB39: 0 | AD39: 0 | AF39: 25000 | AH39: 12000 | AJ39: 20000 | AL39: 8000 | AN39: 0 | AP39: 0 | AR39: 0 | AT39: 0 | AV39: 0 | AX39: 12000 | AY39: 0 | AZ39: 0
A40: Biekoes | B40: Latboskamp | C40: B7 | D40: 2021 | E40: 22.958092 | F40: 0 | H40: 0 | J40: 0 | L40: N.A | N40: 6000 | P40: 8000 | R40: 7000 | T40: 3000 | V40: 0 | X40: 0 | Z40: 0 | AB40: 12000 | AD40: 0 | AF40: 12000 | AH40: 10000 | AJ40: 8000 | AL40: 6000 | AN40: 0 | AP40: 2000 | AR40: 4000 | AT40: 4000 | AV40: 4000 | AX40: 4000 | AY40: 0 | AZ40: 0
A41: Biekoes | B41: Agter Huiskamp | C41: B11 | D41: Braak | E41: 15.497613 | F41: 0 | H41: 0 | J41: 0 | L41: N.A | N41: 6000 | P41: 8000 | R41: 7000 | T41: 3000 | V41: 0 | X41: 0 | Z41: 0 | AB41: 0 | AD41: 0 | AF41: 10000 | AH41: 2000 | AJ41: 0 | AL41: 0 | AN41: 0 | AP41: 0 | AR41: 0 | AT41: 0 | AV41: 0 | AX41: 0 | AY41: 0 | AZ41: 0
A42: Biekoes | B42: Stoorkamp | C42: B9 | D42: 2026 | E42: 35.395201 | F42: 0 | H42: 0 | J42: 0 | L42: N.A | N42: 12000 | P42: 10000 | R42: 5000 | T42: 4000 | V42: 0 | X42: 0 | Z42: 0 | AB42: 0 | AD42: 0 | AF42: 0 | AH42: 0 | AJ42: 7000 | AL42: 8000 | AN42: 5000 | AP42: 0 | AR42: 0 | AT42: 0 | AV42: 0 | AX42: 0 | AY42: 0 | AZ42: 0
A43: Biekoes | B43: Straatklip | C43: B3 | D43: 2022 | E43: 17.032996 | F43: 0 | H43: 0 | J43: 9000 | L43: N.A | N43: 9000 | P43: 5000 | R43: 0 | T43: 0 | V43: 0 | X43: 0 | Z43: 5000 | AB43: 2000 | AD43: 12000 | AF43: 17300 | AH43: 4000 | AJ43: 5000 | AL43: 0 | AN43: 0 | AP43: 0 | AR43: 0 | AT43: 7500 | AV43: 8000 | AX43: 8000 | AY43: 0 | AZ43: 0
A44: Garsland | B44: Huiskamp | C44: GA5 | D44: Braak | E44: 5.9436036 | F44: 0 | H44: 4000 | J44: 6000 | L44: N.A | N44: 6000 | P44: 2000 | R44: 0 | T44: 0 | V44: 0 | X44: 0 | Z44: 0 | AB44: 0 | AD44: 3500 | AF44: 1500 | AH44: 3000 | AJ44: 4500 | AL44: 4000 | AN44: 2500 | AP44: 0 | AR44: 0 | AT44: 0 | AV44: 0 | AX44: 0 | AY44: 0 | AZ44: 0
A45: Garsland | B45: Noordkamp | C45: GA1 | D45: Braak | E45: 14.273504 | F45: 0 | H45: 4000 | J45: 6000 | L45: N.A | N45: 6000 | P45: 2000 | R45: 0 | T45: 0 | V45: 0 | X45: 0 | Z45: 0 | AB45: 1000 | AD45: 3500 | AF45: 8000 | AH45: 3000 | AJ45: 2000 | AL45: 0 | AN45: 2500 | AP45: 0 | AR45: 0 | AT45: 0 | AV45: 0 | AX45: 0 | AY45: 0 | AZ45: 0
A46: Garsland | B46: Stoorland | C46: GA6 | D46: Braak | E46: 3.0312657 | F46: 0 | H46: 4000 | J46: 6000 | L46: N.A | N46: 6000 | P46: 2000 | R46: 0 | T46: 0 | V46: 0 | X46: 0 | Z46: 0 | AB46: 1000 | AD46: 0 | AF46: 1000 | AH46: 0 | AJ46: 0 | AL46: 0 | AN46: 0 | AP46: 0 | AR46: 0 | AT46: 0 | AV46: 0 | AX46: 0 | AY46: 0 | AZ46: 0
A47: Glenridge | B47: Teerpadland | C47: G7a | D47: Braak | E47: 7.6130991 | F47: 0 | H47: 3000 | J47: 3000 | L47: N.A | N47: 1000 | P47: 0 | R47: 0 | T47: 0 | V47: 0 | X47: 1500 | Z47: 2500 | AB47: 5000 | AD47: 0 | AF47: 4000 | AH47: 1000 | AJ47: 1500 | AL47: 1500 | AN47: 0 | AP47: 0 | AR47: 0 | AT47: 0 | AV47: 0 | AX47: 0 | AY47: 0 | AZ47: 0
A48: Glenridge | B48: Popelierland | C48: G7b | D48: Braak | E48: 1.2286475 | F48: 0 | H48: 3000 | J48: 3000 | L48: N.A | N48: 1000 | P48: 0 | R48: 0 | T48: 0 | V48: 0 | X48: 1500 | Z48: 2500 | AB48: 5000 | AD48: 0 | AF48: 1000 | AH48: 1000 | AJ48: 200 | AL48: 200 | AN48: 0 | AP48: 0 | AR48: 0 | AT48: 0 | AV48: 0 | AX48: 0 | AY48: 0 | AZ48: 0
A49: Glenridge | B49: Noordland | C49: G7c | D49: Braak | E49: 0.79330274 | F49: 0 | H49: 3000 | J49: 3000 | L49: N.A | N49: 1000 | P49: 0 | R49: 0 | T49: 0 | V49: 0 | X49: 1500 | Z49: 2500 | AB49: 5000 | AD49: 0 | AF49: 1000 | AH49: 1000 | AJ49: 500 | AL49: 500 | AN49: 0 | AP49: 0 | AR49: 0 | AT49: 0 | AV49: 15000 | AX49: 0 | AY49: 0 | AZ49: 0
A50: Glenridge | B50: Plantjiesland | C50: G7d | D50: Braak | E50: 8.1720683 | F50: 0 | H50: 3000 | J50: 3000 | L50: N.A | N50: 1000 | P50: 0 | R50: 0 | T50: 0 | V50: 0 | X50: 1500 | Z50: 2500 | AB50: 5000 | AD50: 0 | AF50: 4000 | AH50: 1000 | AJ50: 1000 | AL50: 1000 | AN50: 0 | AP50: 0 | AR50: 0 | AT50: 0 | AV50: 0 | AX50: 0 | AY50: 0 | AZ50: 0
A51: Glenridge | B51: Deur-ry-land | C51: G7e | D51: Braak | E51: 3.2858996 | F51: 0 | H51: 3000 | J51: 3000 | L51: N.A | N51: 1000 | P51: 0 | R51: 0 | T51: 0 | V51: 0 | X51: 1500 | Z51: 2500 | AB51: 5000 | AD51: 0 | AF51: 1000 | AH51: 1000 | AJ51: 2000 | AL51: 2000 | AN51: 0 | AP51: 0 | AR51: 0 | AT51: 0 | AV51: 0 | AX51: 0 | AY51: 0 | AZ51: 0
A52: Glenridge | B52: Puntland | C52: G7f | D52: Braak | E52: 4.258856 | F52: 0 | H52: 3000 | J52: 3000 | L52: N.A | N52: 1000 | P52: 0 | R52: 0 | T52: 0 | V52: 0 | X52: 1500 | Z52: 2500 | AB52: 5000 | AD52: 0 | AF52: 1000 | AH52: 1000 | AJ52: 0 | AL52: 0 | AN52: 0 | AP52: 0 | AR52: 0 | AT52: 0 | AV52: 0 | AX52: 0 | AY52: 0 | AZ52: 0
A53: Biekoes | B53: Donkiekamp | C53: B10 | D53: Braak | E53: 15.962332 | F53: 0 | H53: 0 | J53: 0 | L53: N.A | N53: 0 | P53: 0 | R53: 0 | T53: 5000 | V53: 0 | X53: 0 | Z53: 0 | AB53: 0 | AD53: 0 | AF53: 1000 | AH53: 2000 | AJ53: 2000 | AL53: 0 | AN53: 0 | AP53: 0 | AR53: 0 | AT53: 0 | AV53: 0 | AX53: 0 | AY53: 0 | AZ53: 0
A54: Biekoes | B54: Teen Grasberg | C54: B12 | D54: 2026 | E54: 11.799041 | F54: 0 | H54: 0 | J54: 0 | L54: N.A | N54: 0 | P54: 0 | R54: 0 | T54: 5000 | V54: 0 | X54: 0 | Z54: 0 | AB54: 0 | AD54: 0 | AF54: 0 | AH54: 0 | AJ54: 0 | AL54: 3000 | AN54: 5000 | AP54: 6000 | AR54: 4000 | AT54: 0 | AV54: 0 | AX54: 0 | AY54: 0 | AZ54: 0
A55: Biekoes | B55: Voor Huiskamp | C55: B13 | D55: Braak | E55: 27.417025 | F55: 0 | H55: 0 | J55: 0 | L55: N.A | N55: 0 | P55: 0 | R55: 0 | T55: 5000 | V55: 0 | X55: 0 | Z55: 0 | AB55: 0 | AD55: 0 | AF55: 2000 | AH55: 1000 | AJ55: 0 | AL55: 0 | AN55: 0 | AP55: 0 | AR55: 0 | AT55: 0 | AV55: 0 | AX55: 0 | AY55: 0 | AZ55: 0
A56: Biekoes | B56: Tuinkamp | C56: B14 | D56: 2023 | E56: 8.6880705 | F56: 0 | H56: 0 | J56: 0 | L56: N.A | N56: 0 | P56: 0 | R56: 0 | T56: 0 | V56: 0 | X56: 0 | Z56: 0 | AB56: 0 | AD56: 0 | AF56: 0 | AH56: 0 | AJ56: 0 | AL56: 0 | AN56: 0 | AP56: 0 | AR56: 0 | AT56: 0 | AV56: 2000 | AX56: 3000 | AY56: 0 | AZ56: 0
D57: =SUM(Johan_Brand_Skatting_en_Werklik_3[GEPLANT]) -> 72868 | E57: =SUM(Johan_Brand_Skatting_en_Werklik_3[HEKTAAR]) -> 1049.3503 | H57: =SUM(Johan_Brand_Skatting_en_Werklik_3[2005 OESSKAT]) -> 91000 | J57: =SUM(Johan_Brand_Skatting_en_Werklik_3[2006 OESSKAT]) -> 286500 | L57: =SUM(Johan_Brand_Skatting_en_Werklik_3[2007_OESSKAT]) -> 0 | N57: =SUM(Johan_Brand_Skatting_en_Werklik_3[2008_OESSKAT]) -> 310000 | P57: =SUM(Johan_Brand_Skatting_en_Werklik_3[2009_OESSKAT]) -> 189000 | R57: =SUM(Johan_Brand_Skatting_en_Werklik_3[2010_OESSKAT]) -> 132000 | T57: =SUM(Johan_Brand_Skatting_en_Werklik_3[2011_OESSKAT]) -> 236000 | V57: =SUM(Johan_Brand_Skatting_en_Werklik_3[2012_OESSKAT]) -> 172000 | X57: =SUM(Johan_Brand_Skatting_en_Werklik_3[2013_OESSKAT]) -> 142500 | Z57: =SUM(Johan_Brand_Skatting_en_Werklik_3[2014_OESSKAT]) -> 163500 | AB57: =SUM(Johan_Brand_Skatting_en_Werklik_3[2015_OESSKAT]) -> 202000 | AD57: =SUM(Johan_Brand_Skatting_en_Werklik_3[2016_OESSKAT]) -> 132500 | AF57: =SUM(Johan_Brand_Skatting_en_Werklik_3[2017_OESSKAT]) -> 372800 | AH57: =SUM(Johan_Brand_Skatting_en_Werklik_3[2018_OESSKAT]) -> 216003 | AJ57: =SUM(Johan_Brand_Skatting_en_Werklik_3[2019_OESSKAT]) -> 195200 | AL57: =SUM(Johan_Brand_Skatting_en_Werklik_3[2020_OESSKAT]) -> 209200 | AN57: =SUM(Johan_Brand_Skatting_en_Werklik_3[2021_OESSKAT]) -> 207000 | AP57: =SUM(Johan_Brand_Skatting_en_Werklik_3[2022_OESSKAT]) -> 186000 | AR57: =SUM(Johan_Brand_Skatting_en_Werklik_3[2023_OESSKAT]) -> 120000 | AT57: =SUM(Johan_Brand_Skatting_en_Werklik_3[2024_OESSKAT]) -> 192000 | AV57: =SUM(Johan_Brand_Skatting_en_Werklik_3[2025_OESSKAT]) -> 231700 | AX57: =SUM(Johan_Brand_Skatting_en_Werklik_3[2026_OESSKAT]) -> 178000 | AY57: =SUM(Johan_Brand_Skatting_en_Werklik_3[2027_OESSKAT]) -> 93000 | AZ57: =SUM(Johan_Brand_Skatting_en_Werklik_3[2028_OESSKAT]) -> 34000
A60: PLAASNAAM | B60: LANDNAAM | C60: LANDNO | D60: GEPLANT | E60: HEKTAAR | F60: 2004 OESSKAT | G60: Column 31 | H60: 2005 OESSKAT | I60: Column 32 | J60: 2006 OESSKAT | K60: Column 33 | L60: 2007_OESSKAT | M60: Column 34 | N60: 2008_OESSKAT | O60: Column 35 | P60: 2009_OESSKAT | Q60: Column 36 | R60: 2010_OESSKAT | S60: Column 37 | T60: 2011_OESSKAT | U60: Column 38 | V60: 2012_OESSKAT | W60: Column 39 | X60: 2013_OESSKAT | Y60: Column 40 | Z60: 2014_OESSKAT | AA60: Column 41 | AB60: 2015_OESSKAT | AC60: Column 42 | AD60: 2016_OESSKAT | AE60: Column 43 | AF60: 2017_OESSKAT | AG60: Column 44 | AH60: 2018_OESSKAT | AI60: Column 45 | AJ60: 2019_OESSKAT | AK60: Column 46 | AL60: 2020_OESSKAT | AM60: Column 47 | AN60: 2021_OESSKAT | AO60: Column 48 | AP60: 2022_OESSKAT | AQ60: Column 49 | AR60: 2023_OESSKAT | AS60: Column 50 | AT60: 2024_OESSKAT | AU60: Column 51 | AV60: 2025_OESSKAT | AW60: Column 52 | AX60: 2026_OESSKAT | AY60: 2027_OESSKAT | AZ60: 2028_OESSKAT
A61: Biekoes | B61: Spilpuntkamp | C61: B2 | D61: 2026 | E61: 18.110613 | F61: 0 | H61: 0 | J61: 15000 | L61: N.A | N61: 0 | P61: 0 | R61: 6000 | T61: 1000 | V61: 4000 | X61: 2000 | Z61: 2000 | AB61: 2000 | AD61: 4500 | AF61: 34000 | AH61: 9000 | AJ61: 10000 | AL61: 0 | AN61: 0 | AP61: 15000 | AR61: 0 | AT61: 2000 | AV61: 0 | AX61: 0 | AY61: 2000 | AZ61: 9000
A62: Biekoes | B62: Eerste Land | C62: B1 | D62: 2022 | E62: 21.198753 | F62: 0 | H62: 0 | J62: 0 | L62: N.A | N62: 0 | P62: 0 | R62: 0 | T62: 8000 | V62: 8000 | X62: 8000 | Z62: 6000 | AB62: 0 | AD62: 0 | AF62: 16000 | AH62: 16000 | AJ62: 12000 | AL62: 5000 | AN62: 0 | AP62: 0 | AR62: 0 | AT62: 6000 | AV62: 4000 | AX62: 5000 | AY62: 0 | AZ62: 0
A63: Biekoes | B63: Windpompkamp | C63: B4 | D63: 2026 | E63: 11.609562 | F63: 0 | H63: 0 | J63: 5000 | L63: N.A | N63: 3000 | P63: 2000 | R63: 0 | T63: 0 | V63: 0 | X63: 1000 | Z63: 0 | AB63: 0 | AD63: 0 | AF63: 3000 | AH63: 3000 | AJ63: 2000 | AL63: 2000 | AN63: 0 | AP63: 1000 | AR63: 3000 | AT63: 1000 | AV63: 4000 | AX63: 0 | AY63: 1000 | AZ63: 5000
A64: Cloudskraal | B64: Om Groenvlei | C64: C9 | D64: 2026 | E64: 29.471117 | F64: 0 | H64: 0 | J64: 25000 | L64: N.A | N64: 25000 | P64: 10000 | R64: 0 | T64: 18000 | V64: 18000 | X64: 12000 | Z64: 0 | AB64: 3000 | AD64: 12000 | AF64: 30000 | AH64: 8000 | AJ64: 0 | AL64: 0 | AN64: 3000 | AP64: 3000 | AR64: 9000 | AT64: 15000 | AV64: 15000 | AX64: 0 | AY64: 0 | AZ64: 0
A65: Cloudskraal | B65: Groenvlei | C65: C11 | D65: 2022 | E65: 41.979349 | F65: 24000 | H65: 15000 | J65: 15000 | L65: N.A | N65: 15000 | P65: 25000 | R65: 20000 | T65: 10000 | V65: 5000 | X65: 0 | Z65: 0 | AB65: 30000 | AD65: 15000 | AF65: 20000 | AH65: 10000 | AJ65: 5000 | AL65: 5000 | AN65: 3000 | AP65: 0 | AR65: 0 | AT65: 16000 | AV65: 24000 | AX65: 20000 | AY65: 0 | AZ65: 0
A66: Glenridge | B66: Driehoekkamp | C66: G1 | D66: 2026 | E66: 16.552962 | F66: 12000 | H66: 10000 | J66: 3000 | L66: N.A | N66: 5000 | P66: 5000 | R66: 3000 | T66: 6000 | V66: 0 | X66: 0 | Z66: 0 | AB66: 8000 | AD66: 5000 | AF66: 12000 | AH66: 5000 | AJ66: 2000 | AL66: 7000 | AN66: 12000 | AP66: 5000 | AR66: 0 | AT66: 0 | AV66: 0 | AX66: 0 | AY66: 7000 | AZ66: 0
A67: Glenridge | B67: Vleikamp B | C67: G8 | D67: 2022 | E67: 23.028313 | F67: 1000 | H67: 0 | J67: 25000 | L67: N.A | N67: 9000 | P67: 0 | R67: 0 | T67: 0 | V67: 0 | X67: 0 | Z67: 0 | AB67: 0 | AD67: 0 | AF67: 5000 | AH67: 3 | AJ67: 8000 | AL67: 7000 | AN67: 7000 | AP67: 7000 | AR67: 0 | AT67: 12000 | AV67: 10000 | AX67: 5000 | AY67: 0 | AZ67: 0
A68: Glenridge | B68: Baken se land | C68: G3 | D68: 2025 | E68: 53.627997 | F68: 0 | H68: 0 | J68: 0 | L68: N.A | N68: 10000 | P68: 10000 | R68: 0 | T68: 20000 | V68: 20000 | X68: 15000 | Z68: 10000 | AB68: 0 | AD68: 0 | AF68: 10000 | AH68: 25000 | AJ68: 30000 | AL68: 20000 | AN68: 0 | AP68: 27000 | AR68: 30000 | AT68: 26000 | AV68: 0 | AX68: 0 | AY68: 0 | AZ68: 0
A69: Glenridge | B69: Sandkamp | C69: G4 | D69: 2022 | E69: 52.153611 | F69: 7000 | H69: 0 | J69: 10000 | L69: N.A | N69: 18000 | P69: 0 | R69: 0 | T69: 25000 | V69: 20000 | X69: 15000 | Z69: 10000 | AB69: 0 | AD69: 0 | AF69: 25000 | AH69: 20000 | AJ69: 6000 | AL69: 6000 | AN69: 8000 | AP69: 0 | AR69: 0 | AT69: 31000 | AV69: 31000 | AX69: 15000 | AY69: 10000 | AZ69: 0
A70: Glenridge | B70: By Resovoir | C70: G14 | D70: 2026 | E70: 6.7325786 | F70: 1000 | H70: 1000 | J70: 0 | L70: N.A | N70: 0 | P70: 0 | R70: 0 | T70: 0 | V70: 0 | X70: 3000 | Z70: 3000 | AB70: 3000 | AD70: 0 | AF70: 0 | AH70: 0 | AJ70: 0 | AL70: 1000 | AN70: 3000 | AP70: 0 | AR70: 0 | AT70: 0 | AV70: 3500 | AX70: 3500 | AY70: 2000 | AZ70: 0
A71: Glenridge | B71: Teen Pierre | C71: G13 | D71: 2026 | E71: 21.956941 | F71: 0 | H71: 0 | J71: 15000 | L71: N.A | N71: 11000 | P71: 11000 | R71: 0 | T71: 11000 | V71: 11000 | X71: 15000 | Z71: 11000 | AB71: 6000 | AD71: 0 | AF71: 4000 | AH71: 8000 | AJ71: 6000 | AL71: 4000 | AN71: 2000 | AP71: 11000 | AR71: 6000 | AT71: 7000 | AV71: 4000 | AX71: 0 | AY71: 0 | AZ71: 0
A72: Glenridge | B72: Bokant Bloekoms | C72: G11 | D72: Braak | E72: 14.3042 | F72: 6000 | H72: 2000 | J72: 1000 | L72: N.A | N72: 0 | P72: 0 | R72: 0 | T72: 0 | V72: 0 | X72: 6000 | Z72: 8000 | AB72: 3000 | AD72: 1500 | AF72: 0 | AH72: 0 | AJ72: 2000 | AL72: 2000 | AN72: 4000 | AP72: 5000 | AR72: 0 | AT72: 0 | AV72: 0 | AX72: 0 | AY72: 0 | AZ72: 0
A73: Cloudskraal | B73: Teen Kromvlei | C73: C1 | D73: 2023 | E73: 30.751305 | F73: 0 | H73: 0 | J73: 0 | L73: N.A | N73: 4000 | P73: 4000 | R73: 0 | T73: 0 | V73: 0 | X73: 4000 | Z73: 3000 | AB73: 0 | AD73: 0 | AF73: 2000 | AH73: 6000 | AJ73: 2000 | AL73: 3000 | AN73: 7500 | AP73: 0 | AR73: 0 | AT73: 0 | AV73: 13000 | AX73: 21000 | AY73: 0 | AZ73: 0
A74: Cloudskraal | B74: Agter Pomp | C74: C5 | D74: 2024 | E74: 32.66615 | F74: 0 | H74: 0 | J74: 30000 | L74: N.A | N74: 22000 | P74: 5000 | R74: 12000 | T74: 18000 | V74: 18000 | X74: 0 | Z74: 0 | AB74: 3000 | AD74: 15000 | AF74: 36000 | AH74: 8000 | AJ74: 0 | AL74: 3000 | AN74: 7500 | AP74: 10000 | AR74: 6000 | AT74: 0 | AV74: 0 | AX74: 15000 | AY74: 25000 | AZ74: 0
A75: Cloudskraal | B75: Links van vlei | C75: C6 | D75: 2024 | E75: 8.5061747 | F75: 0 | H75: 0 | J75: 6000 | L75: N.A | N75: 2500 | P75: 1000 | R75: 4000 | T75: 3000 | V75: 0 | X75: 0 | Z75: 0 | AB75: 1000 | AD75: 3500 | AF75: 3500 | AH75: 2000 | AJ75: 0 | AL75: 2000 | AN75: 3000 | AP75: 3000 | AR75: 1000 | AT75: 0 | AV75: 0 | AX75: 2500 | AY75: 6000 | AZ75: 0
A76: Cloudskraal | B76: Uilklip | C76: C13 | D76: 2027 | E76: 27.339304 | F76: 3000 | H76: 0 | J76: 0 | L76: N.A | N76: 12000 | P76: 10000 | R76: 0 | T76: 0 | V76: 15000 | X76: 15000 | Z76: 4000 | AB76: 0 | AD76: 0 | AF76: 3000 | AH76: 12000 | AJ76: 10000 | AL76: 7000 | AN76: 9000 | AP76: 0 | AR76: 0 | AT76: 10000 | AV76: 10000 | AX76: 0 | AY76: 0 | AZ76: 0
A77: Cloudskraal | B77: Heelagter | C77: C19 | D77: 2023 | E77: 33.530577 | F77: 0 | H77: 0 | J77: 0 | L77: N.A | N77: 24000 | P77: 5000 | R77: 20000 | T77: 20000 | V77: 15000 | X77: 6000 | Z77: 9000 | AB77: 14000 | AD77: 7000 | AF77: 7000 | AH77: 0 | AJ77: 0 | AL77: 25000 | AN77: 15000 | AP77: 12000 | AR77: 0 | AT77: 0 | AV77: 22000 | AX77: 20000 | AY77: 15000 | AZ77: 0
A78: Cloudskraal | B78: Tweede Spilpunt | C78: C18 | D78: 2025 | E78: 21.68274 | F78: 2000 | H78: 0 | J78: 0 | L78: N.A | N78: 0 | P78: 3000 | R78: 11000 | T78: 11000 | V78: 6000 | X78: 0 | Z78: 0 | AB78: 0 | AD78: 0 | AF78: 6000 | AH78: 8000 | AJ78: 6000 | AL78: 0 | AN78: 3000 | AP78: 7000 | AR78: 7000 | AT78: 0 | AV78: 0 | AX78: 0 | AY78: 0 | AZ78: 0
A79: Cloudskraal | B79: By Begraafplaas | C79: C16 | D79: Braak | E79: 8.7379009 | F79: 6000 | H79: 5000 | J79: 4500 | L79: N.A | N79: 0 | P79: 0 | R79: 0 | T79: 0 | V79: 0 | X79: 0 | Z79: 0 | AB79: 0 | AD79: 0 | AF79: 0 | AH79: 0 | AJ79: 1000 | AL79: 0 | AN79: 0 | AP79: 0 | AR79: 0 | AT79: 0 | AV79: 0 | AX79: 0 | AY79: 0 | AZ79: 0
A80: Cloudskraal | B80: Volkshuise | C80: C15 | D80: 2022 | E80: 7.293002 | F80: 1000 | H80: 1000 | J80: 3000 | L80: N.A | N80: 0 | P80: 0 | R80: 0 | T80: 0 | V80: 0 | X80: 0 | Z80: 0 | AB80: 1000 | AD80: 2500 | AF80: 3500 | AH80: 1000 | AJ80: 2000 | AL80: 0 | AN80: 0 | AP80: 2000 | AR80: 0 | AT80: 2000 | AV80: 2000 | AX80: 1000 | AY80: 0 | AZ80: 0
A81: Cloudskraal | B81: Eerste Spilpunt | C81: C8 | D81: 2022 | E81: 21.626902 | F81: 2500 | H81: 0 | J81: 15000 | L81: N.A | N81: 8000 | P81: 0 | R81: 0 | T81: 0 | V81: 0 | X81: 0 | Z81: 12000 | AB81: 8000 | AD81: 4000 | AF81: 0 | AH81: 0 | AJ81: 6000 | AL81: 15000 | AN81: 15000 | AP81: 0 | AR81: 0 | AT81: 8000 | AV81: 12000 | AX81: 8000 | AY81: 0 | AZ81: 0
A82: Cloudskraal | B82: Pleisterbosrug | C82: C3 | D82: 2021 | E82: 31.037026 | F82: 0 | H82: 0 | J82: 8000 | L82: N.A | N82: 12000 | P82: 4000 | R82: 0 | T82: 0 | V82: 0 | X82: 7000 | Z82: 18000 | AB82: 10000 | AD82: 8000 | AF82: 3000 | AH82: 3000 | AJ82: 6000 | AL82: 6000 | AN82: 0 | AP82: 0 | AR82: 10000 | AT82: 18000 | AV82: 18000 | AX82: 10000 | AY82: 0 | AZ82: 0
A83: Cloudskraal | B83: Hardekop | C83: C2 | D83: 2024 | E83: 21.015682 | F83: 5000 | H83: 5000 | J83: 5000 | L83: N.A | N83: 15000 | P83: 15000 | R83: 10000 | T83: 8000 | V83: 0 | X83: 0 | Z83: 8000 | AB83: 16000 | AD83: 6000 | AF83: 5000 | AH83: 0 | AJ83: 0 | AL83: 3000 | AN83: 15000 | AP83: 11000 | AR83: 5000 | AT83: 0 | AV83: 3000 | AX83: 12000 | AY83: 12000 | AZ83: 0
A84: Glenridge | B84: Langland by Bloekoms | C84: G9 | D84: 2026 | E84: 18.753786 | F84: 0 | H84: 0 | J84: 0 | L84: N.A | N84: 3000 | P84: 2000 | R84: 0 | T84: 0 | V84: 0 | X84: 4000 | Z84: 10000 | AB84: 10000 | AD84: 3000 | AF84: 0 | AH84: 0 | AJ84: 3000 | AL84: 5000 | AN84: 6000 | AP84: 8000 | AR84: 4000 | AT84: 0 | AV84: 0 | AX84: 0 | AY84: 0 | AZ84: 0
A85: Glenridge | B85: Garskamp | C85: G10 | D85: Braak | E85: 10.953934 | F85: 5000 | H85: 0 | J85: 0 | L85: N.A | N85: 1500 | P85: 1000 | R85: 0 | T85: 0 | V85: 0 | X85: 2500 | Z85: 2500 | AB85: 0 | AD85: 0 | AF85: 0 | AH85: 0 | AJ85: 0 | AL85: 1000 | AN85: 0 | AP85: 0 | AR85: 0 | AT85: 0 | AV85: 0 | AX85: 0 | AY85: 0 | AZ85: 0
A86: Glenridge | B86: Klipland | C86: G12 | D86: Braak | E86: 4.6495434 | F86: 5000 | H86: 1000 | J86: 0 | L86: N.A | N86: 0 | P86: 0 | R86: 0 | T86: 0 | V86: 0 | X86: 2000 | Z86: 2000 | AB86: 0 | AD86: 0 | AF86: 0 | AH86: 0 | AJ86: 0 | AL86: 0 | AN86: 0 | AP86: 0 | AR86: 0 | AT86: 0 | AV86: 0 | AX86: 0 | AY86: 0 | AZ86: 0
A87: Garsland | B87: Denneboomland | C87: GA4 | D87: Braak | E87: 2.2378144 | F87: 0 | H87: 0 | J87: 0 | L87: N.A | N87: 0 | P87: 0 | R87: 0 | T87: 0 | V87: 0 | X87: 0 | Z87: 0 | AB87: 0 | AD87: 0 | AF87: 0 | AH87: 0 | AJ87: 0 | AL87: 0 | AN87: 0 | AP87: 0 | AR87: 0 | AT87: 0 | AV87: 0 | AX87: 0 | AY87: 0 | AZ87: 0
A88: Garsland | B88: Driehoekkamp | C88: GA2 | D88: 2025 | E88: 9.3738299 | F88: 0 | H88: 4000 | J88: 9000 | L88: N.A | N88: 6000 | P88: 2000 | R88: 0 | T88: 5000 | V88: 6000 | X88: 2000 | Z88: 0 | AB88: 1000 | AD88: 2500 | AF88: 6000 | AH88: 2000 | AJ88: 1000 | AL88: 5000 | AN88: 6000 | AP88: 3000 | AR88: 1000 | AT88: 0 | AV88: 0 | AX88: 0 | AY88: 0 | AZ88: 0
A89: Garsland | B89: Spilpuntland | C89: GA3 | D89: 2023 | E89: 14.306519 | F89: 0 | H89: 0 | J89: 7000 | L89: N.A | N89: 10000 | P89: 2000 | R89: 0 | T89: 8000 | V89: 5000 | X89: 2000 | Z89: 0 | AB89: 0 | AD89: 0 | AF89: 7000 | AH89: 5000 | AJ89: 4500 | AL89: 2000 | AN89: 5000 | AP89: 0 | AR89: 0 | AT89: 0 | AV89: 4200 | AX89: 6000 | AY89: 3000 | AZ89: 0
A90: Glenridge | B90: Vleikamp A | C90: G2 | D90: 2026 | E90: 21.868015 | F90: 1000 | H90: 0 | J90: 25000 | L90: N.A | N90: 9000 | P90: 0 | R90: 0 | T90: 10000 | V90: 8000 | X90: 2000 | Z90: 0 | AB90: 5000 | AD90: 5000 | AF90: 5000 | AH90: 2000 | AJ90: 3000 | AL90: 8000 | AN90: 12000 | AP90: 0 | AR90: 0 | AT90: 0 | AV90: 0 | AX90: 0 | AY90: 0 | AZ90: 0
A91: Cloudskraal | B91: Regs van vlei | C91: C7 | D91: 2025 | E91: 27.682425 | F91: 0 | H91: 6000 | J91: 8000 | L91: N.A | N91: 0 | P91: 15000 | R91: 15000 | T91: 15000 | V91: 8000 | X91: 0 | Z91: 0 | AB91: 3000 | AD91: 6000 | AF91: 12000 | AH91: 8000 | AJ91: 0 | AL91: 3000 | AN91: 12000 | AP91: 18000 | AR91: 9000 | AT91: 0 | AV91: 0 | AX91: 0 | AY91: 0 | AZ91: 0
A92: Glenridge | B92: Roosklawerkamp | C92: G6 | D92: 2027 | E92: 66.66814 | F92: 0 | H92: 0 | J92: 0 | L92: N.A | N92: 0 | P92: 0 | R92: 0 | T92: 0 | V92: 0 | X92: 10000 | Z92: 25000 | AB92: 15000 | AD92: 0 | AF92: 0 | AH92: 0 | AJ92: 0 | AL92: 10000 | AN92: 10000 | AP92: 20000 | AR92: 15000 | AT92: 12000 | AV92: 0 | AX92: 0 | AY92: 0 | AZ92: 0
A93: Cloudskraal | B93: Onderdam | C93: C17 | D93: 2022 | E93: 16.8566 | F93: 3000 | H93: 3000 | J93: 0 | L93: N.A | N93: 0 | P93: 0 | R93: 0 | T93: 0 | V93: 0 | X93: 0 | Z93: 0 | AB93: 6000 | AD93: 5000 | AF93: 7000 | AH93: 3000 | AJ93: 1000 | AL93: 6000 | AN93: 12000 | AP93: 0 | AR93: 0 | AT93: 7000 | AV93: 5000 | AX93: 2000 | AY93: 0 | AZ93: 0
A94: Cloudskraal | B94: Langland | C94: C12 | D94: 2023 | E94: 20.644499 | F94: 12000 | H94: 8000 | J94: 7000 | L94: N.A | N94: 16000 | P94: 10000 | R94: 7000 | T94: 10000 | V94: 5000 | X94: 0 | Z94: 0 | AB94: 8000 | AD94: 8000 | AF94: 5000 | AH94: 3000 | AJ94: 3000 | AL94: 8000 | AN94: 12000 | AP94: 8000 | AR94: 0 | AT94: 0 | AV94: 8000 | AX94: 5000 | AY94: 5000 | AZ94: 0
A95: Biekoes | B95: Hardekop | C95: B8 | D95: 2026 | E95: 34.192859 | F95: 0 | H95: 0 | J95: 0 | L95: N.A | N95: 0 | P95: 0 | R95: 0 | T95: 0 | V95: 0 | X95: 0 | Z95: 0 | AB95: 0 | AD95: 0 | AF95: 13000 | AH95: 6000 | AJ95: 10000 | AL95: 4000 | AN95: 0 | AP95: 2000 | AR95: 6000 | AT95: 7500 | AV95: 10000 | AX95: 0 | AY95: 5000 | AZ95: 20000
A96: Biekoes | B96: Bokant Dam | C96: B6 | D96: 2023 | E96: 42.898925 | F96: 0 | H96: 0 | J96: 0 | L96: N.A | N96: 12000 | P96: 10000 | R96: 5000 | T96: 4000 | V96: 0 | X96: 0 | Z96: 0 | AB96: 0 | AD96: 0 | AF96: 25000 | AH96: 12000 | AJ96: 20000 | AL96: 8000 | AN96: 0 | AP96: 0 | AR96: 0 | AT96: 0 | AV96: 0 | AX96: 12000 | AY96: 0 | AZ96: 0
A97: Biekoes | B97: Latboskamp | C97: B7 | D97: 2021 | E97: 22.958092 | F97: 0 | H97: 0 | J97: 0 | L97: N.A | N97: 6000 | P97: 8000 | R97: 7000 | T97: 3000 | V97: 0 | X97: 0 | Z97: 0 | AB97: 12000 | AD97: 0 | AF97: 12000 | AH97: 10000 | AJ97: 8000 | AL97: 6000 | AN97: 0 | AP97: 2000 | AR97: 4000 | AT97: 4000 | AV97: 4000 | AX97: 4000 | AY97: 0 | AZ97: 0
A98: Biekoes | B98: Agter Huiskamp | C98: B11 | D98: Braak | E98: 15.497613 | F98: 0 | H98: 0 | J98: 0 | L98: N.A | N98: 6000 | P98: 8000 | R98: 7000 | T98: 3000 | V98: 0 | X98: 0 | Z98: 0 | AB98: 0 | AD98: 0 | AF98: 10000 | AH98: 2000 | AJ98: 0 | AL98: 0 | AN98: 0 | AP98: 0 | AR98: 0 | AT98: 0 | AV98: 0 | AX98: 0 | AY98: 0 | AZ98: 0
A99: Biekoes | B99: Stoorkamp | C99: B9 | D99: 2026 | E99: 35.395201 | F99: 0 | H99: 0 | J99: 0 | L99: N.A | N99: 12000 | P99: 10000 | R99: 5000 | T99: 4000 | V99: 0 | X99: 0 | Z99: 0 | AB99: 0 | AD99: 0 | AF99: 0 | AH99: 0 | AJ99: 7000 | AL99: 8000 | AN99: 5000 | AP99: 0 | AR99: 0 | AT99: 0 | AV99: 0 | AX99: 0 | AY99: 0 | AZ99: 0
A100: Biekoes | B100: Straatklip | C100: B3 | D100: 2022 | E100: 17.032996 | F100: 0 | H100: 0 | J100: 9000 | L100: N.A | N100: 9000 | P100: 5000 | R100: 0 | T100: 0 | V100: 0 | X100: 0 | Z100: 5000 | AB100: 2000 | AD100: 12000 | AF100: 17300 | AH100: 4000 | AJ100: 5000 | AL100: 0 | AN100: 0 | AP100: 0 | AR100: 0 | AT100: 7500 | AV100: 8000 | AX100: 8000 | AY100: 0 | AZ100: 0
A101: Garsland | B101: Huiskamp | C101: GA5 | D101: Braak | E101: 5.9436036 | F101: 0 | H101: 4000 | J101: 6000 | L101: N.A | N101: 6000 | P101: 2000 | R101: 0 | T101: 0 | V101: 0 | X101: 0 | Z101: 0 | AB101: 0 | AD101: 3500 | AF101: 1500 | AH101: 3000 | AJ101: 4500 | AL101: 4000 | AN101: 2500 | AP101: 0 | AR101: 0 | AT101: 0 | AV101: 0 | AX101: 0 | AY101: 0 | AZ101: 0
A102: Garsland | B102: Noordkamp | C102: GA1 | D102: Braak | E102: 14.273504 | F102: 0 | H102: 4000 | J102: 6000 | L102: N.A | N102: 6000 | P102: 2000 | R102: 0 | T102: 0 | V102: 0 | X102: 0 | Z102: 0 | AB102: 1000 | AD102: 3500 | AF102: 8000 | AH102: 3000 | AJ102: 2000 | AL102: 0 | AN102: 2500 | AP102: 0 | AR102: 0 | AT102: 0 | AV102: 0 | AX102: 0 | AY102: 0 | AZ102: 0
...
